Workbook

Sheet Notes and calculations
B3: investment | C3: =SUM('2BAS'!C:C) -> 0
B4: v1cap | C4: =SUM('1CAP'!B2:B34) -> 204902.31
B6: Capital stock | C6: =C4/F6 -> 1366015.4 | E6: Gross | F6: 0.15
B8: rorc | C8: =(C4-C3)/C6 -> 0.15
B10: Depreciation
B11: I want a long run growth of: | C11: 0.03
C13: =(C6+C3)-(C6*(1+C11)) -> -40980.461
B15: Depreciation rate | C15: =C13/C6 -> -0.03

Sheet COM
A1: Value
A2: AG
A3: MIN
A4: FBT
A5: TEX
A6: LEATHER
A7: WOOD
A8: PPP
A9: PC
A10: CHM
A11: RUBBER
A12: NMM
... A34: DWE

Sheet IND
A1: Value
A2: AG
A3: MIN
A4: FBT
A5: TEX
A6: LEATHER
A7: WOOD
A8: PPP
A9: PC
A10: CHM
A11: RUBBER
A12: NMM
... A34: DWE

Sheet OCC
A1: Value
A2: EMIRATI
A3: MIGRANTHH
A4: MIGRANTCOMB
A5: COMMUTING

Sheet LELAS
A1: OCC | B1: Value
A2: EMIRATI | B2: 0.15
A3: MIGRANTHH | B3: 0.3
A4: MIGRANTCOMB | B4: 0.3
A5: COMMUTING | B5: 0.6

Sheet 1BAS
A1: COM | B1: SRC | C1: IND | D1: Value
A2: AG | B2: dom | C2: AG | D2: 9.8941912
A3: MIN | B3: dom | C3: AG | D3: 0
A4: FBT | B4: dom | C4: AG | D4: 157.79694
A5: TEX | B5: dom | C5: AG | D5: 1.256591
A6: LEATHER | B6: dom | C6: AG | D6: 0
A7: WOOD | B7: dom | C7: AG | D7: 0
A8: PPP | B8: dom | C8: AG | D8: 0
A9: PC | B9: dom | C9: AG | D9: 13.401128
A10: CHM | B10: dom | C10: AG | D10: 1.3170773
A11: RUBBER | B11: dom | C11: AG | D11: 0
A12: NMM | B12: dom | C12: AG | D12: 0
A13: METAL | B13: dom | C13: AG | D13: 0
... A2179: DWE | B2179: imp | C2179: DWE | D2179: 0

Sheet VCAPSTOCK Calcs
A1: Value | I1: IND | J1: Value | L1: Check | M1: =A2-SUM(J2:J34) -> 0 | O1: IND | P1: Value
A2: 1640115.4 | I2: =O2 -> AG | J2: =$A$2*Q2 -> 3316.3926 | O2: AG | P2: ='1CAP'!B2 -> 414.32237 | Q2: =P2/SUM($P$2:$P$34) -> 0.0020220483 | R2: dom
I3: =O3 -> MIN | J3: =$A$2*Q3 -> 58883.387 | O3: MIN | P3: ='1CAP'!B3 -> 7356.3983 | Q3: =P3/SUM($P$2:$P$34) -> 0.035901979 | R3: imp
I4: =O4 -> FBT | J4: =$A$2*Q4 -> 27209.435 | O4: FBT | P4: ='1CAP'!B4 -> 3399.3194 | Q4: =P4/SUM($P$2:$P$34) -> 0.016589952
I5: =O5 -> TEX | J5: =$A$2*Q5 -> 6503.4546 | O5: TEX | P5: ='1CAP'!B5 -> 812.48725 | Q5: =P5/SUM($P$2:$P$34) -> 0.0039652421
I6: =O6 -> LEATHER | J6: =$A$2*Q6 -> 30.501796 | O6: LEATHER | P6: ='1CAP'!B6 -> 3.8106395 | Q6: =P6/SUM($P$2:$P$34) -> 1.8597348e-05
I7: =O7 -> WOOD | J7: =$A$2*Q7 -> 2462.7354 | O7: WOOD | P7: ='1CAP'!B7 -> 307.67358 | Q7: =P7/SUM($P$2:$P$34) -> 0.0015015623
I8: =O8 -> PPP | J8: =$A$2*Q8 -> 7037.1675 | O8: PPP | P8: ='1CAP'!B8 -> 879.16488 | Q8: =P8/SUM($P$2:$P$34) -> 0.0042906539
I9: =O9 -> PC | J9: =$A$2*Q9 -> 15434.082 | O9: PC | P9: ='1CAP'!B9 -> 1928.2052 | Q9: =P9/SUM($P$2:$P$34) -> 0.0094103636
I10: =O10 -> CHM | J10: =$A$2*Q10 -> 19504.804 | O10: CHM | P10: ='1CAP'!B10 -> 2436.7671 | Q10: =P10/SUM($P$2:$P$34) -> 0.011892336
I11: =O11 -> RUBBER | J11: =$A$2*Q11 -> 9624.0055 | O11: RUBBER | P11: ='1CAP'!B11 -> 1202.3428 | Q11: =P11/SUM($P$2:$P$34) -> 0.0058678833
I12: =O12 -> NMM | J12: =$A$2*Q12 -> 6775.9986 | O12: NMM | P12: ='1CAP'!B12 -> 846.53663 | Q12: =P12/SUM($P$2:$P$34) -> 0.0041314158
I13: =O13 -> METAL | J13: =$A$2*Q13 -> 58609.301 | O13: METAL | P13: ='1CAP'!B13 -> 7322.1563 | Q13: =P13/SUM($P$2:$P$34) -> 0.035734865
I14: =O14 -> MACH | J14: =$A$2*Q14 -> 7858.9561 | O14: MACH | P14: ='1CAP'!B14 -> 981.83229 | Q14: =P14/SUM($P$2:$P$34) -> 0.0047917093
I15: =O15 -> ELEC | J15: =$A$2*Q15 -> 5483.8537 | O15: ELEC | P15: ='1CAP'!B15 -> 685.10684 | Q15: =P15/SUM($P$2:$P$34) -> 0.003343578
... I34: =O34 -> DWE | J34: =$A$2*Q34 -> 2.7368838 | O34: DWE | P34: ='1CAP'!B34 -> 0.34192339 | Q34: =P34/SUM($P$2:$P$34) -> 1.6687142e-06

Sheet VCAPSTOCK
A1: IND | B1: Value
A2: AG | B2: 3316.3926
A3: MIN | B3: 58883.387
A4: FBT | B4: 27209.435
A5: TEX | B5: 6503.4546
A6: LEATHER | B6: 30.501796
A7: WOOD | B7: 2462.7354
A8: PPP | B8: 7037.1675
A9: PC | B9: 15434.082
A10: CHM | B10: 19504.804
A11: RUBBER | B11: 9624.0055
A12: NMM | B12: 6775.9986
A13: METAL | B13: 58609.301
... A34: DWE | B34: 2.7368838

Sheet VDEP Calcs
A1: Value | I1: IND | J1: Value | L1: Check | M1: =A2-SUM(J2:J34) -> 0 | O1: IND | P1: Value
A2: 67349.233 | I2: =O2 -> AG | J2: =$A$2*Q2 -> 136.1834 | O2: AG | P2: ='1CAP'!B2 -> 414.32237 | Q2: =P2/SUM($P$2:$P$34) -> 0.0020220483 | R2: dom
I3: =O3 -> MIN | J3: =$A$2*Q3 -> 2417.9708 | O3: MIN | P3: ='1CAP'!B3 -> 7356.3983 | Q3: =P3/SUM($P$2:$P$34) -> 0.035901979 | R3: imp
I4: =O4 -> FBT | J4: =$A$2*Q4 -> 1117.3205 | O4: FBT | P4: ='1CAP'!B4 -> 3399.3194 | Q4: =P4/SUM($P$2:$P$34) -> 0.016589952
I5: =O5 -> TEX | J5: =$A$2*Q5 -> 267.05602 | O5: TEX | P5: ='1CAP'!B5 -> 812.48725 | Q5: =P5/SUM($P$2:$P$34) -> 0.0039652421
I6: =O6 -> LEATHER | J6: =$A$2*Q6 -> 1.2525171 | O6: LEATHER | P6: ='1CAP'!B6 -> 3.8106395 | Q6: =P6/SUM($P$2:$P$34) -> 1.8597348e-05
I7: =O7 -> WOOD | J7: =$A$2*Q7 -> 101.12907 | O7: WOOD | P7: ='1CAP'!B7 -> 307.67358 | Q7: =P7/SUM($P$2:$P$34) -> 0.0015015623
I8: =O8 -> PPP | J8: =$A$2*Q8 -> 288.97225 | O8: PPP | P8: ='1CAP'!B8 -> 879.16488 | Q8: =P8/SUM($P$2:$P$34) -> 0.0042906539
I9: =O9 -> PC | J9: =$A$2*Q9 -> 633.78077 | O9: PC | P9: ='1CAP'!B9 -> 1928.2052 | Q9: =P9/SUM($P$2:$P$34) -> 0.0094103636
I10: =O10 -> CHM | J10: =$A$2*Q10 -> 800.93974 | O10: CHM | P10: ='1CAP'!B10 -> 2436.7671 | Q10: =P10/SUM($P$2:$P$34) -> 0.011892336
I11: =O11 -> RUBBER | J11: =$A$2*Q11 -> 395.19744 | O11: RUBBER | P11: ='1CAP'!B11 -> 1202.3428 | Q11: =P11/SUM($P$2:$P$34) -> 0.0058678833
I12: =O12 -> NMM | J12: =$A$2*Q12 -> 278.24769 | O12: NMM | P12: ='1CAP'!B12 -> 846.53663 | Q12: =P12/SUM($P$2:$P$34) -> 0.0041314158
I13: =O13 -> METAL | J13: =$A$2*Q13 -> 2406.7158 | O13: METAL | P13: ='1CAP'!B13 -> 7322.1563 | Q13: =P13/SUM($P$2:$P$34) -> 0.035734865
I14: =O14 -> MACH | J14: =$A$2*Q14 -> 322.71795 | O14: MACH | P14: ='1CAP'!B14 -> 981.83229 | Q14: =P14/SUM($P$2:$P$34) -> 0.0047917093
I15: =O15 -> ELEC | J15: =$A$2*Q15 -> 225.18741 | O15: ELEC | P15: ='1CAP'!B15 -> 685.10684 | Q15: =P15/SUM($P$2:$P$34) -> 0.003343578
... I34: =O34 -> DWE | J34: =$A$2*Q34 -> 0.11238662 | O34: DWE | P34: ='1CAP'!B34 -> 0.34192339 | Q34: =P34/SUM($P$2:$P$34) -> 1.6687142e-06

Sheet VDEP
A1: IND | B1: Value
A2: AG | B2: 136.1834
A3: MIN | B3: 2417.9708
A4: FBT | B4: 1117.3205
A5: TEX | B5: 267.05602
A6: LEATHER | B6: 1.2525171
A7: WOOD | B7: 101.12907
A8: PPP | B8: 288.97225
A9: PC | B9: 633.78077
A10: CHM | B10: 800.93974
A11: RUBBER | B11: 395.19744
A12: NMM | B12: 278.24769
A13: METAL | B13: 2406.7158
... A34: DWE | B34: 0.11238662

Sheet 2BAS
A1: COM | B1: SRC | C1: IND | D1: Value
A2: AG | B2: dom | C2: AG | D2: 0.045862834
A3: MIN | B3: dom | C3: AG | D3: 0.080003963
A4: FBT | B4: dom | C4: AG | D4: 0.13470983
A5: TEX | B5: dom | C5: AG | D5: 0.70168398
A6: LEATHER | B6: dom | C6: AG | D6: 0.0049789556
A7: WOOD | B7: dom | C7: AG | D7: 0.030650387
A8: PPP | B8: dom | C8: AG | D8: 0.61348653
A9: PC | B9: dom | C9: AG | D9: 0.093483475
A10: CHM | B10: dom | C10: AG | D10: 0.5821407
A11: RUBBER | B11: dom | C11: AG | D11: 0.91128513
A12: NMM | B12: dom | C12: AG | D12: 0.8441924
A13: METAL | B13: dom | C13: AG | D13: 2.4691168
... A2179: DWE | B2179: imp | C2179: DWE | D2179: 1e-07

Sheet 3BAS
A1: COM | B1: SRC | C1: Value
A2: AG | B2: dom | C2: 188.42553
A3: MIN | B3: dom | C3: 39.022698
A4: FBT | B4: dom | C4: 3252.1205
A5: TEX | B5: dom | C5: 354.347
A6: LEATHER | B6: dom | C6: 3.900226
A7: WOOD | B7: dom | C7: 1e-07
A8: PPP | B8: dom | C8: 125.19658
A9: PC | B9: dom | C9: 661.44051
A10: CHM | B10: dom | C10: 527.86509
A11: RUBBER | B11: dom | C11: 2.6051403
A12: NMM | B12: dom | C12: 50.778097
A13: METAL | B13: dom | C13: 22.327324
... A67: DWE | B67: imp | C67: 1e-07

Sheet 4BAS
A1: COM | B1: Value
A2: AG | B2: 13478.352
A3: MIN | B3: 125317.36
A4: FBT | B4: 40267.725
A5: TEX | B5: 18250.608
A6: LEATHER | B6: 11177.055
A7: WOOD | B7: 2027.6278
A8: PPP | B8: 3806.5156
A9: PC | B9: 23605.032
A10: CHM | B10: 44799.938
A11: RUBBER | B11: 11455.931
A12: NMM | B12: 4728.6533
A13: METAL | B13: 129405.85
... A34: DWE | B34: 1e-08

Sheet 5BAS
A1: COM | B1: SRC | C1: Value
A2: AG | B2: dom | C2: 0
A3: MIN | B3: dom | C3: 0
A4: FBT | B4: dom | C4: 0
A5: TEX | B5: dom | C5: 0
A6: LEATHER | B6: dom | C6: 0
A7: WOOD | B7: dom | C7: 0
A8: PPP | B8: dom | C8: 0
A9: PC | B9: dom | C9: 0
A10: CHM | B10: dom | C10: 0
A11: RUBBER | B11: dom | C11: 0
A12: NMM | B12: dom | C12: 0
A13: METAL | B13: dom | C13: 0
... A67: DWE | B67: imp | C67: 0

Sheet 6BAS
A1: COM | B1: SRC | C1: Value
A2: AG | B2: dom | C2: 0
A3: MIN | B3: dom | C3: 0
A4: FBT | B4: dom | C4: 0
A5: TEX | B5: dom | C5: 0
A6: LEATHER | B6: dom | C6: 0
A7: WOOD | B7: dom | C7: 0
A8: PPP | B8: dom | C8: 0
A9: PC | B9: dom | C9: 0
A10: CHM | B10: dom | C10: 0
A11: RUBBER | B11: dom | C11: 0
A12: NMM | B12: dom | C12: 0
A13: METAL | B13: dom | C13: 0
... A67: DWE | B67: imp | C67: 0

Sheet 1TAX
A1: COM | B1: SRC | C1: IND | D1: Value
A2: AG | B2: dom | C2: AG | D2: 0
A3: MIN | B3: dom | C3: AG | D3: 0
A4: FBT | B4: dom | C4: AG | D4: 0
A5: TEX | B5: dom | C5: AG | D5: 0
A6: LEATHER | B6: dom | C6: AG | D6: 0
A7: WOOD | B7: dom | C7: AG | D7: 0
A8: PPP | B8: dom | C8: AG | D8: 0
A9: PC | B9: dom | C9: AG | D9: 0
A10: CHM | B10: dom | C10: AG | D10: 0
A11: RUBBER | B11: dom | C11: AG | D11: 0
A12: NMM | B12: dom | C12: AG | D12: 0
A13: METAL | B13: dom | C13: AG | D13: 0
... A2179: DWE | B2179: imp | C2179: DWE | D2179: 0

Sheet 2TAX
A1: COM | B1: SRC | C1: IND | D1: Value
A2: AG | B2: dom | C2: AG | D2: 0
A3: MIN | B3: dom | C3: AG | D3: 0
A4: FBT | B4: dom | C4: AG | D4: 0
A5: TEX | B5: dom | C5: AG | D5: 0
A6: LEATHER | B6: dom | C6: AG | D6: 0
A7: WOOD | B7: dom | C7: AG | D7: 0
A8: PPP | B8: dom | C8: AG | D8: 0
A9: PC | B9: dom | C9: AG | D9: 0
A10: CHM | B10: dom | C10: AG | D10: 0
A11: RUBBER | B11: dom | C11: AG | D11: 0
A12: NMM | B12: dom | C12: AG | D12: 0
A13: METAL | B13: dom | C13: AG | D13: 0
... A2179: DWE | B2179: imp | C2179: DWE | D2179: 0

Sheet 3TAX
A1: COM | B1: SRC | C1: Value
A2: AG | B2: dom | C2: 0
A3: MIN | B3: dom | C3: 0
A4: FBT | B4: dom | C4: 0
A5: TEX | B5: dom | C5: 0
A6: LEATHER | B6: dom | C6: 0
A7: WOOD | B7: dom | C7: 0
A8: PPP | B8: dom | C8: 0
A9: PC | B9: dom | C9: 0
A10: CHM | B10: dom | C10: 0
A11: RUBBER | B11: dom | C11: 0
A12: NMM | B12: dom | C12: 0
A13: METAL | B13: dom | C13: 0
... A67: DWE | B67: imp | C67: 0

Sheet 4TAX
A1: COM | B1: Value
A2: AG | B2: 0
A3: MIN | B3: 0
A4: FBT | B4: 0
A5: TEX | B5: 0
A6: LEATHER | B6: 0
A7: WOOD | B7: 0
A8: PPP | B8: 0
A9: PC | B9: 0
A10: CHM | B10: 0
A11: RUBBER | B11: 0
A12: NMM | B12: 0
A13: METAL | B13: 0
... A34: DWE | B34: 0

Sheet 5TAX
A1: COM | B1: SRC | C1: Value
A2: AG | B2: dom | C2: 0
A3: MIN | B3: dom | C3: 0
A4: FBT | B4: dom | C4: 0
A5: TEX | B5: dom | C5: 0
A6: LEATHER | B6: dom | C6: 0
A7: WOOD | B7: dom | C7: 0
A8: PPP | B8: dom | C8: 0
A9: PC | B9: dom | C9: 0
A10: CHM | B10: dom | C10: 0
A11: RUBBER | B11: dom | C11: 0
A12: NMM | B12: dom | C12: 0
A13: METAL | B13: dom | C13: 0
... A67: DWE | B67: imp | C67: 0

Sheet 1CAP
A1: IND | B1: Value
A2: AG | B2: 414.32237
A3: MIN | B3: 7356.3983
A4: FBT | B4: 3399.3194
A5: TEX | B5: 812.48725
A6: LEATHER | B6: 3.8106395
A7: WOOD | B7: 307.67358
A8: PPP | B8: 879.16488
A9: PC | B9: 1928.2052
A10: CHM | B10: 2436.7671
A11: RUBBER | B11: 1202.3428
A12: NMM | B12: 846.53663
A13: METAL | B13: 7322.1563
... A34: DWE | B34: 0.34192339

Sheet 1LND
A1: IND | B1: Value
A2: AG | B2: 8.1e-05
A3: MIN | B3: 1e-06
A4: FBT | B4: 7e-06
A5: TEX | B5: 4.8e-05
A6: LEATHER | B6: 6.2e-05
A7: WOOD | B7: 4.7e-05
A8: PPP | B8: 2.7e-05
A9: PC | B9: 9.8e-05
A10: CHM | B10: 6.9e-05
A11: RUBBER | B11: 0.0001
A12: NMM | B12: 3e-06
A13: METAL | B13: 4.8e-05
... A34: DWE | B34: 8.2e-05

Sheet 1LAB
A1: IND | B1: OCC | C1: Value
A2: AG | B2: EMIRATI | C2: 14.240861
A3: MIN | B3: EMIRATI | C3: 90.364734
A4: FBT | B4: EMIRATI | C4: 69.178652
A5: TEX | B5: EMIRATI | C5: 21.659221
A6: LEATHER | B6: EMIRATI | C6: 0.19311588
A7: WOOD | B7: EMIRATI | C7: 16.314918
A8: PPP | B8: EMIRATI | C8: 33.470438
A9: PC | B9: EMIRATI | C9: 6.6922626
A10: CHM | B10: EMIRATI | C10: 40.239678
A11: RUBBER | B11: EMIRATI | C11: 18.177604
A12: NMM | B12: EMIRATI | C12: 44.044585
A13: METAL | B13: EMIRATI | C13: 104.69835
... A133: DWE | B133: COMMUTING | C133: 493.60061

Sheet 1PTX
A1: IND | B1: Value
A2: AG | B2: 1e-05
A3: MIN | B3: 1e-05
A4: FBT | B4: 1e-05
A5: TEX | B5: 1e-05
A6: LEATHER | B6: 1e-05
A7: WOOD | B7: 1e-05
A8: PPP | B8: 1e-05
A9: PC | B9: 1e-05
A10: CHM | B10: 1e-05
A11: RUBBER | B11: 1e-05
A12: NMM | B12: 1e-05
A13: METAL | B13: 1e-05
... A34: DWE | B34: 1e-05

Sheet 1OCT
A1: IND | B1: Value
A2: AG | B2: 1e-05
A3: MIN | B3: 1e-05
A4: FBT | B4: 1e-05
A5: TEX | B5: 1e-05
A6: LEATHER | B6: 1e-05
A7: WOOD | B7: 1e-05
A8: PPP | B8: 1e-05
A9: PC | B9: 1e-05
A10: CHM | B10: 1e-05
A11: RUBBER | B11: 1e-05
A12: NMM | B12: 1e-05
A13: METAL | B13: 1e-05
... A34: DWE | B34: 1e-05

Sheet MAKE
A1: COM | B1: IND | C1: Value
A2: AG | B2: AG | C2: 1512.2992
A3: MIN | B3: AG | C3: 0
A4: FBT | B4: AG | C4: 0
A5: TEX | B5: AG | C5: 0
A6: LEATHER | B6: AG | C6: 0
A7: WOOD | B7: AG | C7: 0
A8: PPP | B8: AG | C8: 0
A9: PC | B9: AG | C9: 0
A10: CHM | B10: AG | C10: 0
A11: RUBBER | B11: AG | C11: 0
A12: NMM | B12: AG | C12: 0
A13: METAL | B13: AG | C13: 0
... A1090: DWE | B1090: DWE | C1090: 1945.3419

Sheet 0TAR
A1: COM | B1: Value
A2: AG | B2: 144.4832
A3: MIN | B3: 273.09907
A4: FBT | B4: 470.15579
A5: TEX | B5: 316.85345
A6: LEATHER | B6: 123.97176
A7: WOOD | B7: 25.615143
A8: PPP | B8: 76.334952
A9: PC | B9: 110.92151
A10: CHM | B10: 341.30384
A11: RUBBER | B11: 117.91219
A12: NMM | B12: 78.717072
A13: METAL | B13: 767.68665
... A34: DWE | B34: 0

Sheet SLAB
A1: IND | B1: Value
A2: AG | B2: 2
A3: MIN | B3: 2
A4: FBT | B4: 2
A5: TEX | B5: 2
A6: LEATHER | B6: 2
A7: WOOD | B7: 2
A8: PPP | B8: 2
A9: PC | B9: 2
A10: CHM | B10: 2
A11: RUBBER | B11: 2
A12: NMM | B12: 2
A13: METAL | B13: 2
... A34: DWE | B34: 2

Sheet SCAP
A1: Value
A2: -0.5

Sheet P028
A1: IND | B1: Value
A2: AG | B2: 0.23
A3: MIN | B3: 0.2
A4: FBT | B4: 1.12
A5: TEX | B5: 1.26
A6: LEATHER | B6: 1.26
A7: WOOD | B7: 1.26
A8: PPP | B8: 1.26
A9: PC | B9: 1.26
A10: CHM | B10: 1.26
A11: RUBBER | B11: 1.26
A12: NMM | B12: 1.26
A13: METAL | B13: 1.26
... A34: DWE | B34: 1.26

Sheet 1ARM
A1: COM | B1: Value
A2: AG | B2: 2
A3: MIN | B3: 2
A4: FBT | B4: 2
A5: TEX | B5: 2
A6: LEATHER | B6: 2
A7: WOOD | B7: 2
A8: PPP | B8: 2
A9: PC | B9: 2
A10: CHM | B10: 2
A11: RUBBER | B11: 2
A12: NMM | B12: 2
A13: METAL | B13: 2
... A34: DWE | B34: 2

Sheet SCET
A1: IND | B1: Value
A2: AG | B2: 0.4
A3: MIN | B3: 0.4
A4: FBT | B4: 0.4
A5: TEX | B5: 0.4
A6: LEATHER | B6: 0.4
A7: WOOD | B7: 0.4
A8: PPP | B8: 0.4
A9: PC | B9: 0.4
A10: CHM | B10: 0.4
A11: RUBBER | B11: 0.4
A12: NMM | B12: 0.4
A13: METAL | B13: 0.4
... A34: DWE | B34: 0.4

Sheet 2ARM
A1: COM | B1: Value
A2: AG | B2: 2
A3: MIN | B3: 2
A4: FBT | B4: 2
A5: TEX | B5: 2
A6: LEATHER | B6: 2
A7: WOOD | B7: 2
A8: PPP | B8: 2
A9: PC | B9: 2
A10: CHM | B10: 2
A11: RUBBER | B11: 2
A12: NMM | B12: 2
A13: METAL | B13: 2
... A34: DWE | B34: 2

Sheet 3ARM
A1: COM | B1: Value
A2: AG | B2: 2
A3: MIN | B3: 2
A4: FBT | B4: 2
A5: TEX | B5: 2
A6: LEATHER | B6: 2
A7: WOOD | B7: 2
A8: PPP | B8: 2
A9: PC | B9: 2
A10: CHM | B10: 2
A11: RUBBER | B11: 2
A12: NMM | B12: 2
A13: METAL | B13: 2
... A34: DWE | B34: 2

Sheet P021
A1: Value
A2: -1.15

Sheet XPEL
A1: COM | B1: Value
A2: AG | B2: 1
A3: MIN | B3: 1
A4: FBT | B4: 1
A5: TEX | B5: 1
A6: LEATHER | B6: 1
A7: WOOD | B7: 1
A8: PPP | B8: 1
A9: PC | B9: 1
A10: CHM | B10: 1
A11: RUBBER | B11: 1
A12: NMM | B12: 1
A13: METAL | B13: 1
... A34: DWE | B34: 1

Sheet P018
A1: COM | B1: Value
A2: AG | B2: -4.4
A3: MIN | B3: -5.6
A4: FBT | B4: -4.7
A5: TEX | B5: -6.7
A6: LEATHER | B6: -3.6
A7: WOOD | B7: -3.6
A8: PPP | B8: -3.6
A9: PC | B9: -3.6
A10: CHM | B10: -3.6
A11: RUBBER | B11: -3.6
A12: NMM | B12: -3.6
A13: METAL | B13: -3.6
... A34: DWE | B34: -4

Sheet EXNT
A1: Value
A2: -2

Sheet ITEX
A1: Value
A2: AG
A3: MIN
A4: FBT
A5: TEX
A6: LEATHER
A7: WOOD
A8: PPP
A9: PC
A10: CHM
A11: RUBBER
A12: NMM
... A34: DWE

Sheet ARATIO
A1: COM | B1: Value
A2: AG | B2: 1
A3: MIN | B3: 1
A4: FBT | B4: 1
A5: TEX | B5: 1
A6: LEATHER | B6: 1
A7: WOOD | B7: 1
A8: PPP | B8: 1
A9: PC | B9: 1
A10: CHM | B10: 1
A11: RUBBER | B11: 1
A12: NMM | B12: 1
A13: METAL | B13: 1
... A34: DWE | B34: 1
