Workbook
Name adjFactor: 'Estimating non em split'!$Y$290
Name commuting: Calculations!$C$136
Name lowskillWage: 'Estimating non em split'!$D$216
Name توفير_البيانات___أولي: #REF!
Name توفير_البيانات___أولي: #REF!

Sheet HEADERS
A1: COM | C1: IND | E1: OCC | G1: Calculations for the imported shares | Q1: 1BAS | R1: Check | S1: =SUM(T6:T2183)-SUM('Calculations 2'!C45:AI77) -> -1.6298145e-09 | Z1: Capital shares | AC1: 2BAS | AD1: Check | AE1: =SUM(AF6:AF2183)-SUM('Calculations 2'!CE45:CE77) -> 0 | AI1: 3BAS | AJ1: Check | AK1: =SUM(AK6:AK71)-SUM('Calculations 2'!BY45:CB77) -> 0 | AN1: 4BAS | AQ1: 5BAS | AU1: 6BAS | AY1: 1TAX | BE1: 2TAX | BK1: 3TAX | BP1: 4TAX | BT1: 5TAX | BX1: 0TAR | CA1: 1CAP | CD1: 1LAB | CH1: 1LND | CL1: 1PTX | CP1: 1OCT | CT1: MAKE | CY1: SLAB | DC1: P028 | DG1: 1ARM | DK1: SCET | DP1: 2ARM | DU1: 3ARM | DZ1: P021 | ED1: XPEL | EH1: P018 | EM1: EXNT | EQ1: ITEX
V3: 33
A4: Value | C4: Value | E4: Value | I4: Domestic | J4: Imported | K4: Total | M4: Dom share | N4: Imp share | Q4: COM | R4: SRC | S4: IND | T4: Value | AC4: COM | AD4: SRC | AE4: IND | AF4: Value | AI4: COM | AJ4: SRC | AK4: Value | AN4: COM | AO4: Value | AQ4: COM | AR4: SRC | AS4: Value | AU4: COM | AV4: Value | AY4: COM | AZ4: SRC | BA4: IND | BB4: Value | BE4: COM | BF4: SRC | BG4: IND | BH4: Value | BK4: COM | BL4: SRC | BM4: Value | BP4: COM | BQ4: Value | BT4: COM | BU4: SRC | BV4: Value | BX4: COM | BY4: Value | CA4: IND | CB4: Value | CD4: IND | CE4: OCC | CF4: Value | CH4: IND | CI4: Value | CL4: IND | CM4: Value | CP4: IND | CQ4: Value | CT4: COM | CU4: IND | CV4: Value | CY4: IND | CZ4: Value | DC4: IND | DD4: Value | DG4: COM | DH4: Value | DK4: IND | DL4: Value | DP4: COM | DQ4: Value | DU4: COM | DV4: Value | DZ4: Value | ED4: COM | EE4: Value | EH4: COM | EI4: Value | EM4: Value | EQ4: Value
A6: AG | C6: AG | E6: EMIRATI | H6: AG | I6: {=TRANSPOSE('Calculations 2'!C93:AI93)} -> 1512.2992 | J6: {=TRANSPOSE('Calculations 2'!AJ91:BP91)+TRANSPOSE('Calculations 2'!AJ83:BP83)} -> 20356.806 | K6: {=TRANSPOSE('Calculations 2'!AJ93:BP93)} -> 21869.105 | M6: =I6/$K6 -> 0.069152315 | N6: =J6/$K6 -> 0.93084769 | Q6: AG | R6: dom | S6: AG | T6: =OFFSET('Calculations 2'!$C$45,W6,X6)*OFFSET($M$6,W6,0) -> 9.8941912 | V6: 0 | W6: =MOD(V6,$V$3) -> 0 | X6: =FLOOR(V6/$V$3,1) -> 0 | Z6: AG | AA6: {=TRANSPOSE('Calculations 2'!C82:AI82)/SUM('Calculations 2'!C82:AI82)} -> 0.0016841188 | AC6: AG | AD6: dom | AE6: AG | AF6: =OFFSET('Calculations 2'!$CE$45,W6,0)*OFFSET($AA$6,X6,0)*OFFSET($M$6,W6,) -> 0.038198128 | AI6: AG | AJ6: dom | AK6: =SUM('Calculations 2'!BY45:CB45)*M6 -> 188.42553 | AN6: AG | AO6: {='Calculations 2'!CD45:CD77} -> 13478.352 | AQ6: AG | AR6: dom | AS6: {='Calculations 2'!CC45:CC77*M6:M38} -> 0 | AU6: AG | AV6: 0 | AY6: AG | AZ6: dom | BA6: AG | BB6: 0 | BE6: AG | BF6: dom | BG6: AG | BH6: 0 | BK6: AG | BL6: dom | BM6: 0 | BP6: AG | BQ6: 0 | BT6: AG | BU6: dom | BV6: 0 | BX6: AG | BY6: {=TRANSPOSE('Calculations 2'!AJ83:BP83)} -> 144.4832 | CA6: AG | CB6: {=TRANSPOSE('Calculations 2'!C82:AI82)} -> 414.32237 | CD6: AG | CE6: EMIRATI | CF6: {=TRANSPOSE('Calculations 2'!C78:AI78)} -> 14.240861 | CH6: AG | CI6: 0 | CL6: AG | CM6: 0 | CP6: AG | CQ6: 0 | CT6: AG | CU6: AG | CV6: =OFFSET('Calculations 2'!$AJ$12,W6,X6) -> 1512.2992 | CY6: AG | CZ6: 0.5 | DC6: AG | DD6: 0.23 | DG6: AG | DH6: 2 | DK6: AG | DL6: 0.4 | DP6: AG | DQ6: 2 | DU6: AG | DV6: 2 | DZ6: -1.15 | ED6: AG | EE6: 1 | EH6: AG | EI6: -4.4 | EM6: -2 | EQ6: AG
A7: MIN | C7: MIN | E7: MIGRANTHH | H7: MIN | I7: 11448.729 | J7: 139374.78 | K7: 150823.5 | M7: =I7/$K7 -> 0.075908119 | N7: =J7/$K7 -> 0.92409188 | Q7: MIN | R7: dom | S7: AG | T7: =OFFSET('Calculations 2'!$C$45,W7,X7)*OFFSET($M$6,W7,0) -> 0 | V7: =V6+1 -> 1 | W7: =MOD(V7,$V$3) -> 1 | X7: =FLOOR(V7/$V$3,1) -> 0 | Z7: MIN | AA7: 0.029357277 | AC7: MIN | AD7: dom | AE7: AG | AF7: =OFFSET('Calculations 2'!$CE$45,W7,0)*OFFSET($AA$6,X7,0)*OFFSET($M$6,W7,) -> 0.06663351 | AI7: MIN | AJ7: dom | AK7: =SUM('Calculations 2'!BY46:CB46)*M7 -> 39.022698 | AN7: MIN | AO7: 125317.36 | AQ7: MIN | AR7: dom | AS7: 0 | AU7: MIN | AV7: 0 | AY7: MIN | AZ7: dom | BA7: AG | BB7: 0 | BE7: MIN | BF7: dom | BG7: AG | BH7: 0 | BK7: MIN | BL7: dom | BM7: 0 | BP7: MIN | BQ7: 0 | BT7: MIN | BU7: dom | BV7: 0 | BX7: MIN | BY7: 273.09907 | CA7: MIN | CB7: 7222.3983 | CD7: MIN | CE7: EMIRATI | CF7: 90.364734 | CH7: MIN | CI7: 0 | CL7: MIN | CM7: 0 | CP7: MIN | CQ7: 0 | CT7: MIN | CU7: AG | CV7: =OFFSET('Calculations 2'!$AJ$12,W7,X7) -> 0 | CY7: MIN | CZ7: 0.5 | DC7: MIN | DD7: 0.2 | DG7: MIN | DH7: 2 | DK7: MIN | DL7: 0.4 | DP7: MIN | DQ7: 2 | DU7: MIN | DV7: 2 | ED7: MIN | EE7: 1 | EH7: MIN | EI7: -5.6 | EQ7: MIN
A8: FBT | C8: FBT | E8: MIGRANTCOMB | H8: FBT | I8: 25557.719 | J8: 46238.282 | K8: 71796.001 | M8: =I8/$K8 -> 0.35597691 | N8: =J8/$K8 -> 0.64402309 | Q8: FBT | R8: dom | S8: AG | T8: =OFFSET('Calculations 2'!$C$45,W8,X8)*OFFSET($M$6,W8,0) -> 157.79694 | V8: =V7+1 -> 2 | W8: =MOD(V8,$V$3) -> 2 | X8: =FLOOR(V8/$V$3,1) -> 0 | Z8: FBT | AA8: 0.013820837 | AC8: FBT | AD8: dom | AE8: AG | AF8: =OFFSET('Calculations 2'!$CE$45,W8,0)*OFFSET($AA$6,X8,0)*OFFSET($M$6,W8,) -> 0.1121968 | AI8: FBT | AJ8: dom | AK8: =SUM('Calculations 2'!BY47:CB47)*M8 -> 3252.1205 | AN8: FBT | AO8: 40267.725 | AQ8: FBT | AR8: dom | AS8: 0 | AU8: FBT | AV8: 0 | AY8: FBT | AZ8: dom | BA8: AG | BB8: 0 | BE8: FBT | BF8: dom | BG8: AG | BH8: 0 | BK8: FBT | BL8: dom | BM8: 0 | BP8: FBT | BQ8: 0 | BT8: FBT | BU8: dom | BV8: 0 | BX8: FBT | BY8: 470.15579 | CA8: FBT | CB8: 3400.165 | CD8: FBT | CE8: EMIRATI | CF8: 69.178652 | CH8: FBT | CI8: 0 | CL8: FBT | CM8: 0 | CP8: FBT | CQ8: 0 | CT8: FBT | CU8: AG | CV8: =OFFSET('Calculations 2'!$AJ$12,W8,X8) -> 0 | CY8: FBT | CZ8: 0.5 | DC8: FBT | DD8: 1.12 | DG8: FBT | DH8: 2 | DK8: FBT | DL8: 0.4 | DP8: FBT | DQ8: 2 | DU8: FBT | DV8: 2 | ED8: FBT | EE8: 1 | EH8: FBT | EI8: -4.7 | EQ8: FBT
A9: TEX | C9: TEX | E9: COMMUTING | H9: TEX | I9: 3421.037 | J9: 23317.56 | K9: 26738.597 | M9: =I9/$K9 -> 0.12794378 | N9: =J9/$K9 -> 0.87205622 | Q9: TEX | R9: dom | S9: AG | T9: =OFFSET('Calculations 2'!$C$45,W9,X9)*OFFSET($M$6,W9,0) -> 1.256591 | V9: =V8+1 -> 3 | W9: =MOD(V9,$V$3) -> 3 | X9: =FLOOR(V9/$V$3,1) -> 0 | Z9: TEX | AA9: 0.0033036375 | AC9: TEX | AD9: dom | AE9: AG | AF9: =OFFSET('Calculations 2'!$CE$45,W9,0)*OFFSET($AA$6,X9,0)*OFFSET($M$6,W9,) -> 0.58441687 | AI9: TEX | AJ9: dom | AK9: =SUM('Calculations 2'!BY48:CB48)*M9 -> 354.347 | AN9: TEX | AO9: 18250.608 | AQ9: TEX | AR9: dom | AS9: 0 | AU9: TEX | AV9: 0 | AY9: TEX | AZ9: dom | BA9: AG | BB9: 0 | BE9: TEX | BF9: dom | BG9: AG | BH9: 0 | BK9: TEX | BL9: dom | BM9: 0 | BP9: TEX | BQ9: 0 | BT9: TEX | BU9: dom | BV9: 0 | BX9: TEX | BY9: 316.85345 | CA9: TEX | CB9: 812.752 | CD9: TEX | CE9: EMIRATI | CF9: 21.659221 | CH9: TEX | CI9: 0 | CL9: TEX | CM9: 0 | CP9: TEX | CQ9: 0 | CT9: TEX | CU9: AG | CV9: =OFFSET('Calculations 2'!$AJ$12,W9,X9) -> 0 | CY9: TEX | CZ9: 0.5 | DC9: TEX | DD9: 1.26 | DG9: TEX | DH9: 2 | DK9: TEX | DL9: 0.4 | DP9: TEX | DQ9: 2 | DU9: TEX | DV9: 2 | ED9: TEX | EE9: 1 | EH9: TEX | EI9: -6.7 | EQ9: TEX
A10: LEATHER | C10: LEATHER | H10: LEATHER | I10: 29.598 | J10: 14817.33 | K10: 14846.928 | M10: =I10/$K10 -> 0.0019935437 | N10: =J10/$K10 -> 0.99800646 | Q10: LEATHER | R10: dom | S10: AG | T10: =OFFSET('Calculations 2'!$C$45,W10,X10)*OFFSET($M$6,W10,0) -> 0 | V10: =V9+1 -> 4 | W10: =MOD(V10,$V$3) -> 4 | X10: =FLOOR(V10/$V$3,1) -> 0 | Z10: LEATHER | AA10: 1.549891e-05 | AC10: LEATHER | AD10: dom | AE10: AG | AF10: =OFFSET('Calculations 2'!$CE$45,W10,0)*OFFSET($AA$6,X10,0)*OFFSET($M$6,W10,) -> 0.0041468607 | AI10: LEATHER | AJ10: dom | AK10: =SUM('Calculations 2'!BY49:CB49)*M10 -> 3.900226 | AN10: LEATHER | AO10: 11177.055 | AQ10: LEATHER | AR10: dom | AS10: 0 | AU10: LEATHER | AV10: 0 | AY10: LEATHER | AZ10: dom | BA10: AG | BB10: 0 | BE10: LEATHER | BF10: dom | BG10: AG | BH10: 0 | BK10: LEATHER | BL10: dom | BM10: 0 | BP10: LEATHER | BQ10: 0 | BT10: LEATHER | BU10: dom | BV10: 0 | BX10: LEATHER | BY10: 123.97176 | CA10: LEATHER | CB10: 3.813 | CD10: LEATHER | CE10: EMIRATI | CF10: 0.19311588 | CH10: LEATHER | CI10: 0 | CL10: LEATHER | CM10: 0 | CP10: LEATHER | CQ10: 0 | CT10: LEATHER | CU10: AG | CV10: =OFFSET('Calculations 2'!$AJ$12,W10,X10) -> 0 | CY10: LEATHER | CZ10: 0.5 | DC10: LEATHER | DD10: 1.26 | DG10: LEATHER | DH10: 2 | DK10: LEATHER | DL10: 0.4 | DP10: LEATHER | DQ10: 2 | DU10: LEATHER | DV10: 2 | ED10: LEATHER | EE10: 1 | EH10: LEATHER | EI10: -3.6 | EQ10: LEATHER
A11: WOOD | C11: WOOD | H11: WOOD | I11: 2673.883 | J11: 3892.1263 | K11: 6566.0093 | M11: =I11/$K11 -> 0.40723107 | N11: =J11/$K11 -> 0.59276893 | Q11: WOOD | R11: dom | S11: AG | T11: =OFFSET('Calculations 2'!$C$45,W11,X11)*OFFSET($M$6,W11,0) -> 0 | V11: =V10+1 -> 5 | W11: =MOD(V11,$V$3) -> 5 | X11: =FLOOR(V11/$V$3,1) -> 0 | Z11: WOOD | AA11: 0.0012514282 | AC11: WOOD | AD11: dom | AE11: AG | AF11: =OFFSET('Calculations 2'!$CE$45,W11,0)*OFFSET($AA$6,X11,0)*OFFSET($M$6,W11,) -> 0.025528021 | AI11: WOOD | AJ11: dom | AK11: =SUM('Calculations 2'!BY50:CB50)*M11 -> 0 | AN11: WOOD | AO11: 2027.6278 | AQ11: WOOD | AR11: dom | AS11: 0 | AU11: WOOD | AV11: 0 | AY11: WOOD | AZ11: dom | BA11: AG | BB11: 0 | BE11: WOOD | BF11: dom | BG11: AG | BH11: 0 | BK11: WOOD | BL11: dom | BM11: 0 | BP11: WOOD | BQ11: 0 | BT11: WOOD | BU11: dom | BV11: 0 | BX11: WOOD | BY11: 25.615143 | CA11: WOOD | CB11: 307.873 | CD11: WOOD | CE11: EMIRATI | CF11: 16.314918 | CH11: WOOD | CI11: 0 | CL11: WOOD | CM11: 0 | CP11: WOOD | CQ11: 0 | CT11: WOOD | CU11: AG | CV11: =OFFSET('Calculations 2'!$AJ$12,W11,X11) -> 0 | CY11: WOOD | CZ11: 0.5 | DC11: WOOD | DD11: 1.26 | DG11: WOOD | DH11: 2 | DK11: WOOD | DL11: 0.4 | DP11: WOOD | DQ11: 2 | DU11: WOOD | DV11: 2 | ED11: WOOD | EE11: 1 | EH11: WOOD | EI11: -3.6 | EQ11: WOOD
A12: PPP | C12: PPP | H12: PPP | I12: 7097.443 | J12: 7432.5429 | K12: 14529.986 | M12: =I12/$K12 -> 0.48846868 | N12: =J12/$K12 -> 0.51153132 | Q12: PPP | R12: dom | S12: AG | T12: =OFFSET('Calculations 2'!$C$45,W12,X12)*OFFSET($M$6,W12,0) -> 0 | V12: =V11+1 -> 6 | W12: =MOD(V12,$V$3) -> 6 | X12: =FLOOR(V12/$V$3,1) -> 0 | Z12: PPP | AA12: 0.0035752525 | AC12: PPP | AD12: dom | AE12: AG | AF12: =OFFSET('Calculations 2'!$CE$45,W12,0)*OFFSET($AA$6,X12,0)*OFFSET($M$6,W12,) -> 0.5109592 | AI12: PPP | AJ12: dom | AK12: =SUM('Calculations 2'!BY51:CB51)*M12 -> 125.19658 | AN12: PPP | AO12: 3806.5156 | AQ12: PPP | AR12: dom | AS12: 0 | AU12: PPP | AV12: 0 | AY12: PPP | AZ12: dom | BA12: AG | BB12: 0 | BE12: PPP | BF12: dom | BG12: AG | BH12: 0 | BK12: PPP | BL12: dom | BM12: 0 | BP12: PPP | BQ12: 0 | BT12: PPP | BU12: dom | BV12: 0 | BX12: PPP | BY12: 76.334952 | CA12: PPP | CB12: 879.574 | CD12: PPP | CE12: EMIRATI | CF12: 33.470438 | CH12: PPP | CI12: 0 | CL12: PPP | CM12: 0 | CP12: PPP | CQ12: 0 | CT12: PPP | CU12: AG | CV12: =OFFSET('Calculations 2'!$AJ$12,W12,X12) -> 0 | CY12: PPP | CZ12: 0.5 | DC12: PPP | DD12: 1.26 | DG12: PPP | DH12: 2 | DK12: PPP | DL12: 0.4 | DP12: PPP | DQ12: 2 | DU12: PPP | DV12: 2 | ED12: PPP | EE12: 1 | EH12: PPP | EI12: -3.6 | EQ12: PPP
A13: PC | C13: PC | H13: PC | I13: 28389.412 | J13: 49129.005 | K13: 77518.417 | M13: =I13/$K13 -> 0.36622797 | N13: =J13/$K13 -> 0.63377203 | Q13: PC | R13: dom | S13: AG | T13: =OFFSET('Calculations 2'!$C$45,W13,X13)*OFFSET($M$6,W13,0) -> 13.401128 | V13: =V12+1 -> 7 | W13: =MOD(V13,$V$3) -> 7 | X13: =FLOOR(V13/$V$3,1) -> 0 | Z13: PC | AA13: 0.0078380136 | AC13: PC | AD13: dom | AE13: AG | AF13: =OFFSET('Calculations 2'!$CE$45,W13,0)*OFFSET($AA$6,X13,0)*OFFSET($M$6,W13,) -> 0.077860293 | AI13: PC | AJ13: dom | AK13: =SUM('Calculations 2'!BY52:CB52)*M13 -> 661.44051 | AN13: PC | AO13: 23605.032 | AQ13: PC | AR13: dom | AS13: 0 | AU13: PC | AV13: 0 | AY13: PC | AZ13: dom | BA13: AG | BB13: 0 | BE13: PC | BF13: dom | BG13: AG | BH13: 0 | BK13: PC | BL13: dom | BM13: 0 | BP13: PC | BQ13: 0 | BT13: PC | BU13: dom | BV13: 0 | BX13: PC | BY13: 110.92151 | CA13: PC | CB13: 1928.287 | CD13: PC | CE13: EMIRATI | CF13: 6.6922626 | CH13: PC | CI13: 0 | CL13: PC | CM13: 0 | CP13: PC | CQ13: 0 | CT13: PC | CU13: AG | CV13: =OFFSET('Calculations 2'!$AJ$12,W13,X13) -> 0 | CY13: PC | CZ13: 0.5 | DC13: PC | DD13: 1.26 | DG13: PC | DH13: 2 | DK13: PC | DL13: 0.4 | DP13: PC | DQ13: 2 | DU13: PC | DV13: 2 | ED13: PC | EE13: 1 | EH13: PC | EI13: -3.6 | EQ13: PC
A14: CHM | C14: CHM | H14: CHM | I14: 13147.266 | J14: 50085.109 | K14: 63232.375 | M14: =I14/$K14 -> 0.20791985 | N14: =J14/$K14 -> 0.79208015 | Q14: CHM | R14: dom | S14: AG | T14: =OFFSET('Calculations 2'!$C$45,W14,X14)*OFFSET($M$6,W14,0) -> 1.3170773 | V14: =V13+1 -> 8 | W14: =MOD(V14,$V$3) -> 8 | X14: =FLOOR(V14/$V$3,1) -> 0 | Z14: CHM | AA14: 0.00990686 | AC14: CHM | AD14: dom | AE14: AG | AF14: =OFFSET('Calculations 2'!$CE$45,W14,0)*OFFSET($AA$6,X14,0)*OFFSET($M$6,W14,) -> 0.48485196 | AI14: CHM | AJ14: dom | AK14: =SUM('Calculations 2'!BY53:CB53)*M14 -> 527.86509 | AN14: CHM | AO14: 44799.938 | AQ14: CHM | AR14: dom | AS14: 0 | AU14: CHM | AV14: 0 | AY14: CHM | AZ14: dom | BA14: AG | BB14: 0 | BE14: CHM | BF14: dom | BG14: AG | BH14: 0 | BK14: CHM | BL14: dom | BM14: 0 | BP14: CHM | BQ14: 0 | BT14: CHM | BU14: dom | BV14: 0 | BX14: CHM | BY14: 341.30384 | CA14: CHM | CB14: 2437.259 | CD14: CHM | CE14: EMIRATI | CF14: 40.239678 | CH14: CHM | CI14: 0 | CL14: CHM | CM14: 0 | CP14: CHM | CQ14: 0 | CT14: CHM | CU14: AG | CV14: =OFFSET('Calculations 2'!$AJ$12,W14,X14) -> 0 | CY14: CHM | CZ14: 0.5 | DC14: CHM | DD14: 1.26 | DG14: CHM | DH14: 2 | DK14: CHM | DL14: 0.4 | DP14: CHM | DQ14: 2 | DU14: CHM | DV14: 2 | ED14: CHM | EE14: 1 | EH14: CHM | EI14: -3.6 | EQ14: CHM
A15: RUBBER | C15: RUBBER | H15: RUBBER | I15: 6406.529 | J15: 11940.515 | K15: 18347.044 | M15: =I15/$K15 -> 0.3491859 | N15: =J15/$K15 -> 0.6508141 | Q15: RUBBER | R15: dom | S15: AG | T15: =OFFSET('Calculations 2'!$C$45,W15,X15)*OFFSET($M$6,W15,0) -> 0 | V15: =V14+1 -> 9 | W15: =MOD(V15,$V$3) -> 9 | X15: =FLOOR(V15/$V$3,1) -> 0 | Z15: RUBBER | AA15: 0.0048881317 | AC15: RUBBER | AD15: dom | AE15: AG | AF15: =OFFSET('Calculations 2'!$CE$45,W15,0)*OFFSET($AA$6,X15,0)*OFFSET($M$6,W15,) -> 0.75898898 | AI15: RUBBER | AJ15: dom | AK15: =SUM('Calculations 2'!BY54:CB54)*M15 -> 2.6051403 | AN15: RUBBER | AO15: 11455.931 | AQ15: RUBBER | AR15: dom | AS15: 0 | AU15: RUBBER | AV15: 0 | AY15: RUBBER | AZ15: dom | BA15: AG | BB15: 0 | BE15: RUBBER | BF15: dom | BG15: AG | BH15: 0 | BK15: RUBBER | BL15: dom | BM15: 0 | BP15: RUBBER | BQ15: 0 | BT15: RUBBER | BU15: dom | BV15: 0 | BX15: RUBBER | BY15: 117.91219 | CA15: RUBBER | CB15: 1202.565 | CD15: RUBBER | CE15: EMIRATI | CF15: 18.177604 | CH15: RUBBER | CI15: 0 | CL15: RUBBER | CM15: 0 | CP15: RUBBER | CQ15: 0 | CT15: RUBBER | CU15: AG | CV15: =OFFSET('Calculations 2'!$AJ$12,W15,X15) -> 0 | CY15: RUBBER | CZ15: 0.5 | DC15: RUBBER | DD15: 1.26 | DG15: RUBBER | DH15: 2 | DK15: RUBBER | DL15: 0.4 | DP15: RUBBER | DQ15: 2 | DU15: RUBBER | DV15: 2 | ED15: RUBBER | EE15: 1 | EH15: RUBBER | EI15: -3.6 | EQ15: RUBBER
A16: NMM | C16: NMM | H16: NMM | I16: 8147.143 | J16: 6187.5803 | K16: 14334.723 | M16: =I16/$K16 -> 0.56835021 | N16: =J16/$K16 -> 0.43164979 | Q16: NMM | R16: dom | S16: AG | T16: =OFFSET('Calculations 2'!$C$45,W16,X16)*OFFSET($M$6,W16,0) -> 0 | V16: =V15+1 -> 10 | W16: =MOD(V16,$V$3) -> 10 | X16: =FLOOR(V16/$V$3,1) -> 0 | Z16: NMM | AA16: 0.0034431521 | AC16: NMM | AD16: dom | AE16: AG | AF16: =OFFSET('Calculations 2'!$CE$45,W16,0)*OFFSET($AA$6,X16,0)*OFFSET($M$6,W16,) -> 0.70310895 | AI16: NMM | AJ16: dom | AK16: =SUM('Calculations 2'!BY55:CB55)*M16 -> 50.778097 | AN16: NMM | AO16: 4728.6533 | AQ16: NMM | AR16: dom | AS16: 0 | AU16: NMM | AV16: 0 | AY16: NMM | AZ16: dom | BA16: AG | BB16: 0 | BE16: NMM | BF16: dom | BG16: AG | BH16: 0 | BK16: NMM | BL16: dom | BM16: 0 | BP16: NMM | BQ16: 0 | BT16: NMM | BU16: dom | BV16: 0 | BX16: NMM | BY16: 78.717072 | CA16: NMM | CB16: 847.075 | CD16: NMM | CE16: EMIRATI | CF16: 44.044585 | CH16: NMM | CI16: 0 | CL16: NMM | CM16: 0 | CP16: NMM | CQ16: 0 | CT16: NMM | CU16: AG | CV16: =OFFSET('Calculations 2'!$AJ$12,W16,X16) -> 0 | CY16: NMM | CZ16: 0.5 | DC16: NMM | DD16: 1.26 | DG16: NMM | DH16: 2 | DK16: NMM | DL16: 0.4 | DP16: NMM | DQ16: 2 | DU16: NMM | DV16: 2 | ED16: NMM | EE16: 1 | EH16: NMM | EI16: -3.6 | EQ16: NMM
A17: METAL | C17: METAL | H17: METAL | I17: 38703.505 | J17: 125797.11 | K17: 164500.62 | M17: =I17/$K17 -> 0.23527878 | N17: =J17/$K17 -> 0.76472122 | Q17: METAL | R17: dom | S17: AG | T17: =OFFSET('Calculations 2'!$C$45,W17,X17)*OFFSET($M$6,W17,0) -> 0 | V17: =V16+1 -> 11 | W17: =MOD(V17,$V$3) -> 11 | X17: =FLOOR(V17/$V$3,1) -> 0 | Z17: METAL | AA17: 0.029767971 | AC17: METAL | AD17: dom | AE17: AG | AF17: =OFFSET('Calculations 2'!$CE$45,W17,0)*OFFSET($AA$6,X17,0)*OFFSET($M$6,W17,) -> 2.0564721 | AI17: METAL | AJ17: dom | AK17: =SUM('Calculations 2'!BY56:CB56)*M17 -> 22.327324 | AN17: METAL | AO17: 129405.85 | AQ17: METAL | AR17: dom | AS17: 0 | AU17: METAL | AV17: 0 | AY17: METAL | AZ17: dom | BA17: AG | BB17: 0 | BE17: METAL | BF17: dom | BG17: AG | BH17: 0 | BK17: METAL | BL17: dom | BM17: 0 | BP17: METAL | BQ17: 0 | BT17: METAL | BU17: dom | BV17: 0 | BX17: METAL | BY17: 767.68665 | CA17: METAL | CB17: 7323.436 | CD17: METAL | CE17: EMIRATI | CF17: 104.69835 | CH17: METAL | CI17: 0 | CL17: METAL | CM17: 0 | CP17: METAL | CQ17: 0 | CT17: METAL | CU17: AG | CV17: =OFFSET('Calculations 2'!$AJ$12,W17,X17) -> 0 | CY17: METAL | CZ17: 0.5 | DC17: METAL | DD17: 1.26 | DG17: METAL | DH17: 2 | DK17: METAL | DL17: 0.4 | DP17: METAL | DQ17: 2 | DU17: METAL | DV17: 2 | ED17: METAL | EE17: 1 | EH17: METAL | EI17: -3.6 | EQ17: METAL
A18: MACH | C18: MACH | H18: MACH | I18: 7111.347 | J18: 61173.541 | K18: 68284.888 | M18: =I18/$K18 -> 0.10414232 | N18: =J18/$K18 -> 0.89585768 | Q18: MACH | R18: dom | S18: AG | T18: =OFFSET('Calculations 2'!$C$45,W18,X18)*OFFSET($M$6,W18,0) -> 0 | V18: =V17+1 -> 12 | W18: =MOD(V18,$V$3) -> 12 | X18: =FLOOR(V18/$V$3,1) -> 0 | Z18: MACH | AA18: 0.0039926053 | AC18: MACH | AD18: dom | AE18: AG | AF18: =OFFSET('Calculations 2'!$CE$45,W18,0)*OFFSET($AA$6,X18,0)*OFFSET($M$6,W18,) -> 2.9765813 | AI18: MACH | AJ18: dom | AK18: =SUM('Calculations 2'!BY57:CB57)*M18 -> 2.4711649 | AN18: MACH | AO18: 40306.888 | AQ18: MACH | AR18: dom | AS18: 0 | AU18: MACH | AV18: 0 | AY18: MACH | AZ18: dom | BA18: AG | BB18: 0 | BE18: MACH | BF18: dom | BG18: AG | BH18: 0 | BK18: MACH | BL18: dom | BM18: 0 | BP18: MACH | BQ18: 0 | BT18: MACH | BU18: dom | BV18: 0 | BX18: MACH | BY18: 552.83399 | CA18: MACH | CB18: 982.25 | CD18: MACH | CE18: EMIRATI | CF18: 34.173652 | CH18: MACH | CI18: 0 | CL18: MACH | CM18: 0 | CP18: MACH | CQ18: 0 | CT18: MACH | CU18: AG | CV18: =OFFSET('Calculations 2'!$AJ$12,W18,X18) -> 0 | CY18: MACH | CZ18: 0.5 | DC18: MACH | DD18: 1.26 | DG18: MACH | DH18: 2 | DK18: MACH | DL18: 0.4 | DP18: MACH | DQ18: 2 | DU18: MACH | DV18: 2 | ED18: MACH | EE18: 1 | EH18: MACH | EI18: -3.6 | EQ18: MACH
A19: ELEC | C19: ELEC | H19: ELEC | I19: 6245.682 | J19: 138479.37 | K19: 144725.05 | M19: =I19/$K19 -> 0.043155499 | N19: =J19/$K19 -> 0.9568445 | Q19: ELEC | R19: dom | S19: AG | T19: =OFFSET('Calculations 2'!$C$45,W19,X19)*OFFSET($M$6,W19,0) -> 0 | V19: =V18+1 -> 13 | W19: =MOD(V19,$V$3) -> 13 | X19: =FLOOR(V19/$V$3,1) -> 0 | Z19: ELEC | AA19: 0.0027857674 | AC19: ELEC | AD19: dom | AE19: AG | AF19: =OFFSET('Calculations 2'!$CE$45,W19,0)*OFFSET($AA$6,X19,0)*OFFSET($M$6,W19,) -> 0.61919349 | AI19: ELEC | AJ19: dom | AK19: =SUM('Calculations 2'!BY58:CB58)*M19 -> 15.927874 | AN19: ELEC | AO19: 127465.51 | AQ19: ELEC | AR19: dom | AS19: 0 | AU19: ELEC | AV19: 0 | AY19: ELEC | AZ19: dom | BA19: AG | BB19: 0 | BE19: ELEC | BF19: dom | BG19: AG | BH19: 0 | BK19: ELEC | BL19: dom | BM19: 0 | BP19: ELEC | BQ19: 0 | BT19: ELEC | BU19: dom | BV19: 0 | BX19: ELEC | BY19: 901.72973 | CA19: ELEC | CB19: 685.347 | CD19: ELEC | CE19: EMIRATI | CF19: 19.647828 | CH19: ELEC | CI19: 0 | CL19: ELEC | CM19: 0 | CP19: ELEC | CQ19: 0 | CT19: ELEC | CU19: AG | CV19: =OFFSET('Calculations 2'!$AJ$12,W19,X19) -> 0 | CY19: ELEC | CZ19: 0.5 | DC19: ELEC | DD19: 1.26 | DG19: ELEC | DH19: 2 | DK19: ELEC | DL19: 0.4 | DP19: ELEC | DQ19: 2 | DU19: ELEC | DV19: 2 | ED19: ELEC | EE19: 1 | EH19: ELEC | EI19: -3.6 | EQ19: ELEC
A20: TRNEQUIP | C20: TRNEQUIP | H20: TRNEQUIP | I20: 2014.772 | J20: 49352.989 | K20: 51367.761 | M20: =I20/$K20 -> 0.0392225 | N20: =J20/$K20 -> 0.9607775 | Q20: TRNEQUIP | R20: dom | S20: AG | T20: =OFFSET('Calculations 2'!$C$45,W20,X20)*OFFSET($M$6,W20,0) -> 0 | V20: =V19+1 -> 14 | W20: =MOD(V20,$V$3) -> 14 | X20: =FLOOR(V20/$V$3,1) -> 0 | Z20: TRNEQUIP | AA20: 0.0024970438 | AC20: TRNEQUIP | AD20: dom | AE20: AG | AF20: =OFFSET('Calculations 2'!$CE$45,W20,0)*OFFSET($AA$6,X20,0)*OFFSET($M$6,W20,) -> 0.89442993 | AI20: TRNEQUIP | AJ20: dom | AK20: =SUM('Calculations 2'!BY59:CB59)*M20 -> 21.395993 | AN20: TRNEQUIP | AO20: 32111.616 | AQ20: TRNEQUIP | AR20: dom | AS20: 0 | AU20: TRNEQUIP | AV20: 0 | AY20: TRNEQUIP | AZ20: dom | BA20: AG | BB20: 0 | BE20: TRNEQUIP | BF20: dom | BG20: AG | BH20: 0 | BK20: TRNEQUIP | BL20: dom | BM20: 0 | BP20: TRNEQUIP | BQ20: 0 | BT20: TRNEQUIP | BU20: dom | BV20: 0 | BX20: TRNEQUIP | BY20: 798.31085 | CA20: TRNEQUIP | CB20: 614.316 | CD20: TRNEQUIP | CE20: EMIRATI | CF20: 7.7914024 | CH20: TRNEQUIP | CI20: 0 | CL20: TRNEQUIP | CM20: 0 | CP20: TRNEQUIP | CQ20: 0 | CT20: TRNEQUIP | CU20: AG | CV20: =OFFSET('Calculations 2'!$AJ$12,W20,X20) -> 0 | CY20: TRNEQUIP | CZ20: 0.5 | DC20: TRNEQUIP | DD20: 1.26 | DG20: TRNEQUIP | DH20: 2 | DK20: TRNEQUIP | DL20: 0.4 | DP20: TRNEQUIP | DQ20: 2 | DU20: TRNEQUIP | DV20: 2 | ED20: TRNEQUIP | EE20: 1 | EH20: TRNEQUIP | EI20: -3.6 | EQ20: TRNEQUIP
A21: ROMAN | C21: ROMAN | H21: ROMAN | I21: 13743.5 | J21: 46912.072 | K21: 60655.572 | M21: =I21/$K21 -> 0.22658265 | N21: =J21/$K21 -> 0.77341735 | Q21: ROMAN | R21: dom | S21: AG | T21: =OFFSET('Calculations 2'!$C$45,W21,X21)*OFFSET($M$6,W21,0) -> 0 | V21: =V20+1 -> 15 | W21: =MOD(V21,$V$3) -> 15 | X21: =FLOOR(V21/$V$3,1) -> 0 | Z21: ROMAN | AA21: 0.0081449839 | AC21: ROMAN | AD21: dom | AE21: AG | AF21: =OFFSET('Calculations 2'!$CE$45,W21,0)*OFFSET($AA$6,X21,0)*OFFSET($M$6,W21,) -> 2.4354747 | AI21: ROMAN | AJ21: dom | AK21: =SUM('Calculations 2'!BY60:CB60)*M21 -> 93.284318 | AN21: ROMAN | AO21: 45765.019 | AQ21: ROMAN | AR21: dom | AS21: 0 | AU21: ROMAN | AV21: 0 | AY21: ROMAN | AZ21: dom | BA21: AG | BB21: 0 | BE21: ROMAN | BF21: dom | BG21: AG | BH21: 0 | BK21: ROMAN | BL21: dom | BM21: 0 | BP21: ROMAN | BQ21: 0 | BT21: ROMAN | BU21: dom | BV21: 0 | BX21: ROMAN | BY21: 364.30454 | CA21: ROMAN | CB21: 2003.807 | CD21: ROMAN | CE21: EMIRATI | CF21: 74.587809 | CH21: ROMAN | CI21: 0 | CL21: ROMAN | CM21: 0 | CP21: ROMAN | CQ21: 0 | CT21: ROMAN | CU21: AG | CV21: =OFFSET('Calculations 2'!$AJ$12,W21,X21) -> 0 | CY21: ROMAN | CZ21: 0.5 | DC21: ROMAN | DD21: 1.26 | DG21: ROMAN | DH21: 2 | DK21: ROMAN | DL21: 0.4 | DP21: ROMAN | DQ21: 2 | DU21: ROMAN | DV21: 2 | ED21: ROMAN | EE21: 1 | EH21: ROMAN | EI21: -3.6 | EQ21: ROMAN
... A38: DWE | C38: DWE | H38: DWE | I38: 1945.3419 | J38: 0 | K38: 1945.3419 | M38: =I38/$K38 -> 1 | N38: =J38/$K38 -> 0 | Q38: DWE | R38: dom | S38: AG | T38: =OFFSET('Calculations 2'!$C$45,W38,X38)*OFFSET($M$6,W38,0) -> 0 | V38: =V37+1 -> 32 | W38: =MOD(V38,$V$3) -> 32 | X38: =FLOOR(V38/$V$3,1) -> 0 | Z38: DWE | AA38: 1.3898347e-06 | AC38: DWE | AD38: dom | AE38: AG | AF38: =OFFSET('Calculations 2'!$CE$45,W38,0)*OFFSET($AA$6,X38,0)*OFFSET($M$6,W38,) -> 0 | AI38: DWE | AJ38: dom | AK38: =SUM('Calculations 2'!BY77:CB77)*M38 -> 1945.3419 | AN38: DWE | AO38: 0 | AQ38: DWE | AR38: dom | AS38: 0 | AU38: DWE | AV38: 0 | AY38: DWE | AZ38: dom | BA38: AG | BB38: 0 | BE38: DWE | BF38: dom | BG38: AG | BH38: 0 | BK38: DWE | BL38: dom | BM38: 0 | BP38: DWE | BQ38: 0 | BT38: DWE | BU38: dom | BV38: 0 | BX38: DWE | BY38: 0 | CA38: DWE | CB38: 0.34192339 | CD38: DWE | CE38: EMIRATI | CF38: 147.79424 | CH38: DWE | CI38: 0 | CL38: DWE | CM38: 0 | CP38: DWE | CQ38: 0 | CT38: DWE | CU38: AG | CV38: =OFFSET('Calculations 2'!$AJ$12,W38,X38) -> 0 | CY38: DWE | CZ38: 0.5 | DC38: DWE | DD38: 1.26 | DG38: DWE | DH38: 2 | DK38: DWE | DL38: 0.4 | DP38: DWE | DQ38: 2 | DU38: DWE | DV38: 2 | ED38: DWE | EE38: 1 | EH38: DWE | EI38: -4 | EQ38: DWE
Q39: AG | R39: dom | S39: MIN | T39: =OFFSET('Calculations 2'!$C$45,W39,X39)*OFFSET($M$6,W39,0) -> 0 | V39: =V38+1 -> 33 | W39: =MOD(V39,$V$3) -> 0 | X39: =FLOOR(V39/$V$3,1) -> 1 | AC39: AG | AD39: dom | AE39: MIN | AF39: =OFFSET('Calculations 2'!$CE$45,W39,0)*OFFSET($AA$6,X39,0)*OFFSET($M$6,W39,) -> 0.66586338 | AI39: AG | AJ39: imp | AK39: =SUM('Calculations 2'!BY45:CB45)*N6 -> 2536.3645 | AQ39: AG | AR39: imp | AS39: {='Calculations 2'!CC45:CC77*N6:N38} -> 0 | AY39: AG | AZ39: dom | BA39: MIN | BB39: 0 | BE39: AG | BF39: dom | BG39: MIN | BH39: 0 | BK39: AG | BL39: imp | BM39: 0 | BT39: AG | BU39: imp | BV39: 0 | CD39: AG | CE39: MIGRANTHH | CF39: {=TRANSPOSE('Calculations 2'!C79:AI79)} -> 23.695215 | CT39: AG | CU39: MIN | CV39: =OFFSET('Calculations 2'!$AJ$12,W39,X39) -> 0
Q40: MIN | R40: dom | S40: MIN | T40: =OFFSET('Calculations 2'!$C$45,W40,X40)*OFFSET($M$6,W40,0) -> 49.580861 | V40: =V39+1 -> 34 | W40: =MOD(V40,$V$3) -> 1 | X40: =FLOOR(V40/$V$3,1) -> 1 | AC40: MIN | AD40: dom | AE40: MIN | AF40: =OFFSET('Calculations 2'!$CE$45,W40,0)*OFFSET($AA$6,X40,0)*OFFSET($M$6,W40,) -> 1.1615442 | AI40: MIN | AJ40: imp | AK40: =SUM('Calculations 2'!BY46:CB46)*N7 -> 475.05536 | AQ40: MIN | AR40: imp | AS40: 0 | AY40: MIN | AZ40: dom | BA40: MIN | BB40: 0 | BE40: MIN | BF40: dom | BG40: MIN | BH40: 0 | BK40: MIN | BL40: imp | BM40: 0 | BT40: MIN | BU40: imp | BV40: 0 | CD40: MIN | CE40: MIGRANTHH | CF40: 650.11793 | CT40: MIN | CU40: MIN | CV40: =OFFSET('Calculations 2'!$AJ$12,W40,X40) -> 11448.729
Q41: FBT | R41: dom | S41: MIN | T41: =OFFSET('Calculations 2'!$C$45,W41,X41)*OFFSET($M$6,W41,0) -> 0 | V41: =V40+1 -> 35 | W41: =MOD(V41,$V$3) -> 2 | X41: =FLOOR(V41/$V$3,1) -> 1 | AC41: FBT | AD41: dom | AE41: MIN | AF41: =OFFSET('Calculations 2'!$CE$45,W41,0)*OFFSET($AA$6,X41,0)*OFFSET($M$6,W41,) -> 1.9557959 | AI41: FBT | AJ41: imp | AK41: =SUM('Calculations 2'!BY47:CB47)*N8 -> 5883.6418 | AQ41: FBT | AR41: imp | AS41: 0 | AY41: FBT | AZ41: dom | BA41: MIN | BB41: 0 | BE41: FBT | BF41: dom | BG41: MIN | BH41: 0 | BK41: FBT | BL41: imp | BM41: 0 | BT41: FBT | BU41: imp | BV41: 0 | CD41: FBT | CE41: MIGRANTHH | CF41: 861.60638 | CT41: FBT | CU41: MIN | CV41: =OFFSET('Calculations 2'!$AJ$12,W41,X41) -> 0
Q42: TEX | R42: dom | S42: MIN | T42: =OFFSET('Calculations 2'!$C$45,W42,X42)*OFFSET($M$6,W42,0) -> 0 | V42: =V41+1 -> 36 | W42: =MOD(V42,$V$3) -> 3 | X42: =FLOOR(V42/$V$3,1) -> 1 | AC42: TEX | AD42: dom | AE42: MIN | AF42: =OFFSET('Calculations 2'!$CE$45,W42,0)*OFFSET($AA$6,X42,0)*OFFSET($M$6,W42,) -> 10.187457 | AI42: TEX | AJ42: imp | AK42: =SUM('Calculations 2'!BY48:CB48)*N9 -> 2415.2055 | AQ42: TEX | AR42: imp | AS42: 0 | AY42: TEX | AZ42: dom | BA42: MIN | BB42: 0 | BE42: TEX | BF42: dom | BG42: MIN | BH42: 0 | BK42: TEX | BL42: imp | BM42: 0 | BT42: TEX | BU42: imp | BV42: 0 | CD42: TEX | CE42: MIGRANTHH | CF42: 269.76131 | CT42: TEX | CU42: MIN | CV42: =OFFSET('Calculations 2'!$AJ$12,W42,X42) -> 0
Q43: LEATHER | R43: dom | S43: MIN | T43: =OFFSET('Calculations 2'!$C$45,W43,X43)*OFFSET($M$6,W43,0) -> 0 | V43: =V42+1 -> 37 | W43: =MOD(V43,$V$3) -> 4 | X43: =FLOOR(V43/$V$3,1) -> 1 | AC43: LEATHER | AD43: dom | AE43: MIN | AF43: =OFFSET('Calculations 2'!$CE$45,W43,0)*OFFSET($AA$6,X43,0)*OFFSET($M$6,W43,) -> 0.072287382 | AI43: LEATHER | AJ43: imp | AK43: =SUM('Calculations 2'!BY49:CB49)*N10 -> 1952.5284 | AQ43: LEATHER | AR43: imp | AS43: 0 | AY43: LEATHER | AZ43: dom | BA43: MIN | BB43: 0 | BE43: LEATHER | BF43: dom | BG43: MIN | BH43: 0 | BK43: LEATHER | BL43: imp | BM43: 0 | BT43: LEATHER | BU43: imp | BV43: 0 | CD43: LEATHER | CE43: MIGRANTHH | CF43: 2.4052201 | CT43: LEATHER | CU43: MIN | CV43: =OFFSET('Calculations 2'!$AJ$12,W43,X43) -> 0
Q44: WOOD | R44: dom | S44: MIN | T44: =OFFSET('Calculations 2'!$C$45,W44,X44)*OFFSET($M$6,W44,0) -> 0 | V44: =V43+1 -> 38 | W44: =MOD(V44,$V$3) -> 5 | X44: =FLOOR(V44/$V$3,1) -> 1 | AC44: WOOD | AD44: dom | AE44: MIN | AF44: =OFFSET('Calculations 2'!$CE$45,W44,0)*OFFSET($AA$6,X44,0)*OFFSET($M$6,W44,) -> 0.4450002 | AI44: WOOD | AJ44: imp | AK44: =SUM('Calculations 2'!BY50:CB50)*N11 -> 0 | AQ44: WOOD | AR44: imp | AS44: 0 | AY44: WOOD | AZ44: dom | BA44: MIN | BB44: 0 | BE44: WOOD | BF44: dom | BG44: MIN | BH44: 0 | BK44: WOOD | BL44: imp | BM44: 0 | BT44: WOOD | BU44: imp | BV44: 0 | CD44: WOOD | CE44: MIGRANTHH | CF44: 203.19907 | CT44: WOOD | CU44: MIN | CV44: =OFFSET('Calculations 2'!$AJ$12,W44,X44) -> 0
Q45: PPP | R45: dom | S45: MIN | T45: =OFFSET('Calculations 2'!$C$45,W45,X45)*OFFSET($M$6,W45,0) -> 0 | V45: =V44+1 -> 39 | W45: =MOD(V45,$V$3) -> 6 | X45: =FLOOR(V45/$V$3,1) -> 1 | AC45: PPP | AD45: dom | AE45: MIN | AF45: =OFFSET('Calculations 2'!$CE$45,W45,0)*OFFSET($AA$6,X45,0)*OFFSET($M$6,W45,) -> 8.9069554 | AI45: PPP | AJ45: imp | AK45: =SUM('Calculations 2'!BY51:CB51)*N12 -> 131.10763 | AQ45: PPP | AR45: imp | AS45: 0 | AY45: PPP | AZ45: dom | BA45: MIN | BB45: 0 | BE45: PPP | BF45: dom | BG45: MIN | BH45: 0 | BK45: PPP | BL45: imp | BM45: 0 | BT45: PPP | BU45: imp | BV45: 0 | CD45: PPP | CE45: MIGRANTHH | CF45: 416.86765 | CT45: PPP | CU45: MIN | CV45: =OFFSET('Calculations 2'!$AJ$12,W45,X45) -> 0
Q46: PC | R46: dom | S46: MIN | T46: =OFFSET('Calculations 2'!$C$45,W46,X46)*OFFSET($M$6,W46,0) -> 181.03496 | V46: =V45+1 -> 40 | W46: =MOD(V46,$V$3) -> 7 | X46: =FLOOR(V46/$V$3,1) -> 1 | AC46: PC | AD46: dom | AE46: MIN | AF46: =OFFSET('Calculations 2'!$CE$45,W46,0)*OFFSET($AA$6,X46,0)*OFFSET($M$6,W46,) -> 1.3572476 | AI46: PC | AJ46: imp | AK46: =SUM('Calculations 2'!BY52:CB52)*N13 -> 1144.6491 | AQ46: PC | AR46: imp | AS46: 0 | AY46: PC | AZ46: dom | BA46: MIN | BB46: 0 | BE46: PC | BF46: dom | BG46: MIN | BH46: 0 | BK46: PC | BL46: imp | BM46: 0 | BT46: PC | BU46: imp | BV46: 0 | CD46: PC | CE46: MIGRANTHH | CF46: 83.350803 | CT46: PC | CU46: MIN | CV46: =OFFSET('Calculations 2'!$AJ$12,W46,X46) -> 0
Q47: CHM | R47: dom | S47: MIN | T47: =OFFSET('Calculations 2'!$C$45,W47,X47)*OFFSET($M$6,W47,0) -> 0 | V47: =V46+1 -> 41 | W47: =MOD(V47,$V$3) -> 8 | X47: =FLOOR(V47/$V$3,1) -> 1 | AC47: CHM | AD47: dom | AE47: MIN | AF47: =OFFSET('Calculations 2'!$CE$45,W47,0)*OFFSET($AA$6,X47,0)*OFFSET($M$6,W47,) -> 8.4518583 | AI47: CHM | AJ47: imp | AK47: =SUM('Calculations 2'!BY53:CB53)*N14 -> 2010.9261 | AQ47: CHM | AR47: imp | AS47: 0 | AY47: CHM | AZ47: dom | BA47: MIN | BB47: 0 | BE47: CHM | BF47: dom | BG47: MIN | BH47: 0 | BK47: CHM | BL47: imp | BM47: 0 | BT47: CHM | BU47: imp | BV47: 0 | CD47: CHM | CE47: MIGRANTHH | CF47: 501.17719 | CT47: CHM | CU47: MIN | CV47: =OFFSET('Calculations 2'!$AJ$12,W47,X47) -> 0
Q48: RUBBER | R48: dom | S48: MIN | T48: =OFFSET('Calculations 2'!$C$45,W48,X48)*OFFSET($M$6,W48,0) -> 0 | V48: =V47+1 -> 42 | W48: =MOD(V48,$V$3) -> 9 | X48: =FLOOR(V48/$V$3,1) -> 1 | AC48: RUBBER | AD48: dom | AE48: MIN | AF48: =OFFSET('Calculations 2'!$CE$45,W48,0)*OFFSET($AA$6,X48,0)*OFFSET($M$6,W48,) -> 13.230569 | AI48: RUBBER | AJ48: imp | AK48: =SUM('Calculations 2'!BY54:CB54)*N15 -> 4.8554712 | AQ48: RUBBER | AR48: imp | AS48: 0 | AY48: RUBBER | AZ48: dom | BA48: MIN | BB48: 0 | BE48: RUBBER | BF48: dom | BG48: MIN | BH48: 0 | BK48: RUBBER | BL48: imp | BM48: 0 | BT48: RUBBER | BU48: imp | BV48: 0 | CD48: RUBBER | CE48: MIGRANTHH | CF48: 226.39843 | CT48: RUBBER | CU48: MIN | CV48: =OFFSET('Calculations 2'!$AJ$12,W48,X48) -> 0
Q49: NMM | R49: dom | S49: MIN | T49: =OFFSET('Calculations 2'!$C$45,W49,X49)*OFFSET($M$6,W49,0) -> 0 | V49: =V48+1 -> 43 | W49: =MOD(V49,$V$3) -> 10 | X49: =FLOOR(V49/$V$3,1) -> 1 | AC49: NMM | AD49: dom | AE49: MIN | AF49: =OFFSET('Calculations 2'!$CE$45,W49,0)*OFFSET($AA$6,X49,0)*OFFSET($M$6,W49,) -> 12.256478 | AI49: NMM | AJ49: imp | AK49: =SUM('Calculations 2'!BY55:CB55)*N16 -> 38.564875 | AQ49: NMM | AR49: imp | AS49: 0 | AY49: NMM | AZ49: dom | BA49: MIN | BB49: 0 | BE49: NMM | BF49: dom | BG49: MIN | BH49: 0 | BK49: NMM | BL49: imp | BM49: 0 | BT49: NMM | BU49: imp | BV49: 0 | CD49: NMM | CE49: MIGRANTHH | CF49: 548.56656 | CT49: NMM | CU49: MIN | CV49: =OFFSET('Calculations 2'!$AJ$12,W49,X49) -> 0
Q50: METAL | R50: dom | S50: MIN | T50: =OFFSET('Calculations 2'!$C$45,W50,X50)*OFFSET($M$6,W50,0) -> 0 | V50: =V49+1 -> 44 | W50: =MOD(V50,$V$3) -> 11 | X50: =FLOOR(V50/$V$3,1) -> 1 | AC50: METAL | AD50: dom | AE50: MIN | AF50: =OFFSET('Calculations 2'!$CE$45,W50,0)*OFFSET($AA$6,X50,0)*OFFSET($M$6,W50,) -> 35.848079 | AI50: METAL | AJ50: imp | AK50: =SUM('Calculations 2'!BY56:CB56)*N17 -> 72.569987 | AQ50: METAL | AR50: imp | AS50: 0 | AY50: METAL | AZ50: dom | BA50: MIN | BB50: 0 | BE50: METAL | BF50: dom | BG50: MIN | BH50: 0 | BK50: METAL | BL50: imp | BM50: 0 | BT50: METAL | BU50: imp | BV50: 0 | CD50: METAL | CE50: MIGRANTHH | CF50: 1303.9972 | CT50: METAL | CU50: MIN | CV50: =OFFSET('Calculations 2'!$AJ$12,W50,X50) -> 0
Q51: MACH | R51: dom | S51: MIN | T51: =OFFSET('Calculations 2'!$C$45,W51,X51)*OFFSET($M$6,W51,0) -> 0 | V51: =V50+1 -> 45 | W51: =MOD(V51,$V$3) -> 12 | X51: =FLOOR(V51/$V$3,1) -> 1 | AC51: MACH | AD51: dom | AE51: MIN | AF51: =OFFSET('Calculations 2'!$CE$45,W51,0)*OFFSET($AA$6,X51,0)*OFFSET($M$6,W51,) -> 51.887268 | AI51: MACH | AJ51: imp | AK51: =SUM('Calculations 2'!BY57:CB57)*N18 -> 21.257563 | AQ51: MACH | AR51: imp | AS51: 0 | AY51: MACH | AZ51: dom | BA51: MIN | BB51: 0 | BE51: MACH | BF51: dom | BG51: MIN | BH51: 0 | BK51: MACH | BL51: imp | BM51: 0 | BT51: MACH | BU51: imp | BV51: 0 | CD51: MACH | CE51: MIGRANTHH | CF51: 425.62606 | CT51: MACH | CU51: MIN | CV51: =OFFSET('Calculations 2'!$AJ$12,W51,X51) -> 0
... Q71: DWE | R71: dom | S71: MIN | T71: =OFFSET('Calculations 2'!$C$45,W71,X71)*OFFSET($M$6,W71,0) -> 0 | V71: =V70+1 -> 65 | W71: =MOD(V71,$V$3) -> 32 | X71: =FLOOR(V71/$V$3,1) -> 1 | AC71: DWE | AD71: dom | AE71: MIN | AF71: =OFFSET('Calculations 2'!$CE$45,W71,0)*OFFSET($AA$6,X71,0)*OFFSET($M$6,W71,) -> 0 | AI71: DWE | AJ71: imp | AK71: =SUM('Calculations 2'!BY77:CB77)*N38 -> 0 | AQ71: DWE | AR71: imp | AS71: 0 | AY71: DWE | AZ71: dom | BA71: MIN | BB71: 0 | BE71: DWE | BF71: dom | BG71: MIN | BH71: 0 | BK71: DWE | BL71: imp | BM71: 0 | BT71: DWE | BU71: imp | BV71: 0 | CD71: DWE | CE71: MIGRANTHH | CF71: 1275.7365 | CT71: DWE | CU71: MIN | CV71: =OFFSET('Calculations 2'!$AJ$12,W71,X71) -> 0
Q72: AG | R72: dom | S72: FBT | T72: =OFFSET('Calculations 2'!$C$45,W72,X72)*OFFSET($M$6,W72,0) -> 203.88011 | V72: =V71+1 -> 66 | W72: =MOD(V72,$V$3) -> 0 | X72: =FLOOR(V72/$V$3,1) -> 2 | AC72: AG | AD72: dom | AE72: FBT | AF72: =OFFSET('Calculations 2'!$CE$45,W72,0)*OFFSET($AA$6,X72,0)*OFFSET($M$6,W72,) -> 0.31347556 | AY72: AG | AZ72: dom | BA72: FBT | BB72: 0 | BE72: AG | BF72: dom | BG72: FBT | BH72: 0 | CD72: AG | CE72: MIGRANTCOMB | CF72: {=TRANSPOSE('Calculations 2'!C80:AI80)} -> 132.08054 | CT72: AG | CU72: FBT | CV72: =OFFSET('Calculations 2'!$AJ$12,W72,X72) -> 0
Q73: MIN | R73: dom | S73: FBT | T73: =OFFSET('Calculations 2'!$C$45,W73,X73)*OFFSET($M$6,W73,0) -> 7.7002252 | V73: =V72+1 -> 67 | W73: =MOD(V73,$V$3) -> 1 | X73: =FLOOR(V73/$V$3,1) -> 2 | AC73: MIN | AD73: dom | AE73: FBT | AF73: =OFFSET('Calculations 2'!$CE$45,W73,0)*OFFSET($AA$6,X73,0)*OFFSET($M$6,W73,) -> 0.54683248 | AY73: MIN | AZ73: dom | BA73: FBT | BB73: 0 | BE73: MIN | BF73: dom | BG73: FBT | BH73: 0 | CD73: MIN | CE73: MIGRANTCOMB | CF73: 167.09936 | CT73: MIN | CU73: FBT | CV73: =OFFSET('Calculations 2'!$AJ$12,W73,X73) -> 0
Q74: FBT | R74: dom | S74: FBT | T74: =OFFSET('Calculations 2'!$C$45,W74,X74)*OFFSET($M$6,W74,0) -> 3134.5643 | V74: =V73+1 -> 68 | W74: =MOD(V74,$V$3) -> 2 | X74: =FLOOR(V74/$V$3,1) -> 2 | AC74: FBT | AD74: dom | AE74: FBT | AF74: =OFFSET('Calculations 2'!$CE$45,W74,0)*OFFSET($AA$6,X74,0)*OFFSET($M$6,W74,) -> 0.92075075 | AY74: FBT | AZ74: dom | BA74: FBT | BB74: 0 | BE74: FBT | BF74: dom | BG74: FBT | BH74: 0 | CD74: FBT | CE74: MIGRANTCOMB | CF74: 994.88488 | CT74: FBT | CU74: FBT | CV74: =OFFSET('Calculations 2'!$AJ$12,W74,X74) -> 25557.719
Q75: TEX | R75: dom | S75: FBT | T75: =OFFSET('Calculations 2'!$C$45,W75,X75)*OFFSET($M$6,W75,0) -> 5.2170992 | V75: =V74+1 -> 69 | W75: =MOD(V75,$V$3) -> 3 | X75: =FLOOR(V75/$V$3,1) -> 2 | AC75: TEX | AD75: dom | AE75: FBT | AF75: =OFFSET('Calculations 2'!$CE$45,W75,0)*OFFSET($AA$6,X75,0)*OFFSET($M$6,W75,) -> 4.7960573 | AY75: TEX | AZ75: dom | BA75: FBT | BB75: 0 | BE75: TEX | BF75: dom | BG75: FBT | BH75: 0 | CD75: TEX | CE75: MIGRANTCOMB | CF75: 311.48962 | CT75: TEX | CU75: FBT | CV75: =OFFSET('Calculations 2'!$AJ$12,W75,X75) -> 0
Q76: LEATHER | R76: dom | S76: FBT | T76: =OFFSET('Calculations 2'!$C$45,W76,X76)*OFFSET($M$6,W76,0) -> 0 | V76: =V75+1 -> 70 | W76: =MOD(V76,$V$3) -> 4 | X76: =FLOOR(V76/$V$3,1) -> 2 | AC76: LEATHER | AD76: dom | AE76: FBT | AF76: =OFFSET('Calculations 2'!$CE$45,W76,0)*OFFSET($AA$6,X76,0)*OFFSET($M$6,W76,) -> 0.034031497 | AY76: LEATHER | AZ76: dom | BA76: FBT | BB76: 0 | BE76: LEATHER | BF76: dom | BG76: FBT | BH76: 0 | CD76: LEATHER | CE76: MIGRANTCOMB | CF76: 2.7772738 | CT76: LEATHER | CU76: FBT | CV76: =OFFSET('Calculations 2'!$AJ$12,W76,X76) -> 0
Q77: WOOD | R77: dom | S77: FBT | T77: =OFFSET('Calculations 2'!$C$45,W77,X77)*OFFSET($M$6,W77,0) -> 0 | V77: =V76+1 -> 71 | W77: =MOD(V77,$V$3) -> 5 | X77: =FLOOR(V77/$V$3,1) -> 2 | AC77: WOOD | AD77: dom | AE77: FBT | AF77: =OFFSET('Calculations 2'!$CE$45,W77,0)*OFFSET($AA$6,X77,0)*OFFSET($M$6,W77,) -> 0.20949746 | AY77: WOOD | AZ77: dom | BA77: FBT | BB77: 0 | BE77: WOOD | BF77: dom | BG77: FBT | BH77: 0 | CD77: WOOD | CE77: MIGRANTCOMB | CF77: 234.63114 | CT77: WOOD | CU77: FBT | CV77: =OFFSET('Calculations 2'!$AJ$12,W77,X77) -> 0
Q78: PPP | R78: dom | S78: FBT | T78: =OFFSET('Calculations 2'!$C$45,W78,X78)*OFFSET($M$6,W78,0) -> 113.43713 | V78: =V77+1 -> 72 | W78: =MOD(V78,$V$3) -> 6 | X78: =FLOOR(V78/$V$3,1) -> 2 | AC78: PPP | AD78: dom | AE78: FBT | AF78: =OFFSET('Calculations 2'!$CE$45,W78,0)*OFFSET($AA$6,X78,0)*OFFSET($M$6,W78,) -> 4.1932218 | AY78: PPP | AZ78: dom | BA78: FBT | BB78: 0 | BE78: PPP | BF78: dom | BG78: FBT | BH78: 0 | CD78: PPP | CE78: MIGRANTCOMB | CF78: 481.35129 | CT78: PPP | CU78: FBT | CV78: =OFFSET('Calculations 2'!$AJ$12,W78,X78) -> 0
Q79: PC | R79: dom | S79: FBT | T79: =OFFSET('Calculations 2'!$C$45,W79,X79)*OFFSET($M$6,W79,0) -> 151.36281 | V79: =V78+1 -> 73 | W79: =MOD(V79,$V$3) -> 7 | X79: =FLOOR(V79/$V$3,1) -> 2 | AC79: PC | AD79: dom | AE79: FBT | AF79: =OFFSET('Calculations 2'!$CE$45,W79,0)*OFFSET($AA$6,X79,0)*OFFSET($M$6,W79,) -> 0.63896585 | AY79: PC | AZ79: dom | BA79: FBT | BB79: 0 | BE79: PC | BF79: dom | BG79: FBT | BH79: 0 | CD79: PC | CE79: MIGRANTCOMB | CF79: 96.24401 | CT79: PC | CU79: FBT | CV79: =OFFSET('Calculations 2'!$AJ$12,W79,X79) -> 0
Q80: CHM | R80: dom | S80: FBT | T80: =OFFSET('Calculations 2'!$C$45,W80,X80)*OFFSET($M$6,W80,0) -> 20.027406 | V80: =V79+1 -> 74 | W80: =MOD(V80,$V$3) -> 8 | X80: =FLOOR(V80/$V$3,1) -> 2 | AC80: CHM | AD80: dom | AE80: FBT | AF80: =OFFSET('Calculations 2'!$CE$45,W80,0)*OFFSET($AA$6,X80,0)*OFFSET($M$6,W80,) -> 3.9789709 | AY80: CHM | AZ80: dom | BA80: FBT | BB80: 0 | BE80: CHM | BF80: dom | BG80: FBT | BH80: 0 | CD80: CHM | CE80: MIGRANTCOMB | CF80: 578.70234 | CT80: CHM | CU80: FBT | CV80: =OFFSET('Calculations 2'!$AJ$12,W80,X80) -> 0
Q81: RUBBER | R81: dom | S81: FBT | T81: =OFFSET('Calculations 2'!$C$45,W81,X81)*OFFSET($M$6,W81,0) -> 453.56768 | V81: =V80+1 -> 75 | W81: =MOD(V81,$V$3) -> 9 | X81: =FLOOR(V81/$V$3,1) -> 2 | AC81: RUBBER | AD81: dom | AE81: FBT | AF81: =OFFSET('Calculations 2'!$CE$45,W81,0)*OFFSET($AA$6,X81,0)*OFFSET($M$6,W81,) -> 6.2286953 | AY81: RUBBER | AZ81: dom | BA81: FBT | BB81: 0 | BE81: RUBBER | BF81: dom | BG81: FBT | BH81: 0 | CD81: RUBBER | CE81: MIGRANTCOMB | CF81: 261.41915 | CT81: RUBBER | CU81: FBT | CV81: =OFFSET('Calculations 2'!$AJ$12,W81,X81) -> 0
Q82: NMM | R82: dom | S82: FBT | T82: =OFFSET('Calculations 2'!$C$45,W82,X82)*OFFSET($M$6,W82,0) -> 2.0643592 | V82: =V81+1 -> 76 | W82: =MOD(V82,$V$3) -> 10 | X82: =FLOOR(V82/$V$3,1) -> 2 | AC82: NMM | AD82: dom | AE82: FBT | AF82: =OFFSET('Calculations 2'!$CE$45,W82,0)*OFFSET($AA$6,X82,0)*OFFSET($M$6,W82,) -> 5.770112 | AY82: NMM | AZ82: dom | BA82: FBT | BB82: 0 | BE82: NMM | BF82: dom | BG82: FBT | BH82: 0 | CD82: NMM | CE82: MIGRANTCOMB | CF82: 633.42218 | CT82: NMM | CU82: FBT | CV82: =OFFSET('Calculations 2'!$AJ$12,W82,X82) -> 0
Q83: METAL | R83: dom | S83: FBT | T83: =OFFSET('Calculations 2'!$C$45,W83,X83)*OFFSET($M$6,W83,0) -> 3.5473463 | V83: =V82+1 -> 77 | W83: =MOD(V83,$V$3) -> 11 | X83: =FLOOR(V83/$V$3,1) -> 2 | AC83: METAL | AD83: dom | AE83: FBT | AF83: =OFFSET('Calculations 2'!$CE$45,W83,0)*OFFSET($AA$6,X83,0)*OFFSET($M$6,W83,) -> 16.87658 | AY83: METAL | AZ83: dom | BA83: FBT | BB83: 0 | BE83: METAL | BF83: dom | BG83: FBT | BH83: 0 | CD83: METAL | CE83: MIGRANTCOMB | CF83: 1505.7074 | CT83: METAL | CU83: FBT | CV83: =OFFSET('Calculations 2'!$AJ$12,W83,X83) -> 0
Q84: MACH | R84: dom | S84: FBT | T84: =OFFSET('Calculations 2'!$C$45,W84,X84)*OFFSET($M$6,W84,0) -> 12.969049 | V84: =V83+1 -> 78 | W84: =MOD(V84,$V$3) -> 12 | X84: =FLOOR(V84/$V$3,1) -> 2 | AC84: MACH | AD84: dom | AE84: FBT | AF84: =OFFSET('Calculations 2'!$CE$45,W84,0)*OFFSET($AA$6,X84,0)*OFFSET($M$6,W84,) -> 24.427519 | AY84: MACH | AZ84: dom | BA84: FBT | BB84: 0 | BE84: MACH | BF84: dom | BG84: FBT | BH84: 0 | CD84: MACH | CE84: MIGRANTCOMB | CF84: 491.46448 | CT84: MACH | CU84: FBT | CV84: =OFFSET('Calculations 2'!$AJ$12,W84,X84) -> 0
... Q104: DWE | R104: dom | S104: FBT | T104: =OFFSET('Calculations 2'!$C$45,W104,X104)*OFFSET($M$6,W104,0) -> 0 | V104: =V103+1 -> 98 | W104: =MOD(V104,$V$3) -> 32 | X104: =FLOOR(V104/$V$3,1) -> 2 | AC104: DWE | AD104: dom | AE104: FBT | AF104: =OFFSET('Calculations 2'!$CE$45,W104,0)*OFFSET($AA$6,X104,0)*OFFSET($M$6,W104,) -> 0 | AY104: DWE | AZ104: dom | BA104: FBT | BB104: 0 | BE104: DWE | BF104: dom | BG104: FBT | BH104: 0 | CD104: DWE | CE104: MIGRANTCOMB | CF104: 4.0321788 | CT104: DWE | CU104: FBT | CV104: =OFFSET('Calculations 2'!$AJ$12,W104,X104) -> 0
Q105: AG | R105: dom | S105: TEX | T105: =OFFSET('Calculations 2'!$C$45,W105,X105)*OFFSET($M$6,W105,0) -> 0.055519873 | V105: =V104+1 -> 99 | W105: =MOD(V105,$V$3) -> 0 | X105: =FLOOR(V105/$V$3,1) -> 3 | AC105: AG | AD105: dom | AE105: TEX | AF105: =OFFSET('Calculations 2'!$CE$45,W105,0)*OFFSET($AA$6,X105,0)*OFFSET($M$6,W105,) -> 0.074931037 | AY105: AG | AZ105: dom | BA105: TEX | BB105: 0 | BE105: AG | BF105: dom | BG105: TEX | BH105: 0 | CD105: AG | CE105: COMMUTING | CF105: {=TRANSPOSE('Calculations 2'!C81:AI81)} -> 62.983383 | CT105: AG | CU105: TEX | CV105: =OFFSET('Calculations 2'!$AJ$12,W105,X105) -> 0
Q106: MIN | R106: dom | S106: TEX | T106: =OFFSET('Calculations 2'!$C$45,W106,X106)*OFFSET($M$6,W106,0) -> 0 | V106: =V105+1 -> 100 | W106: =MOD(V106,$V$3) -> 1 | X106: =FLOOR(V106/$V$3,1) -> 3 | AC106: MIN | AD106: dom | AE106: TEX | AF106: =OFFSET('Calculations 2'!$CE$45,W106,0)*OFFSET($AA$6,X106,0)*OFFSET($M$6,W106,) -> 0.13071107 | AY106: MIN | AZ106: dom | BA106: TEX | BB106: 0 | BE106: MIN | BF106: dom | BG106: TEX | BH106: 0 | CD106: MIN | CE106: COMMUTING | CF106: 330.41798 | CT106: MIN | CU106: TEX | CV106: =OFFSET('Calculations 2'!$AJ$12,W106,X106) -> 0
Q107: FBT | R107: dom | S107: TEX | T107: =OFFSET('Calculations 2'!$C$45,W107,X107)*OFFSET($M$6,W107,0) -> 0 | V107: =V106+1 -> 101 | W107: =MOD(V107,$V$3) -> 2 | X107: =FLOOR(V107/$V$3,1) -> 3 | AC107: FBT | AD107: dom | AE107: TEX | AF107: =OFFSET('Calculations 2'!$CE$45,W107,0)*OFFSET($AA$6,X107,0)*OFFSET($M$6,W107,) -> 0.22008991 | AY107: FBT | AZ107: dom | BA107: TEX | BB107: 0 | BE107: FBT | BF107: dom | BG107: TEX | BH107: 0 | CD107: FBT | CE107: COMMUTING | CF107: 750.61809 | CT107: FBT | CU107: TEX | CV107: =OFFSET('Calculations 2'!$AJ$12,W107,X107) -> 0
Q108: TEX | R108: dom | S108: TEX | T108: =OFFSET('Calculations 2'!$C$45,W108,X108)*OFFSET($M$6,W108,0) -> 108.46761 | V108: =V107+1 -> 102 | W108: =MOD(V108,$V$3) -> 3 | X108: =FLOOR(V108/$V$3,1) -> 3 | AC108: TEX | AD108: dom | AE108: TEX | AF108: =OFFSET('Calculations 2'!$CE$45,W108,0)*OFFSET($AA$6,X108,0)*OFFSET($M$6,W108,) -> 1.1464165 | AY108: TEX | AZ108: dom | BA108: TEX | BB108: 0 | BE108: TEX | BF108: dom | BG108: TEX | BH108: 0 | CD108: TEX | CE108: COMMUTING | CF108: 235.01186 | CT108: TEX | CU108: TEX | CV108: =OFFSET('Calculations 2'!$AJ$12,W108,X108) -> 3421.037
Q109: LEATHER | R109: dom | S109: TEX | T109: =OFFSET('Calculations 2'!$C$45,W109,X109)*OFFSET($M$6,W109,0) -> 9.397117e-05 | V109: =V108+1 -> 103 | W109: =MOD(V109,$V$3) -> 4 | X109: =FLOOR(V109/$V$3,1) -> 3 | AC109: LEATHER | AD109: dom | AE109: TEX | AF109: =OFFSET('Calculations 2'!$CE$45,W109,0)*OFFSET($AA$6,X109,0)*OFFSET($M$6,W109,) -> 0.0081346545 | AY109: LEATHER | AZ109: dom | BA109: TEX | BB109: 0 | BE109: LEATHER | BF109: dom | BG109: TEX | BH109: 0 | CD109: LEATHER | CE109: COMMUTING | CF109: 2.0953902 | CT109: LEATHER | CU109: TEX | CV109: =OFFSET('Calculations 2'!$AJ$12,W109,X109) -> 0
Q110: WOOD | R110: dom | S110: TEX | T110: =OFFSET('Calculations 2'!$C$45,W110,X110)*OFFSET($M$6,W110,0) -> 0 | V110: =V109+1 -> 104 | W110: =MOD(V110,$V$3) -> 5 | X110: =FLOOR(V110/$V$3,1) -> 3 | AC110: WOOD | AD110: dom | AE110: TEX | AF110: =OFFSET('Calculations 2'!$CE$45,W110,0)*OFFSET($AA$6,X110,0)*OFFSET($M$6,W110,) -> 0.050076829 | AY110: WOOD | AZ110: dom | BA110: TEX | BB110: 0 | BE110: WOOD | BF110: dom | BG110: TEX | BH110: 0 | CD110: WOOD | CE110: COMMUTING | CF110: 177.02387 | CT110: WOOD | CU110: TEX | CV110: =OFFSET('Calculations 2'!$AJ$12,W110,X110) -> 0
Q111: PPP | R111: dom | S111: TEX | T111: =OFFSET('Calculations 2'!$C$45,W111,X111)*OFFSET($M$6,W111,0) -> 2.7152884 | V111: =V110+1 -> 105 | W111: =MOD(V111,$V$3) -> 6 | X111: =FLOOR(V111/$V$3,1) -> 3 | AC111: PPP | AD111: dom | AE111: TEX | AF111: =OFFSET('Calculations 2'!$CE$45,W111,0)*OFFSET($AA$6,X111,0)*OFFSET($M$6,W111,) -> 1.0023188 | AY111: PPP | AZ111: dom | BA111: TEX | BB111: 0 | BE111: PPP | BF111: dom | BG111: TEX | BH111: 0 | CD111: PPP | CE111: COMMUTING | CF111: 363.16863 | CT111: PPP | CU111: TEX | CV111: =OFFSET('Calculations 2'!$AJ$12,W111,X111) -> 0
Q112: PC | R112: dom | S112: TEX | T112: =OFFSET('Calculations 2'!$C$45,W112,X112)*OFFSET($M$6,W112,0) -> 2.7215181 | V112: =V111+1 -> 106 | W112: =MOD(V112,$V$3) -> 7 | X112: =FLOOR(V112/$V$3,1) -> 3 | AC112: PC | AD112: dom | AE112: TEX | AF112: =OFFSET('Calculations 2'!$CE$45,W112,0)*OFFSET($AA$6,X112,0)*OFFSET($M$6,W112,) -> 0.15273399 | AY112: PC | AZ112: dom | BA112: TEX | BB112: 0 | BE112: PC | BF112: dom | BG112: TEX | BH112: 0 | CD112: PC | CE112: COMMUTING | CF112: 72.613924 | CT112: PC | CU112: TEX | CV112: =OFFSET('Calculations 2'!$AJ$12,W112,X112) -> 0
Q113: CHM | R113: dom | S113: TEX | T113: =OFFSET('Calculations 2'!$C$45,W113,X113)*OFFSET($M$6,W113,0) -> 0.40139675 | V113: =V112+1 -> 107 | W113: =MOD(V113,$V$3) -> 8 | X113: =FLOOR(V113/$V$3,1) -> 3 | AC113: CHM | AD113: dom | AE113: TEX | AF113: =OFFSET('Calculations 2'!$CE$45,W113,0)*OFFSET($AA$6,X113,0)*OFFSET($M$6,W113,) -> 0.95110578 | AY113: CHM | AZ113: dom | BA113: TEX | BB113: 0 | BE113: CHM | BF113: dom | BG113: TEX | BH113: 0 | CD113: CHM | CE113: COMMUTING | CF113: 436.61779 | CT113: CHM | CU113: TEX | CV113: =OFFSET('Calculations 2'!$AJ$12,W113,X113) -> 0
Q114: RUBBER | R114: dom | S114: TEX | T114: =OFFSET('Calculations 2'!$C$45,W114,X114)*OFFSET($M$6,W114,0) -> 11.056506 | V114: =V113+1 -> 108 | W114: =MOD(V114,$V$3) -> 9 | X114: =FLOOR(V114/$V$3,1) -> 3 | AC114: RUBBER | AD114: dom | AE114: TEX | AF114: =OFFSET('Calculations 2'!$CE$45,W114,0)*OFFSET($AA$6,X114,0)*OFFSET($M$6,W114,) -> 1.4888644 | AY114: RUBBER | AZ114: dom | BA114: TEX | BB114: 0 | BE114: RUBBER | BF114: dom | BG114: TEX | BH114: 0 | CD114: RUBBER | CE114: COMMUTING | CF114: 197.23481 | CT114: RUBBER | CU114: TEX | CV114: =OFFSET('Calculations 2'!$AJ$12,W114,X114) -> 0
Q115: NMM | R115: dom | S115: TEX | T115: =OFFSET('Calculations 2'!$C$45,W115,X115)*OFFSET($M$6,W115,0) -> 5.3084574 | V115: =V114+1 -> 109 | W115: =MOD(V115,$V$3) -> 10 | X115: =FLOOR(V115/$V$3,1) -> 3 | AC115: NMM | AD115: dom | AE115: TEX | AF115: =OFFSET('Calculations 2'!$CE$45,W115,0)*OFFSET($AA$6,X115,0)*OFFSET($M$6,W115,) -> 1.3792478 | AY115: NMM | AZ115: dom | BA115: TEX | BB115: 0 | BE115: NMM | BF115: dom | BG115: TEX | BH115: 0 | CD115: NMM | CE115: COMMUTING | CF115: 477.90267 | CT115: NMM | CU115: TEX | CV115: =OFFSET('Calculations 2'!$AJ$12,W115,X115) -> 0
Q116: METAL | R116: dom | S116: TEX | T116: =OFFSET('Calculations 2'!$C$45,W116,X116)*OFFSET($M$6,W116,0) -> 19.395605 | V116: =V115+1 -> 110 | W116: =MOD(V116,$V$3) -> 11 | X116: =FLOOR(V116/$V$3,1) -> 3 | AC116: METAL | AD116: dom | AE116: TEX | AF116: =OFFSET('Calculations 2'!$CE$45,W116,0)*OFFSET($AA$6,X116,0)*OFFSET($M$6,W116,) -> 4.0340613 | AY116: METAL | AZ116: dom | BA116: TEX | BB116: 0 | BE116: METAL | BF116: dom | BG116: TEX | BH116: 0 | CD116: METAL | CE116: COMMUTING | CF116: 1136.0221 | CT116: METAL | CU116: TEX | CV116: =OFFSET('Calculations 2'!$AJ$12,W116,X116) -> 0
Q117: MACH | R117: dom | S117: TEX | T117: =OFFSET('Calculations 2'!$C$45,W117,X117)*OFFSET($M$6,W117,0) -> 0.20582256 | V117: =V116+1 -> 111 | W117: =MOD(V117,$V$3) -> 12 | X117: =FLOOR(V117/$V$3,1) -> 3 | AC117: MACH | AD117: dom | AE117: TEX | AF117: =OFFSET('Calculations 2'!$CE$45,W117,0)*OFFSET($AA$6,X117,0)*OFFSET($M$6,W117,) -> 5.8389858 | AY117: MACH | AZ117: dom | BA117: TEX | BB117: 0 | BE117: MACH | BF117: dom | BG117: TEX | BH117: 0 | CD117: MACH | CE117: COMMUTING | CF117: 370.79881 | CT117: MACH | CU117: TEX | CV117: =OFFSET('Calculations 2'!$AJ$12,W117,X117) -> 0
... Q137: DWE | R137: dom | S137: TEX | T137: =OFFSET('Calculations 2'!$C$45,W137,X137)*OFFSET($M$6,W137,0) -> 0 | V137: =V136+1 -> 131 | W137: =MOD(V137,$V$3) -> 32 | X137: =FLOOR(V137/$V$3,1) -> 3 | AC137: DWE | AD137: dom | AE137: TEX | AF137: =OFFSET('Calculations 2'!$CE$45,W137,0)*OFFSET($AA$6,X137,0)*OFFSET($M$6,W137,) -> 0 | AY137: DWE | AZ137: dom | BA137: TEX | BB137: 0 | BE137: DWE | BF137: dom | BG137: TEX | BH137: 0 | CD137: DWE | CE137: COMMUTING | CF137: 517.43712 | CT137: DWE | CU137: TEX | CV137: =OFFSET('Calculations 2'!$AJ$12,W137,X137) -> 0
Q138: AG | R138: dom | S138: LEATHER | T138: =OFFSET('Calculations 2'!$C$45,W138,X138)*OFFSET($M$6,W138,0) -> 0 | V138: =V137+1 -> 132 | W138: =MOD(V138,$V$3) -> 0 | X138: =FLOOR(V138/$V$3,1) -> 4 | AC138: AG | AD138: dom | AE138: LEATHER | AF138: =OFFSET('Calculations 2'!$CE$45,W138,0)*OFFSET($AA$6,X138,0)*OFFSET($M$6,W138,) -> 0.00035153656 | AY138: AG | AZ138: dom | BA138: LEATHER | BB138: 0 | BE138: AG | BF138: dom | BG138: LEATHER | BH138: 0 | CT138: AG | CU138: LEATHER | CV138: =OFFSET('Calculations 2'!$AJ$12,W138,X138) -> 0
Q139: MIN | R139: dom | S139: LEATHER | T139: =OFFSET('Calculations 2'!$C$45,W139,X139)*OFFSET($M$6,W139,0) -> 0 | V139: =V138+1 -> 133 | W139: =MOD(V139,$V$3) -> 1 | X139: =FLOOR(V139/$V$3,1) -> 4 | AC139: MIN | AD139: dom | AE139: LEATHER | AF139: =OFFSET('Calculations 2'!$CE$45,W139,0)*OFFSET($AA$6,X139,0)*OFFSET($M$6,W139,) -> 0.00061322679 | AY139: MIN | AZ139: dom | BA139: LEATHER | BB139: 0 | BE139: MIN | BF139: dom | BG139: LEATHER | BH139: 0 | CT139: MIN | CU139: LEATHER | CV139: =OFFSET('Calculations 2'!$AJ$12,W139,X139) -> 0
Q140: FBT | R140: dom | S140: LEATHER | T140: =OFFSET('Calculations 2'!$C$45,W140,X140)*OFFSET($M$6,W140,0) -> 0 | V140: =V139+1 -> 134 | W140: =MOD(V140,$V$3) -> 2 | X140: =FLOOR(V140/$V$3,1) -> 4 | AC140: FBT | AD140: dom | AE140: LEATHER | AF140: =OFFSET('Calculations 2'!$CE$45,W140,0)*OFFSET($AA$6,X140,0)*OFFSET($M$6,W140,) -> 0.0010325448 | AY140: FBT | AZ140: dom | BA140: LEATHER | BB140: 0 | BE140: FBT | BF140: dom | BG140: LEATHER | BH140: 0 | CT140: FBT | CU140: LEATHER | CV140: =OFFSET('Calculations 2'!$AJ$12,W140,X140) -> 0
Q141: TEX | R141: dom | S141: LEATHER | T141: =OFFSET('Calculations 2'!$C$45,W141,X141)*OFFSET($M$6,W141,0) -> 0.34793832 | V141: =V140+1 -> 135 | W141: =MOD(V141,$V$3) -> 3 | X141: =FLOOR(V141/$V$3,1) -> 4 | AC141: TEX | AD141: dom | AE141: LEATHER | AF141: =OFFSET('Calculations 2'!$CE$45,W141,0)*OFFSET($AA$6,X141,0)*OFFSET($M$6,W141,) -> 0.0053783762 | AY141: TEX | AZ141: dom | BA141: LEATHER | BB141: 0 | BE141: TEX | BF141: dom | BG141: LEATHER | BH141: 0 | CT141: TEX | CU141: LEATHER | CV141: =OFFSET('Calculations 2'!$AJ$12,W141,X141) -> 0
Q142: LEATHER | R142: dom | S142: LEATHER | T142: =OFFSET('Calculations 2'!$C$45,W142,X142)*OFFSET($M$6,W142,0) -> 0.009249609 | V142: =V141+1 -> 136 | W142: =MOD(V142,$V$3) -> 4 | X142: =FLOOR(V142/$V$3,1) -> 4 | AC142: LEATHER | AD142: dom | AE142: LEATHER | AF142: =OFFSET('Calculations 2'!$CE$45,W142,0)*OFFSET($AA$6,X142,0)*OFFSET($M$6,W142,) -> 3.8163471e-05 | AY142: LEATHER | AZ142: dom | BA142: LEATHER | BB142: 0 | BE142: LEATHER | BF142: dom | BG142: LEATHER | BH142: 0 | CT142: LEATHER | CU142: LEATHER | CV142: =OFFSET('Calculations 2'!$AJ$12,W142,X142) -> 29.598
Q143: WOOD | R143: dom | S143: LEATHER | T143: =OFFSET('Calculations 2'!$C$45,W143,X143)*OFFSET($M$6,W143,0) -> 0 | V143: =V142+1 -> 137 | W143: =MOD(V143,$V$3) -> 5 | X143: =FLOOR(V143/$V$3,1) -> 4 | AC143: WOOD | AD143: dom | AE143: LEATHER | AF143: =OFFSET('Calculations 2'!$CE$45,W143,0)*OFFSET($AA$6,X143,0)*OFFSET($M$6,W143,) -> 0.00023493384 | AY143: WOOD | AZ143: dom | BA143: LEATHER | BB143: 0 | BE143: WOOD | BF143: dom | BG143: LEATHER | BH143: 0 | CT143: WOOD | CU143: LEATHER | CV143: =OFFSET('Calculations 2'!$AJ$12,W143,X143) -> 0
Q144: PPP | R144: dom | S144: LEATHER | T144: =OFFSET('Calculations 2'!$C$45,W144,X144)*OFFSET($M$6,W144,0) -> 0.15142241 | V144: =V143+1 -> 138 | W144: =MOD(V144,$V$3) -> 6 | X144: =FLOOR(V144/$V$3,1) -> 4 | AC144: PPP | AD144: dom | AE144: LEATHER | AF144: =OFFSET('Calculations 2'!$CE$45,W144,0)*OFFSET($AA$6,X144,0)*OFFSET($M$6,W144,) -> 0.0047023467 | AY144: PPP | AZ144: dom | BA144: LEATHER | BB144: 0 | BE144: PPP | BF144: dom | BG144: LEATHER | BH144: 0 | CT144: PPP | CU144: LEATHER | CV144: =OFFSET('Calculations 2'!$AJ$12,W144,X144) -> 0
Q145: PC | R145: dom | S145: LEATHER | T145: =OFFSET('Calculations 2'!$C$45,W145,X145)*OFFSET($M$6,W145,0) -> 0.044477576 | V145: =V144+1 -> 139 | W145: =MOD(V145,$V$3) -> 7 | X145: =FLOOR(V145/$V$3,1) -> 4 | AC145: PC | AD145: dom | AE145: LEATHER | AF145: =OFFSET('Calculations 2'!$CE$45,W145,0)*OFFSET($AA$6,X145,0)*OFFSET($M$6,W145,) -> 0.00071654664 | AY145: PC | AZ145: dom | BA145: LEATHER | BB145: 0 | BE145: PC | BF145: dom | BG145: LEATHER | BH145: 0 | CT145: PC | CU145: LEATHER | CV145: =OFFSET('Calculations 2'!$AJ$12,W145,X145) -> 0
Q146: CHM | R146: dom | S146: LEATHER | T146: =OFFSET('Calculations 2'!$C$45,W146,X146)*OFFSET($M$6,W146,0) -> 0.1635324 | V146: =V145+1 -> 140 | W146: =MOD(V146,$V$3) -> 8 | X146: =FLOOR(V146/$V$3,1) -> 4 | AC146: CHM | AD146: dom | AE146: LEATHER | AF146: =OFFSET('Calculations 2'!$CE$45,W146,0)*OFFSET($AA$6,X146,0)*OFFSET($M$6,W146,) -> 0.0044620823 | AY146: CHM | AZ146: dom | BA146: LEATHER | BB146: 0 | BE146: CHM | BF146: dom | BG146: LEATHER | BH146: 0 | CT146: CHM | CU146: LEATHER | CV146: =OFFSET('Calculations 2'!$AJ$12,W146,X146) -> 0
Q147: RUBBER | R147: dom | S147: LEATHER | T147: =OFFSET('Calculations 2'!$C$45,W147,X147)*OFFSET($M$6,W147,0) -> 0.21141674 | V147: =V146+1 -> 141 | W147: =MOD(V147,$V$3) -> 9 | X147: =FLOOR(V147/$V$3,1) -> 4 | AC147: RUBBER | AD147: dom | AE147: LEATHER | AF147: =OFFSET('Calculations 2'!$CE$45,W147,0)*OFFSET($AA$6,X147,0)*OFFSET($M$6,W147,) -> 0.0069849596 | AY147: RUBBER | AZ147: dom | BA147: LEATHER | BB147: 0 | BE147: RUBBER | BF147: dom | BG147: LEATHER | BH147: 0 | CT147: RUBBER | CU147: LEATHER | CV147: =OFFSET('Calculations 2'!$AJ$12,W147,X147) -> 0
Q148: NMM | R148: dom | S148: LEATHER | T148: =OFFSET('Calculations 2'!$C$45,W148,X148)*OFFSET($M$6,W148,0) -> 0.26455063 | V148: =V147+1 -> 142 | W148: =MOD(V148,$V$3) -> 10 | X148: =FLOOR(V148/$V$3,1) -> 4 | AC148: NMM | AD148: dom | AE148: LEATHER | AF148: =OFFSET('Calculations 2'!$CE$45,W148,0)*OFFSET($AA$6,X148,0)*OFFSET($M$6,W148,) -> 0.0064706969 | AY148: NMM | AZ148: dom | BA148: LEATHER | BB148: 0 | BE148: NMM | BF148: dom | BG148: LEATHER | BH148: 0 | CT148: NMM | CU148: LEATHER | CV148: =OFFSET('Calculations 2'!$AJ$12,W148,X148) -> 0
Q149: METAL | R149: dom | S149: LEATHER | T149: =OFFSET('Calculations 2'!$C$45,W149,X149)*OFFSET($M$6,W149,0) -> 0 | V149: =V148+1 -> 143 | W149: =MOD(V149,$V$3) -> 11 | X149: =FLOOR(V149/$V$3,1) -> 4 | AC149: METAL | AD149: dom | AE149: LEATHER | AF149: =OFFSET('Calculations 2'!$CE$45,W149,0)*OFFSET($AA$6,X149,0)*OFFSET($M$6,W149,) -> 0.01892567 | AY149: METAL | AZ149: dom | BA149: LEATHER | BB149: 0 | BE149: METAL | BF149: dom | BG149: LEATHER | BH149: 0 | CT149: METAL | CU149: LEATHER | CV149: =OFFSET('Calculations 2'!$AJ$12,W149,X149) -> 0
... Q1094: DWE | R1094: dom | S1094: DWE | T1094: =OFFSET('Calculations 2'!$C$45,W1094,X1094)*OFFSET($M$6,W1094,0) -> 0 | V1094: =V1093+1 -> 1088 | W1094: =MOD(V1094,$V$3) -> 32 | X1094: =FLOOR(V1094/$V$3,1) -> 32 | AC1094: DWE | AD1094: dom | AE1094: DWE | AF1094: =OFFSET('Calculations 2'!$CE$45,W1094,0)*OFFSET($AA$6,X1094,0)*OFFSET($M$6,W1094,) -> 0 | AY1094: DWE | AZ1094: dom | BA1094: DWE | BB1094: 0 | BE1094: DWE | BF1094: dom | BG1094: DWE | BH1094: 0 | CT1094: DWE | CU1094: DWE | CV1094: =OFFSET('Calculations 2'!$AJ$12,W1094,X1094) -> 1945.3419
Q1095: AG | R1095: imp | S1095: AG | T1095: =OFFSET('Calculations 2'!$C$45,W1095,X1095)*OFFSET($N$6,W1095,0) -> 133.18404 | V1095: 0 | W1095: =MOD(V1095,$V$3) -> 0 | X1095: =FLOOR(V1095/$V$3,1) -> 0 | AC1095: AG | AD1095: imp | AE1095: AG | AF1095: =OFFSET('Calculations 2'!$CE$45,W1095,0)*OFFSET($AA$6,X1095,0)*OFFSET($N$6,W1095,) -> 0.51417857 | AY1095: AG | AZ1095: imp | BA1095: AG | BB1095: 0 | BE1095: AG | BF1095: imp | BG1095: AG | BH1095: 0
Q1096: MIN | R1096: imp | S1096: AG | T1096: =OFFSET('Calculations 2'!$C$45,W1096,X1096)*OFFSET($N$6,W1096,0) -> 0 | V1096: =V1095+1 -> 1 | W1096: =MOD(V1096,$V$3) -> 1 | X1096: =FLOOR(V1096/$V$3,1) -> 0 | AC1096: MIN | AD1096: imp | AE1096: AG | AF1096: =OFFSET('Calculations 2'!$CE$45,W1096,0)*OFFSET($AA$6,X1096,0)*OFFSET($N$6,W1096,) -> 0.81118445 | AY1096: MIN | AZ1096: imp | BA1096: AG | BB1096: 0 | BE1096: MIN | BF1096: imp | BG1096: AG | BH1096: 0
Q1097: FBT | R1097: imp | S1097: AG | T1097: =OFFSET('Calculations 2'!$C$45,W1097,X1097)*OFFSET($N$6,W1097,0) -> 285.48164 | V1097: =V1096+1 -> 2 | W1097: =MOD(V1097,$V$3) -> 2 | X1097: =FLOOR(V1097/$V$3,1) -> 0 | AC1097: FBT | AD1097: imp | AE1097: AG | AF1097: =OFFSET('Calculations 2'!$CE$45,W1097,0)*OFFSET($AA$6,X1097,0)*OFFSET($N$6,W1097,) -> 0.20298319 | AY1097: FBT | AZ1097: imp | BA1097: AG | BB1097: 0 | BE1097: FBT | BF1097: imp | BG1097: AG | BH1097: 0
Q1098: TEX | R1098: imp | S1098: AG | T1098: =OFFSET('Calculations 2'!$C$45,W1098,X1098)*OFFSET($N$6,W1098,0) -> 8.56484 | V1098: =V1097+1 -> 3 | W1098: =MOD(V1098,$V$3) -> 3 | X1098: =FLOOR(V1098/$V$3,1) -> 0 | AC1098: TEX | AD1098: imp | AE1098: AG | AF1098: =OFFSET('Calculations 2'!$CE$45,W1098,0)*OFFSET($AA$6,X1098,0)*OFFSET($N$6,W1098,) -> 3.9833464 | AY1098: TEX | AZ1098: imp | BA1098: AG | BB1098: 0 | BE1098: TEX | BF1098: imp | BG1098: AG | BH1098: 0
Q1099: LEATHER | R1099: imp | S1099: AG | T1099: =OFFSET('Calculations 2'!$C$45,W1099,X1099)*OFFSET($N$6,W1099,0) -> 0 | V1099: =V1098+1 -> 4 | W1099: =MOD(V1099,$V$3) -> 4 | X1099: =FLOOR(V1099/$V$3,1) -> 0 | AC1099: LEATHER | AD1099: imp | AE1099: AG | AF1099: =OFFSET('Calculations 2'!$CE$45,W1099,0)*OFFSET($AA$6,X1099,0)*OFFSET($N$6,W1099,) -> 2.0759985 | AY1099: LEATHER | AZ1099: imp | BA1099: AG | BB1099: 0 | BE1099: LEATHER | BF1099: imp | BG1099: AG | BH1099: 0
Q1100: WOOD | R1100: imp | S1100: AG | T1100: =OFFSET('Calculations 2'!$C$45,W1100,X1100)*OFFSET($N$6,W1100,0) -> 0 | V1100: =V1099+1 -> 5 | W1100: =MOD(V1100,$V$3) -> 5 | X1100: =FLOOR(V1100/$V$3,1) -> 0 | AC1100: WOOD | AD1100: imp | AE1100: AG | AF1100: =OFFSET('Calculations 2'!$CE$45,W1100,0)*OFFSET($AA$6,X1100,0)*OFFSET($N$6,W1100,) -> 0.0371588 | AY1100: WOOD | AZ1100: imp | BA1100: AG | BB1100: 0 | BE1100: WOOD | BF1100: imp | BG1100: AG | BH1100: 0
Q1101: PPP | R1101: imp | S1101: AG | T1101: =OFFSET('Calculations 2'!$C$45,W1101,X1101)*OFFSET($N$6,W1101,0) -> 0 | V1101: =V1100+1 -> 6 | W1101: =MOD(V1101,$V$3) -> 6 | X1101: =FLOOR(V1101/$V$3,1) -> 0 | AC1101: PPP | AD1101: imp | AE1101: AG | AF1101: =OFFSET('Calculations 2'!$CE$45,W1101,0)*OFFSET($AA$6,X1101,0)*OFFSET($N$6,W1101,) -> 0.53508371 | AY1101: PPP | AZ1101: imp | BA1101: AG | BB1101: 0 | BE1101: PPP | BF1101: imp | BG1101: AG | BH1101: 0
Q1102: PC | R1102: imp | S1102: AG | T1102: =OFFSET('Calculations 2'!$C$45,W1102,X1102)*OFFSET($N$6,W1102,0) -> 23.191185 | V1102: =V1101+1 -> 7 | W1102: =MOD(V1102,$V$3) -> 7 | X1102: =FLOOR(V1102/$V$3,1) -> 0 | AC1102: PC | AD1102: imp | AE1102: AG | AF1102: =OFFSET('Calculations 2'!$CE$45,W1102,0)*OFFSET($AA$6,X1102,0)*OFFSET($N$6,W1102,) -> 0.13474033 | AY1102: PC | AZ1102: imp | BA1102: AG | BB1102: 0 | BE1102: PC | BF1102: imp | BG1102: AG | BH1102: 0
Q1103: CHM | R1103: imp | S1103: AG | T1103: =OFFSET('Calculations 2'!$C$45,W1103,X1103)*OFFSET($N$6,W1103,0) -> 5.0174662 | V1103: =V1102+1 -> 8 | W1103: =MOD(V1103,$V$3) -> 8 | X1103: =FLOOR(V1103/$V$3,1) -> 0 | AC1103: CHM | AD1103: imp | AE1103: AG | AF1103: =OFFSET('Calculations 2'!$CE$45,W1103,0)*OFFSET($AA$6,X1103,0)*OFFSET($N$6,W1103,) -> 1.8470656 | AY1103: CHM | AZ1103: imp | BA1103: AG | BB1103: 0 | BE1103: CHM | BF1103: imp | BG1103: AG | BH1103: 0
Q1104: RUBBER | R1104: imp | S1104: AG | T1104: =OFFSET('Calculations 2'!$C$45,W1104,X1104)*OFFSET($N$6,W1104,0) -> 0 | V1104: =V1103+1 -> 9 | W1104: =MOD(V1104,$V$3) -> 9 | X1104: =FLOOR(V1104/$V$3,1) -> 0 | AC1104: RUBBER | AD1104: imp | AE1104: AG | AF1104: =OFFSET('Calculations 2'!$CE$45,W1104,0)*OFFSET($AA$6,X1104,0)*OFFSET($N$6,W1104,) -> 1.4146068 | AY1104: RUBBER | AZ1104: imp | BA1104: AG | BB1104: 0 | BE1104: RUBBER | BF1104: imp | BG1104: AG | BH1104: 0
Q1105: NMM | R1105: imp | S1105: AG | T1105: =OFFSET('Calculations 2'!$C$45,W1105,X1105)*OFFSET($N$6,W1105,0) -> 0 | V1105: =V1104+1 -> 10 | W1105: =MOD(V1105,$V$3) -> 10 | X1105: =FLOOR(V1105/$V$3,1) -> 0 | AC1105: NMM | AD1105: imp | AE1105: AG | AF1105: =OFFSET('Calculations 2'!$CE$45,W1105,0)*OFFSET($AA$6,X1105,0)*OFFSET($N$6,W1105,) -> 0.53399616 | AY1105: NMM | AZ1105: imp | BA1105: AG | BB1105: 0 | BE1105: NMM | BF1105: imp | BG1105: AG | BH1105: 0
Q1106: METAL | R1106: imp | S1106: AG | T1106: =OFFSET('Calculations 2'!$C$45,W1106,X1106)*OFFSET($N$6,W1106,0) -> 0 | V1106: =V1105+1 -> 11 | W1106: =MOD(V1106,$V$3) -> 11 | X1106: =FLOOR(V1106/$V$3,1) -> 0 | AC1106: METAL | AD1106: imp | AE1106: AG | AF1106: =OFFSET('Calculations 2'!$CE$45,W1106,0)*OFFSET($AA$6,X1106,0)*OFFSET($N$6,W1106,) -> 6.6841042 | AY1106: METAL | AZ1106: imp | BA1106: AG | BB1106: 0 | BE1106: METAL | BF1106: imp | BG1106: AG | BH1106: 0
Q1107: MACH | R1107: imp | S1107: AG | T1107: =OFFSET('Calculations 2'!$C$45,W1107,X1107)*OFFSET($N$6,W1107,0) -> 0 | V1107: =V1106+1 -> 12 | W1107: =MOD(V1107,$V$3) -> 12 | X1107: =FLOOR(V1107/$V$3,1) -> 0 | AC1107: MACH | AD1107: imp | AE1107: AG | AF1107: =OFFSET('Calculations 2'!$CE$45,W1107,0)*OFFSET($AA$6,X1107,0)*OFFSET($N$6,W1107,) -> 25.605278 | AY1107: MACH | AZ1107: imp | BA1107: AG | BB1107: 0 | BE1107: MACH | BF1107: imp | BG1107: AG | BH1107: 0
... Q2183: DWE | R2183: imp | S2183: DWE | T2183: =OFFSET('Calculations 2'!$C$45,W2183,X2183)*OFFSET($N$6,W2183,0) -> 0 | V2183: =V2182+1 -> 1088 | W2183: =MOD(V2183,$V$3) -> 32 | X2183: =FLOOR(V2183/$V$3,1) -> 32 | AC2183: DWE | AD2183: imp | AE2183: DWE | AF2183: =OFFSET('Calculations 2'!$CE$45,W2183,0)*OFFSET($AA$6,X2183,0)*OFFSET($N$6,W2183,) -> 0 | AY2183: DWE | AZ2183: imp | BA2183: DWE | BB2183: 0 | BE2183: DWE | BF2183: imp | BG2183: DWE | BH2183: 0

Sheet MAP
D2: Activities | H2: Commodities | L2: Factors | P2: Tax | S2: Institutions | Z2: Capital
C3: Million AED | D3: Agriculture, hunting, forestry, and fishing | E3: Mining and quarrying | F3: Other community, social, and personal services | G3: Private households with employed persons | H3: Agriculture, hunting, forestry, and fishing | I3: Mining and quarrying | J3: Other community, social, and personal services | K3: Private households with employed persons | L3: Emirati Labour | M3: Migrant Labour | N3: Commuting Labour | O3: Capital | P3: Indirect taxes | Q3: Subsidies | R3: Direct taxes | S3: Emirati Household | T3: Non-Emirati Household | U3: Collective Households | V3: Labour Camps | W3: Commuting household | X3: Government | Y3: Rest of the World | Z3: Savings - Investment
B4: Activities | C4: Agriculture, hunting, forestry, and fishing | D4: 0 | E4: 0 | F4: 0 | G4: 0 | H4: 1512.2992 | I4: 0 | J4: MAKE | K4: 0 | L4: 0 | M4: 0 | N4: 0 | O4: 0 | P4: 0 | Q4: 0 | R4: 0 | S4: 0 | T4: 0 | U4: 0 | V4: 0 | W4: 0 | X4: 0 | Y4: 0 | Z4: 0
C5: Mining and quarrying | D5: 0 | E5: 0 | F5: 0 | G5: 0 | H5: 0 | I5: 11448.729 | J5: 0 | K5: 0 | L5: 0 | M5: 0 | N5: 0 | O5: 0 | P5: 0 | Q5: 0 | R5: 0 | S5: 0 | T5: 0 | U5: 0 | V5: 0 | W5: 0 | X5: 0 | Y5: 0 | Z5: 0
C6: Other community, social, and personal services | D6: 0 | E6: 0 | F6: 0 | G6: 0 | H6: 0 | I6: 0 | J6: 7820.8397 | K6: 0 | L6: 0 | M6: 0 | N6: 0 | O6: 0 | P6: 0 | Q6: 0 | R6: 0 | S6: 0 | T6: 0 | U6: 0 | V6: 0 | W6: 0 | X6: 0 | Y6: 0 | Z6: 0
C7: Private households with employed persons | D7: 0 | E7: 0 | F7: 0 | G7: 0 | H7: 0 | I7: 0 | J7: 0 | K7: 1945.3419 | L7: 0 | M7: 0 | N7: 0 | O7: 0 | P7: 0 | Q7: 0 | R7: 0 | S7: 0 | T7: 0 | U7: 0 | V7: 0 | W7: 0 | X7: 0 | Y7: 0 | Z7: 0
B8: Commodities | C8: Agriculture, hunting, forestry, and fishing | D8: 143.07824 | E8: 0 | F8: V1BAS | G8: 0 | H8: 0 | I8: 0 | J8: 0 | K8: 0 | L8: 0 | M8: 0 | N8: 0 | O8: 0 | P8: 0 | Q8: 0 | R8: 0 | S8: 650.05757 | T8: 1816.241 | U8: 181.61415 | V8: 76.877273 | W8: 0 | X8: 0 | Y8: 13478.352 | Z8: 327.99153
C9: Mining and quarrying | D9: 0 | E9: 653.16941 | F9: 0 | G9: 0 | H9: 0 | I9: 0 | J9: 0 | K9: 0 | L9: 0 | M9: 0 | N9: 0 | O9: 0 | P9: 0 | Q9: 0 | R9: 0 | S9: 72.153961 | T9: 3BAS | U9: 42.576965 | V9: 9.3433054 | W9: 0 | X9: 5BAS | Y9: 4BAS | Z9: 521.23281
C10: Other community, social, and personal services | D10: 0 | E10: 2.5079417 | F10: 101.93045 | G10: 0 | H10: 0 | I10: 0 | J10: 0 | K10: 0 | L10: 0 | M10: 0 | N10: 0 | O10: 0 | P10: 0 | Q10: 0 | R10: 0 | S10: 600.69964 | T10: 1250.5101 | U10: 33.165917 | V10: 3.978187 | W10: 0 | X10: 811.9882 | Y10: 3516.9782 | Z10: 2BAS
C11: Private households with employed persons | D11: 0 | E11: 0 | F11: 0 | G11: 0 | H11: 0 | I11: 0 | J11: 0 | K11: 0 | L11: 0 | M11: 0 | N11: 0 | O11: 0 | P11: 0 | Q11: 0 | R11: 0 | S11: 845.94664 | T11: 1026.5238 | U11: 47.701429 | V11: 25.170006 | W11: 0 | X11: 0 | Y11: 0 | Z11: 0
B12: Factors | C12: Emirati Labour | D12: 14.240861 | E12: 90.364734 | F12: V1LAB | G12: 147.79424 | H12: 0 | I12: 0 | J12: 0 | K12: 0 | L12: 0 | M12: 0 | N12: 0 | O12: 0 | P12: 0 | Q12: 0 | R12: 0 | S12: 0 | T12: 0 | U12: 0 | V12: 0 | W12: 0 | X12: 0 | Y12: 0 | Z12: 0
C13: Migrant Labour | D13: 155.77576 | E13: 817.21729 | F13: 1850.1452 | G13: 1279.7686 | H13: 0 | I13: 0 | J13: 0 | K13: 0 | L13: 0 | M13: 0 | N13: 0 | O13: 0 | P13: 0 | Q13: 0 | R13: 0 | S13: 0 | T13: 0 | U13: 0 | V13: 0 | W13: 0 | X13: 0 | Y13: 0 | Z13: 0
C14: Commuting Labour | D14: 62.983383 | E14: 330.41798 | F14: 748.05224 | G14: 517.43712 | H14: 0 | I14: 0 | J14: 0 | K14: 0 | L14: 0 | M14: 0 | N14: 0 | O14: 0 | P14: 0 | Q14: 0 | R14: 0 | S14: 0 | T14: 0 | U14: 0 | V14: 0 | W14: 0 | X14: 0 | Y14: 0 | Z14: 0
C15: Capital | D15: 414.32237 | E15: 7222.3983 | F15: V1CAP | G15: 0.34192339 | H15: 0 | I15: 0 | J15: 0 | K15: 0 | L15: 0 | M15: 0 | N15: 0 | O15: 0 | P15: 0 | Q15: 0 | R15: 0 | S15: 0 | T15: 0 | U15: 0 | V15: 0 | W15: 0 | X15: 0 | Y15: 0 | Z15: 0
B16: Tax | C16: Indirect taxes | D16: 0 | E16: 0 | F16: 0 | G16: 0 | H16: 144.4832 | I16: 0TAR | J16: 200.26044 | K16: 0 | L16: 0 | M16: 0 | N16: 0 | O16: 0 | P16: 0 | Q16: 0 | R16: 0 | S16: 0 | T16: 0 | U16: 0 | V16: 0 | W16: 0 | X16: 0 | Y16: 0 | Z16: 0
C17: Subsidies | D17: 0 | E17: 0 | F17: 0 | G17: 0 | H17: 0 | I17: 0 | J17: 0 | K17: 0 | L17: 0 | M17: 0 | N17: 0 | O17: 0 | P17: 0 | Q17: 0 | R17: 0 | S17: 0 | T17: 0 | U17: 0 | V17: 0 | W17: 0 | X17: 0 | Y17: 0 | Z17: 0
C18: Direct taxes | D18: 0 | E18: 0 | F18: 0 | G18: 0 | H18: 0 | I18: 0 | J18: 0 | K18: 0 | L18: 0 | M18: 0 | N18: 0 | O18: 39520 | P18: 0 | Q18: 0 | R18: 0 | S18: 0 | T18: 0 | U18: 0 | V18: 0 | W18: 0 | X18: 0 | Y18: 0 | Z18: 0
B19: Institutions | C19: Emirati Household | D19: 0 | E19: 0 | F19: 0 | G19: 0 | H19: 0 | I19: 0 | J19: 0 | K19: 0 | L19: 16934.765 | M19: 0 | N19: 0 | O19: 185847.58 | P19: 0 | Q19: 0 | R19: 0 | S19: 0 | T19: 0 | U19: 0 | V19: 0 | W19: 0 | X19: 20278.234 | Y19: 0 | Z19: 0
C20: Non-Emirati Household | D20: 0 | E20: 0 | F20: 0 | G20: 0 | H20: 0 | I20: 0 | J20: 0 | K20: 0 | L20: 0 | M20: 90773.272 | N20: 0 | O20: 20649.731 | P20: 0 | Q20: 0 | R20: 0 | S20: 0 | T20: 0 | U20: 0 | V20: 0 | W20: 0 | X20: 0 | Y20: 0 | Z20: 0
C21: Collective Households | D21: 0 | E21: 0 | F21: 0 | G21: 0 | H21: 0 | I21: 0 | J21: 0 | K21: 0 | L21: 0 | M21: 50235.39 | N21: 0 | O21: 0 | P21: 0 | Q21: 0 | R21: 0 | S21: 0 | T21: 0 | U21: 0 | V21: 0 | W21: 0 | X21: 0 | Y21: 0 | Z21: 0
C22: Labour Camps | D22: 0 | E22: 0 | F22: 0 | G22: 0 | H22: 0 | I22: 0 | J22: 0 | K22: 0 | L22: 0 | M22: 18952.739 | N22: 0 | O22: 0 | P22: 0 | Q22: 0 | R22: 0 | S22: 0 | T22: 0 | U22: 0 | V22: 0 | W22: 0 | X22: 0 | Y22: 0 | Z22: 0
C23: Commuting Household | D23: 0 | E23: 0 | F23: 0 | G23: 0 | H23: 0 | I23: 0 | J23: 0 | K23: 0 | L23: 0 | M23: 0 | N23: 64675.726 | O23: 0 | P23: 0 | Q23: 0 | R23: 0 | S23: 0 | T23: 0 | U23: 0 | V23: 0 | W23: 0 | X23: 0 | Y23: 0 | Z23: 0
C24: Government | D24: 0 | E24: 0 | F24: 0 | G24: 0 | H24: 0 | I24: 0 | J24: 0 | K24: 0 | L24: 0 | M24: 0 | N24: 0 | O24: 0 | P24: 18030 | Q24: 0 | R24: 39520 | S24: 3180.3749 | T24: 8363.7131 | U24: 942.81661 | V24: 1031.9181 | W24: 0 | X24: 0 | Y24: 0 | Z24: 0
C25: Rest of the World | D25: 0 | E25: 0 | F25: 0 | G25: 0 | H25: 20212.322 | I25: Feeds into the 'imp' of BAS | J25: 449.61518 | K25: 0 | L25: 0 | M25: 0 | N25: 0 | O25: 0 | P25: 0 | Q25: 0 | R25: 0 | S25: 113534.54 | T25: 26449.301 | U25: 42510.857 | V25: 13191.575 | W25: 64675.726 | X25: 0 | Y25: 0 | Z25: 0
B26: Capital | C26: Savings - Investment | D26: 0 | E26: 0 | F26: 0 | G26: 0 | H26: 0 | I26: 0 | J26: 0 | K26: 0 | L26: 0 | M26: 0 | N26: 0 | O26: 0 | P26: 0 | Q26: 0 | R26: 0 | S26: 69448.446 | T26: 7716.494 | U26: 0 | V26: 0 | W26: 0 | X26: 2800 | Y26: 36587.752 | Z26: 0
C30: V6BAS set to zero
C31: V2TAX set to zero for domestic

Sheet Calculations 2
A1: Transfer assumptions
A3: Government transfers to Emirati households | D3: -1.2836954e-16 | E3: of emirati non-transfer income | G3: =D3*Calculations!BX356 -> -2.6031075e-11
A4: Households transfers to government | D4: =2/3 -> 0.66666667 | E4: of government transfers - allocated proportiunally to real estate expenditure
A5: Emirati Household | D5: =G$3*D$4*Calculations!BX$334/SUM(Calculations!BX$334:CA$334) -> -4.0826326e-12 | F5: =D5 -> -4.0826326e-12
A6: Non-Emirati Household | D6: =G$3*D$4*Calculations!BY$334/SUM(Calculations!BX$334:CA$334) -> -1.073646e-11 | F6: =D6 -> -1.073646e-11
A7: Collective Households | D7: =G$3*D$4*Calculations!BZ$334/SUM(Calculations!BX$334:CA$334) -> -1.2102893e-12 | F7: =D7+D8 -> -2.5349578e-12
A8: Labour Camps | D8: =G$3*D$4*Calculations!CA$334/SUM(Calculations!BX$334:CA$334) -> -1.3246685e-12
C10: Activities | AJ10: Commodities | BQ10: Factors | BV10: Tax | BY10: Institutions | CE10: Capital
B11: Million AED | C11: Agriculture, hunting, forestry, and fishing | D11: Mining and quarrying | E11: Food, beverages, and tobacco | F11: Textiles and textile products | G11: Leather, leather products, and footwear | H11: Wood and products of wood and cork | I11: Pulp, paper, paper products, printing, and publishing | J11: Coke, refined petroleum, and nuclear fuel | K11: Chemicals and chemical products | L11: Rubber and plastics | M11: Other nonmetallic minerals | N11: Basic metals and fabricated metal | O11: Machinery, nec | P11: Electrical and optical equipment | Q11: Transport equipment | R11: Manufacturing, nec; recycling | S11: Electricity, gas, and water supply | T11: Construction | U11: Wholesale and Retail Trade; Repair of Motor Vehicles and Motorcycles | V11: Hotels and restaurants | W11: Inland transport | X11: Water transport | Y11: Air transport | Z11: Other supporting and auxiliary transport activities; activities of travel agencies | AA11: Post and telecommunications | AB11: Financial intermediation | AC11: Real estate activities | AD11: Renting of M&Eq and other business activities | AE11: Public administration and defense; compulsory social security | AF11: Education | AG11: Health and social work | AH11: Other community, social, and personal services | AI11: Private households with employed persons | AJ11: Agriculture, hunting, forestry, and fishing | AK11: Mining and quarrying | AL11: Food, beverages, and tobacco | AM11: Textiles and textile products | AN11: Leather, leather products, and footwear | AO11: Wood and products of wood and cork | AP11: Pulp, paper, paper products, printing, and publishing | AQ11: Coke, refined petroleum, and nuclear fuel | AR11: Chemicals and chemical products | AS11: Rubber and plastics | AT11: Other nonmetallic minerals | AU11: Basic metals and fabricated metal | AV11: Machinery, nec | AW11: Electrical and optical equipment | AX11: Transport equipment | AY11: Manufacturing, nec; recycling | AZ11: Electricity, gas, and water supply | BA11: Construction | BB11: Wholesale and Retail Trade; Repair of Motor Vehicles and Motorcycles | BC11: Hotels and restaurants | BD11: Inland transport | BE11: Water transport | BF11: Air transport | BG11: Other supporting and auxiliary transport activities; activities of travel agencies | BH11: Post and telecommunications | BI11: Financial intermediation | BJ11: Real estate activities | BK11: Renting of M&Eq and other business activities | BL11: Public administration and defense; compulsory social security | BM11: Education | BN11: Health and social work | BO11: Other community, social, and personal services | BP11: Private households with employed persons | BQ11: Emirati Labour | BR11: Migrant HH | BS11: Migrant Combines | BT11: Commuting Labour | BU11: Capital | BV11: Indirect taxes | BW11: Subsidies | BX11: Direct taxes | BY11: Emirati Household | BZ11: Non-Emirati Household | CA11: Combines | CB11: Commuting household | CC11: Government | CD11: Rest of the World | CE11: Savings - Investment | CF11: TOTAL
A12: Activities | B12: Agriculture, hunting, forestry, and fishing | C12: =Calculations!C275 -> 0 | D12: =Calculations!D275 -> 0 | E12: =Calculations!E275 -> 0 | F12: =Calculations!F275 -> 0 | G12: =Calculations!G275 -> 0 | H12: =Calculations!H275 -> 0 | I12: =Calculations!I275 -> 0 | J12: =Calculations!J275 -> 0 | ... BR12: =Calculations!BR275 -> 0 | BS12: 0 | BT12: =Calculations!BS275 -> 0 | BU12: =Calculations!BT275 -> 0 | BV12: =Calculations!BU275 -> 0 | BW12: =Calculations!BV275 -> 0 | BX12: =Calculations!BW275 -> 0 | BY12: =Calculations!BX275 -> 0 | BZ12: =Calculations!BY275 -> 0 | CA12: =Calculations!BZ275+Calculations!CA275 -> 0 | CB12: =Calculations!CB275 -> 0 | CC12: =Calculations!CC275 -> 0 | CD12: =Calculations!CD275 -> 0 | CE12: =Calculations!CE275 -> 0 | CF12: =SUM(C12:CE12) -> 1512.2992 | CH12: {=CF12:CF92-TRANSPOSE(C93:CE93)} -> 0
B13: Mining and quarrying | C13: =Calculations!C276 -> 0 | D13: =Calculations!D276 -> 0 | E13: =Calculations!E276 -> 0 | F13: =Calculations!F276 -> 0 | G13: =Calculations!G276 -> 0 | H13: =Calculations!H276 -> 0 | I13: =Calculations!I276 -> 0 | J13: =Calculations!J276 -> 0 | ... BR13: =Calculations!BR276 -> 0 | BS13: 0 | BT13: =Calculations!BS276 -> 0 | BU13: =Calculations!BT276 -> 0 | BV13: =Calculations!BU276 -> 0 | BW13: =Calculations!BV276 -> 0 | BX13: =Calculations!BW276 -> 0 | BY13: =Calculations!BX276 -> 0 | BZ13: =Calculations!BY276 -> 0 | CA13: =Calculations!BZ276+Calculations!CA276 -> 0 | CB13: =Calculations!CB276 -> 0 | CC13: =Calculations!CC276 -> 0 | CD13: =Calculations!CD276 -> 0 | CE13: =Calculations!CE276 -> 0 | CF13: =SUM(C13:CE13) -> 11448.729 | CH13: 0
B14: Food, beverages, and tobacco | C14: =Calculations!C277 -> 0 | D14: =Calculations!D277 -> 0 | E14: =Calculations!E277 -> 0 | F14: =Calculations!F277 -> 0 | G14: =Calculations!G277 -> 0 | H14: =Calculations!H277 -> 0 | I14: =Calculations!I277 -> 0 | J14: =Calculations!J277 -> 0 | ... BR14: =Calculations!BR277 -> 0 | BS14: 0 | BT14: =Calculations!BS277 -> 0 | BU14: =Calculations!BT277 -> 0 | BV14: =Calculations!BU277 -> 0 | BW14: =Calculations!BV277 -> 0 | BX14: =Calculations!BW277 -> 0 | BY14: =Calculations!BX277 -> 0 | BZ14: =Calculations!BY277 -> 0 | CA14: =Calculations!BZ277+Calculations!CA277 -> 0 | CB14: =Calculations!CB277 -> 0 | CC14: =Calculations!CC277 -> 0 | CD14: =Calculations!CD277 -> 0 | CE14: =Calculations!CE277 -> 0 | CF14: =SUM(C14:CE14) -> 25557.719 | CH14: 0
B15: Textiles and textile products | C15: =Calculations!C278 -> 0 | D15: =Calculations!D278 -> 0 | E15: =Calculations!E278 -> 0 | F15: =Calculations!F278 -> 0 | G15: =Calculations!G278 -> 0 | H15: =Calculations!H278 -> 0 | I15: =Calculations!I278 -> 0 | J15: =Calculations!J278 -> 0 | ... BR15: =Calculations!BR278 -> 0 | BS15: 0 | BT15: =Calculations!BS278 -> 0 | BU15: =Calculations!BT278 -> 0 | BV15: =Calculations!BU278 -> 0 | BW15: =Calculations!BV278 -> 0 | BX15: =Calculations!BW278 -> 0 | BY15: =Calculations!BX278 -> 0 | BZ15: =Calculations!BY278 -> 0 | CA15: =Calculations!BZ278+Calculations!CA278 -> 0 | CB15: =Calculations!CB278 -> 0 | CC15: =Calculations!CC278 -> 0 | CD15: =Calculations!CD278 -> 0 | CE15: =Calculations!CE278 -> 0 | CF15: =SUM(C15:CE15) -> 3421.037 | CH15: 0
B16: Leather, leather products, and footwear | C16: =Calculations!C279 -> 0 | D16: =Calculations!D279 -> 0 | E16: =Calculations!E279 -> 0 | F16: =Calculations!F279 -> 0 | G16: =Calculations!G279 -> 0 | H16: =Calculations!H279 -> 0 | I16: =Calculations!I279 -> 0 | J16: =Calculations!J279 -> 0 | ... BR16: =Calculations!BR279 -> 0 | BS16: 0 | BT16: =Calculations!BS279 -> 0 | BU16: =Calculations!BT279 -> 0 | BV16: =Calculations!BU279 -> 0 | BW16: =Calculations!BV279 -> 0 | BX16: =Calculations!BW279 -> 0 | BY16: =Calculations!BX279 -> 0 | BZ16: =Calculations!BY279 -> 0 | CA16: =Calculations!BZ279+Calculations!CA279 -> 0 | CB16: =Calculations!CB279 -> 0 | CC16: =Calculations!CC279 -> 0 | CD16: =Calculations!CD279 -> 0 | CE16: =Calculations!CE279 -> 0 | CF16: =SUM(C16:CE16) -> 29.598 | CH16: 0
B17: Wood and products of wood and cork | C17: =Calculations!C280 -> 0 | D17: =Calculations!D280 -> 0 | E17: =Calculations!E280 -> 0 | F17: =Calculations!F280 -> 0 | G17: =Calculations!G280 -> 0 | H17: =Calculations!H280 -> 0 | I17: =Calculations!I280 -> 0 | J17: =Calculations!J280 -> 0 | ... BR17: =Calculations!BR280 -> 0 | BS17: 0 | BT17: =Calculations!BS280 -> 0 | BU17: =Calculations!BT280 -> 0 | BV17: =Calculations!BU280 -> 0 | BW17: =Calculations!BV280 -> 0 | BX17: =Calculations!BW280 -> 0 | BY17: =Calculations!BX280 -> 0 | BZ17: =Calculations!BY280 -> 0 | CA17: =Calculations!BZ280+Calculations!CA280 -> 0 | CB17: =Calculations!CB280 -> 0 | CC17: =Calculations!CC280 -> 0 | CD17: =Calculations!CD280 -> 0 | CE17: =Calculations!CE280 -> 0 | CF17: =SUM(C17:CE17) -> 2673.883 | CH17: 0
B18: Pulp, paper, paper products, printing, and publishing | C18: =Calculations!C281 -> 0 | D18: =Calculations!D281 -> 0 | E18: =Calculations!E281 -> 0 | F18: =Calculations!F281 -> 0 | G18: =Calculations!G281 -> 0 | H18: =Calculations!H281 -> 0 | I18: =Calculations!I281 -> 0 | J18: =Calculations!J281 -> 0 | ... BR18: =Calculations!BR281 -> 0 | BS18: 0 | BT18: =Calculations!BS281 -> 0 | BU18: =Calculations!BT281 -> 0 | BV18: =Calculations!BU281 -> 0 | BW18: =Calculations!BV281 -> 0 | BX18: =Calculations!BW281 -> 0 | BY18: =Calculations!BX281 -> 0 | BZ18: =Calculations!BY281 -> 0 | CA18: =Calculations!BZ281+Calculations!CA281 -> 0 | CB18: =Calculations!CB281 -> 0 | CC18: =Calculations!CC281 -> 0 | CD18: =Calculations!CD281 -> 0 | CE18: =Calculations!CE281 -> 0 | CF18: =SUM(C18:CE18) -> 7097.443 | CH18: 0
B19: Coke, refined petroleum, and nuclear fuel | C19: =Calculations!C282 -> 0 | D19: =Calculations!D282 -> 0 | E19: =Calculations!E282 -> 0 | F19: =Calculations!F282 -> 0 | G19: =Calculations!G282 -> 0 | H19: =Calculations!H282 -> 0 | I19: =Calculations!I282 -> 0 | J19: =Calculations!J282 -> 0 | ... BR19: =Calculations!BR282 -> 0 | BS19: 0 | BT19: =Calculations!BS282 -> 0 | BU19: =Calculations!BT282 -> 0 | BV19: =Calculations!BU282 -> 0 | BW19: =Calculations!BV282 -> 0 | BX19: =Calculations!BW282 -> 0 | BY19: =Calculations!BX282 -> 0 | BZ19: =Calculations!BY282 -> 0 | CA19: =Calculations!BZ282+Calculations!CA282 -> 0 | CB19: =Calculations!CB282 -> 0 | CC19: =Calculations!CC282 -> 0 | CD19: =Calculations!CD282 -> 0 | CE19: =Calculations!CE282 -> 0 | CF19: =SUM(C19:CE19) -> 28389.412 | CH19: 0
B20: Chemicals and chemical products | C20: =Calculations!C283 -> 0 | D20: =Calculations!D283 -> 0 | E20: =Calculations!E283 -> 0 | F20: =Calculations!F283 -> 0 | G20: =Calculations!G283 -> 0 | H20: =Calculations!H283 -> 0 | I20: =Calculations!I283 -> 0 | J20: =Calculations!J283 -> 0 | ... BR20: =Calculations!BR283 -> 0 | BS20: 0 | BT20: =Calculations!BS283 -> 0 | BU20: =Calculations!BT283 -> 0 | BV20: =Calculations!BU283 -> 0 | BW20: =Calculations!BV283 -> 0 | BX20: =Calculations!BW283 -> 0 | BY20: =Calculations!BX283 -> 0 | BZ20: =Calculations!BY283 -> 0 | CA20: =Calculations!BZ283+Calculations!CA283 -> 0 | CB20: =Calculations!CB283 -> 0 | CC20: =Calculations!CC283 -> 0 | CD20: =Calculations!CD283 -> 0 | CE20: =Calculations!CE283 -> 0 | CF20: =SUM(C20:CE20) -> 13147.266 | CH20: 0
B21: Rubber and plastics | C21: =Calculations!C284 -> 0 | D21: =Calculations!D284 -> 0 | E21: =Calculations!E284 -> 0 | F21: =Calculations!F284 -> 0 | G21: =Calculations!G284 -> 0 | H21: =Calculations!H284 -> 0 | I21: =Calculations!I284 -> 0 | J21: =Calculations!J284 -> 0 | ... BR21: =Calculations!BR284 -> 0 | BS21: 0 | BT21: =Calculations!BS284 -> 0 | BU21: =Calculations!BT284 -> 0 | BV21: =Calculations!BU284 -> 0 | BW21: =Calculations!BV284 -> 0 | BX21: =Calculations!BW284 -> 0 | BY21: =Calculations!BX284 -> 0 | BZ21: =Calculations!BY284 -> 0 | CA21: =Calculations!BZ284+Calculations!CA284 -> 0 | CB21: =Calculations!CB284 -> 0 | CC21: =Calculations!CC284 -> 0 | CD21: =Calculations!CD284 -> 0 | CE21: =Calculations!CE284 -> 0 | CF21: =SUM(C21:CE21) -> 6406.529 | CH21: 0
B22: Other nonmetallic minerals | C22: =Calculations!C285 -> 0 | D22: =Calculations!D285 -> 0 | E22: =Calculations!E285 -> 0 | F22: =Calculations!F285 -> 0 | G22: =Calculations!G285 -> 0 | H22: =Calculations!H285 -> 0 | I22: =Calculations!I285 -> 0 | J22: =Calculations!J285 -> 0 | ... BR22: =Calculations!BR285 -> 0 | BS22: 0 | BT22: =Calculations!BS285 -> 0 | BU22: =Calculations!BT285 -> 0 | BV22: =Calculations!BU285 -> 0 | BW22: =Calculations!BV285 -> 0 | BX22: =Calculations!BW285 -> 0 | BY22: =Calculations!BX285 -> 0 | BZ22: =Calculations!BY285 -> 0 | CA22: =Calculations!BZ285+Calculations!CA285 -> 0 | CB22: =Calculations!CB285 -> 0 | CC22: =Calculations!CC285 -> 0 | CD22: =Calculations!CD285 -> 0 | CE22: =Calculations!CE285 -> 0 | CF22: =SUM(C22:CE22) -> 8147.143 | CH22: 0
B23: Basic metals and fabricated metal | C23: =Calculations!C286 -> 0 | D23: =Calculations!D286 -> 0 | E23: =Calculations!E286 -> 0 | F23: =Calculations!F286 -> 0 | G23: =Calculations!G286 -> 0 | H23: =Calculations!H286 -> 0 | I23: =Calculations!I286 -> 0 | J23: =Calculations!J286 -> 0 | ... BR23: =Calculations!BR286 -> 0 | BS23: 0 | BT23: =Calculations!BS286 -> 0 | BU23: =Calculations!BT286 -> 0 | BV23: =Calculations!BU286 -> 0 | BW23: =Calculations!BV286 -> 0 | BX23: =Calculations!BW286 -> 0 | BY23: =Calculations!BX286 -> 0 | BZ23: =Calculations!BY286 -> 0 | CA23: =Calculations!BZ286+Calculations!CA286 -> 0 | CB23: =Calculations!CB286 -> 0 | CC23: =Calculations!CC286 -> 0 | CD23: =Calculations!CD286 -> 0 | CE23: =Calculations!CE286 -> 0 | CF23: =SUM(C23:CE23) -> 38703.505 | CH23: 0
B24: Machinery, nec | C24: =Calculations!C287 -> 0 | D24: =Calculations!D287 -> 0 | E24: =Calculations!E287 -> 0 | F24: =Calculations!F287 -> 0 | G24: =Calculations!G287 -> 0 | H24: =Calculations!H287 -> 0 | I24: =Calculations!I287 -> 0 | J24: =Calculations!J287 -> 0 | ... BR24: =Calculations!BR287 -> 0 | BS24: 0 | BT24: =Calculations!BS287 -> 0 | BU24: =Calculations!BT287 -> 0 | BV24: =Calculations!BU287 -> 0 | BW24: =Calculations!BV287 -> 0 | BX24: =Calculations!BW287 -> 0 | BY24: =Calculations!BX287 -> 0 | BZ24: =Calculations!BY287 -> 0 | CA24: =Calculations!BZ287+Calculations!CA287 -> 0 | CB24: =Calculations!CB287 -> 0 | CC24: =Calculations!CC287 -> 0 | CD24: =Calculations!CD287 -> 0 | CE24: =Calculations!CE287 -> 0 | CF24: =SUM(C24:CE24) -> 7111.347 | CH24: 0
... B44: Private households with employed persons | C44: =Calculations!C307 -> 0 | D44: =Calculations!D307 -> 0 | E44: =Calculations!E307 -> 0 | F44: =Calculations!F307 -> 0 | G44: =Calculations!G307 -> 0 | H44: =Calculations!H307 -> 0 | I44: =Calculations!I307 -> 0 | J44: =Calculations!J307 -> 0 | ... BR44: =Calculations!BR307 -> 0 | BS44: 0 | BT44: =Calculations!BS307 -> 0 | BU44: =Calculations!BT307 -> 0 | BV44: =Calculations!BU307 -> 0 | BW44: =Calculations!BV307 -> 0 | BX44: =Calculations!BW307 -> 0 | BY44: =Calculations!BX307 -> 0 | BZ44: =Calculations!BY307 -> 0 | CA44: =Calculations!BZ307+Calculations!CA307 -> 0 | CB44: =Calculations!CB307 -> 0 | CC44: =Calculations!CC307 -> 0 | CD44: =Calculations!CD307 -> 0 | CE44: =Calculations!CE307 -> 0 | CF44: =SUM(C44:CE44) -> 1945.3419 | CH44: 0
A45: Commodities | B45: Agriculture, hunting, forestry, and fishing | C45: =Calculations!C308 -> 143.07824 | D45: =Calculations!D308 -> 0 | E45: =Calculations!E308 -> 2948.276 | F45: =Calculations!F308 -> 0.80286355 | G45: =Calculations!G308 -> 0 | H45: =Calculations!H308 -> 47.293888 | I45: =Calculations!I308 -> 0 | J45: =Calculations!J308 -> 0 | ... BR45: =Calculations!BR308 -> 0 | BS45: 0 | BT45: =Calculations!BS308 -> 0 | BU45: =Calculations!BT308 -> 0 | BV45: =Calculations!BU308 -> 0 | BW45: =Calculations!BV308 -> 0 | BX45: =Calculations!BW308 -> 0 | BY45: =Calculations!BX308+'Calculations 2'!CJ45 -> 387.54161 | BZ45: =Calculations!BY308+'Calculations 2'!CK45 -> 2036.7338 | CA45: =Calculations!BZ308+Calculations!CA308 -> 300.51459 | CB45: =Calculations!CB308+'Calculations 2'!CN45 -> 0 | CC45: =Calculations!CC308+'Calculations 2'!CO45 -> 0 | CD45: =Calculations!CD308 -> 13478.352 | CE45: =Calculations!CE308 -> 327.99153 | CF45: =SUM(C45:CE45) -> 21869.105 | CH45: 0
B46: Mining and quarrying | C46: =Calculations!C309 -> 0 | D46: =Calculations!D309 -> 653.16941 | E46: =Calculations!E309 -> 101.44139 | F46: =Calculations!F309 -> 0 | G46: =Calculations!G309 -> 0 | H46: =Calculations!H309 -> 6.1203669 | I46: =Calculations!I309 -> 0 | J46: =Calculations!J309 -> 22262.802 | ... BR46: =Calculations!BR309 -> 0 | BS46: 0 | BT46: =Calculations!BS309 -> 0 | BU46: =Calculations!BT309 -> 0 | BV46: =Calculations!BU309 -> 0 | BW46: =Calculations!BV309 -> 0 | BX46: =Calculations!BW309 -> 0 | BY46: =Calculations!BX309+'Calculations 2'!CJ46 -> 16.849359 | BZ46: =Calculations!BY309+'Calculations 2'!CK46 -> 437.35054 | CA46: =Calculations!BZ309+Calculations!CA309 -> 59.878164 | CB46: =Calculations!CB309+'Calculations 2'!CN46 -> 0 | CC46: =Calculations!CC309+'Calculations 2'!CO46 -> 0 | CD46: =Calculations!CD309 -> 125317.36 | CE46: =Calculations!CE309 -> 521.23281 | CF46: =SUM(C46:CE46) -> 150823.5 | CH46: 0
B47: Food, beverages, and tobacco | C47: =Calculations!C310 -> 443.27859 | D47: =Calculations!D310 -> 0 | E47: =Calculations!E310 -> 8805.5268 | F47: =Calculations!F310 -> 0 | G47: =Calculations!G310 -> 0 | H47: =Calculations!H310 -> 0.023586799 | I47: =Calculations!I310 -> 0.24330827 | J47: =Calculations!J310 -> 0 | ... BR47: =Calculations!BR310 -> 0 | BS47: 0 | BT47: =Calculations!BS310 -> 0 | BU47: =Calculations!BT310 -> 0 | BV47: =Calculations!BU310 -> 0 | BW47: =Calculations!BV310 -> 0 | BX47: =Calculations!BW310 -> 0 | BY47: =Calculations!BX310+'Calculations 2'!CJ47 -> 1253.1685 | BZ47: =Calculations!BY310+'Calculations 2'!CK47 -> 6198.5989 | CA47: =Calculations!BZ310+Calculations!CA310 -> 1683.9949 | CB47: =Calculations!CB310+'Calculations 2'!CN47 -> 0 | CC47: =Calculations!CC310+'Calculations 2'!CO47 -> 0 | CD47: =Calculations!CD310 -> 40267.725 | CE47: =Calculations!CE310 -> 187.14831 | CF47: =SUM(C47:CE47) -> 71796.001 | CH47: 0
B48: Textiles and textile products | C48: =Calculations!C311 -> 9.8214309 | D48: =Calculations!D311 -> 0 | E48: =Calculations!E311 -> 40.776498 | F48: =Calculations!F311 -> 847.77563 | G48: =Calculations!G311 -> 2.7194627 | H48: =Calculations!H311 -> 24.203471 | I48: =Calculations!I311 -> 14.517659 | J48: =Calculations!J311 -> 0.0014346228 | ... BR48: =Calculations!BR311 -> 0 | BS48: 0 | BT48: =Calculations!BS311 -> 0 | BU48: =Calculations!BT311 -> 0 | BV48: =Calculations!BU311 -> 0 | BW48: =Calculations!BV311 -> 0 | BX48: =Calculations!BW311 -> 0 | BY48: =Calculations!BX311+'Calculations 2'!CJ48 -> 470.47535 | BZ48: =Calculations!BY311+'Calculations 2'!CK48 -> 2116.3817 | CA48: =Calculations!BZ311+Calculations!CA311 -> 182.69544 | CB48: =Calculations!CB311+'Calculations 2'!CN48 -> 0 | CC48: =Calculations!CC311+'Calculations 2'!CO48 -> 0 | CD48: =Calculations!CD311 -> 18250.608 | CE48: =Calculations!CE311 -> 2712.2572 | CF48: =SUM(C48:CE48) -> 26738.597 | CH48: 0
B49: Leather, leather products, and footwear | C49: =Calculations!C312 -> 0 | D49: =Calculations!D312 -> 0 | E49: =Calculations!E312 -> 0 | F49: =Calculations!F312 -> 0.047137753 | G49: =Calculations!G312 -> 4.6397824 | H49: =Calculations!H312 -> 0 | I49: =Calculations!I312 -> 43.06195 | J49: =Calculations!J312 -> 0 | ... BR49: =Calculations!BR312 -> 0 | BS49: 0 | BT49: =Calculations!BS312 -> 0 | BU49: =Calculations!BT312 -> 0 | BV49: =Calculations!BU312 -> 0 | BW49: =Calculations!BV312 -> 0 | BX49: =Calculations!BW312 -> 0 | BY49: =Calculations!BX312+'Calculations 2'!CJ49 -> 332.34663 | BZ49: =Calculations!BY312+'Calculations 2'!CK49 -> 1495.0248 | CA49: =Calculations!BZ312+Calculations!CA312 -> 129.05717 | CB49: =Calculations!CB312+'Calculations 2'!CN49 -> 0 | CC49: =Calculations!CC312+'Calculations 2'!CO49 -> 0 | CD49: =Calculations!CD312 -> 11177.055 | CE49: =Calculations!CE312 -> 1235.1536 | CF49: =SUM(C49:CE49) -> 14846.928 | CH49: 0
B50: Wood and products of wood and cork | C50: =Calculations!C313 -> 0 | D50: =Calculations!D313 -> 0 | E50: =Calculations!E313 -> 0 | F50: =Calculations!F313 -> 0 | G50: =Calculations!G313 -> 0 | H50: =Calculations!H313 -> 442.57759 | I50: =Calculations!I313 -> 17.960527 | J50: =Calculations!J313 -> 0 | ... BR50: =Calculations!BR313 -> 0 | BS50: 0 | BT50: =Calculations!BS313 -> 0 | BU50: =Calculations!BT313 -> 0 | BV50: =Calculations!BU313 -> 0 | BW50: =Calculations!BV313 -> 0 | BX50: =Calculations!BW313 -> 0 | BY50: =Calculations!BX313+'Calculations 2'!CJ50 -> 0 | BZ50: =Calculations!BY313+'Calculations 2'!CK50 -> 0 | CA50: =Calculations!BZ313+Calculations!CA313 -> 0 | CB50: =Calculations!CB313+'Calculations 2'!CN50 -> 0 | CC50: =Calculations!CC313+'Calculations 2'!CO50 -> 0 | CD50: =Calculations!CD313 -> 2027.6278 | CE50: =Calculations!CE313 -> 37.222327 | CF50: =SUM(C50:CE50) -> 6566.0093 | CH50: 0
B51: Pulp, paper, paper products, printing, and publishing | C51: =Calculations!C314 -> 0 | D51: =Calculations!D314 -> 0 | E51: =Calculations!E314 -> 232.2301 | F51: =Calculations!F314 -> 5.5587769 | G51: =Calculations!G314 -> 0.30999411 | H51: =Calculations!H314 -> 28.845784 | I51: =Calculations!I314 -> 2353.3699 | J51: =Calculations!J314 -> 0.16826761 | ... BR51: =Calculations!BR314 -> 0 | BS51: 0 | BT51: =Calculations!BS314 -> 0 | BU51: =Calculations!BT314 -> 0 | BV51: =Calculations!BU314 -> 0 | BW51: =Calculations!BV314 -> 0 | BX51: =Calculations!BW314 -> 0 | BY51: =Calculations!BX314+'Calculations 2'!CJ51 -> 31.846153 | BZ51: =Calculations!BY314+'Calculations 2'!CK51 -> 184.70072 | CA51: =Calculations!BZ314+Calculations!CA314 -> 39.757334 | CB51: =Calculations!CB314+'Calculations 2'!CN51 -> 0 | CC51: =Calculations!CC314+'Calculations 2'!CO51 -> 0 | CD51: =Calculations!CD314 -> 3806.5156 | CE51: =Calculations!CE314 -> 621.12181 | CF51: =SUM(C51:CE51) -> 14529.986 | CH51: 0
B52: Coke, refined petroleum, and nuclear fuel | C52: =Calculations!C315 -> 36.592313 | D52: =Calculations!D315 -> 494.32315 | E52: =Calculations!E315 -> 413.30215 | F52: =Calculations!F315 -> 7.4312133 | G52: =Calculations!G315 -> 0.12144779 | H52: =Calculations!H315 -> 9.4906176 | I52: =Calculations!I315 -> 15.137528 | J52: =Calculations!J315 -> 1608.8147 | ... BR52: =Calculations!BR315 -> 0 | BS52: 0 | BT52: =Calculations!BS315 -> 0 | BU52: =Calculations!BT315 -> 0 | BV52: =Calculations!BU315 -> 0 | BW52: =Calculations!BV315 -> 0 | BX52: =Calculations!BW315 -> 0 | BY52: =Calculations!BX315+'Calculations 2'!CJ52 -> 59.19617 | BZ52: =Calculations!BY315+'Calculations 2'!CK52 -> 1536.5259 | CA52: =Calculations!BZ315+Calculations!CA315 -> 210.36752 | CB52: =Calculations!CB315+'Calculations 2'!CN52 -> 0 | CC52: =Calculations!CC315+'Calculations 2'!CO52 -> 0 | CD52: =Calculations!CD315 -> 23605.032 | CE52: =Calculations!CE315 -> 126.2385 | CF52: =SUM(C52:CE52) -> 77518.417 | CH52: 0
B53: Chemicals and chemical products | C53: =Calculations!C316 -> 6.3345435 | D53: =Calculations!D316 -> 0 | E53: =Calculations!E316 -> 96.322723 | F53: =Calculations!F316 -> 1.930536 | G53: =Calculations!G316 -> 0.78651652 | H53: =Calculations!H316 -> 387.75162 | I53: =Calculations!I316 -> 347.68442 | J53: =Calculations!J316 -> 679.9407 | ... BR53: =Calculations!BR316 -> 0 | BS53: 0 | BT53: =Calculations!BS316 -> 0 | BU53: =Calculations!BT316 -> 0 | BV53: =Calculations!BU316 -> 0 | BW53: =Calculations!BV316 -> 0 | BX53: =Calculations!BW316 -> 0 | BY53: =Calculations!BX316+'Calculations 2'!CJ53 -> 361.08737 | BZ53: =Calculations!BY316+'Calculations 2'!CK53 -> 1897.7029 | CA53: =Calculations!BZ316+Calculations!CA316 -> 280.00095 | CB53: =Calculations!CB316+'Calculations 2'!CN53 -> 0 | CC53: =Calculations!CC316+'Calculations 2'!CO53 -> 0 | CD53: =Calculations!CD316 -> 44799.938 | CE53: =Calculations!CE316 -> 1384.6515 | CF53: =SUM(C53:CE53) -> 63232.375 | CH53: 0
B54: Rubber and plastics | C54: =Calculations!C317 -> 0 | D54: =Calculations!D317 -> 0 | E54: =Calculations!E317 -> 1298.929 | F54: =Calculations!F317 -> 31.663667 | G54: =Calculations!G317 -> 0.60545612 | H54: =Calculations!H317 -> 73.899941 | I54: =Calculations!I317 -> 160.16559 | J54: =Calculations!J317 -> 244.93128 | ... BR54: =Calculations!BR317 -> 0 | BS54: 0 | BT54: =Calculations!BS317 -> 0 | BU54: =Calculations!BT317 -> 0 | BV54: =Calculations!BU317 -> 0 | BW54: =Calculations!BV317 -> 0 | BX54: =Calculations!BW317 -> 0 | BY54: =Calculations!BX317+'Calculations 2'!CJ54 -> 1.0611084 | BZ54: =Calculations!BY317+'Calculations 2'!CK54 -> 5.5766792 | CA54: =Calculations!BZ317+Calculations!CA317 -> 0.822824 | CB54: =Calculations!CB317+'Calculations 2'!CN54 -> 0 | CC54: =Calculations!CC317+'Calculations 2'!CO54 -> 0 | CD54: =Calculations!CD317 -> 11455.931 | CE54: =Calculations!CE317 -> 1290.6428 | CF54: =SUM(C54:CE54) -> 18347.044 | CH54: 0
B55: Other nonmetallic minerals | C55: =Calculations!C318 -> 0 | D55: =Calculations!D318 -> 0 | E55: =Calculations!E318 -> 3.6321957 | F55: =Calculations!F318 -> 9.3401169 | G55: =Calculations!G318 -> 0.46547115 | H55: =Calculations!H318 -> 31.308112 | I55: =Calculations!I318 -> 0 | J55: =Calculations!J318 -> 0 | ... BR55: =Calculations!BR318 -> 0 | BS55: 0 | BT55: =Calculations!BS318 -> 0 | BU55: =Calculations!BT318 -> 0 | BV55: =Calculations!BU318 -> 0 | BW55: =Calculations!BV318 -> 0 | BX55: =Calculations!BW318 -> 0 | BY55: =Calculations!BX318+'Calculations 2'!CJ55 -> 12.707078 | BZ55: =Calculations!BY318+'Calculations 2'!CK55 -> 66.782339 | CA55: =Calculations!BZ318+Calculations!CA318 -> 9.8535544 | CB55: =Calculations!CB318+'Calculations 2'!CN55 -> 0 | CC55: =Calculations!CC318+'Calculations 2'!CO55 -> 0 | CD55: =Calculations!CD318 -> 4728.6533 | CE55: =Calculations!CE318 -> 734.57118 | CF55: =SUM(C55:CE55) -> 14334.723 | CH55: 0
B56: Basic metals and fabricated metal | C56: =Calculations!C319 -> 0 | D56: =Calculations!D319 -> 0 | E56: =Calculations!E319 -> 15.077205 | F56: =Calculations!F319 -> 82.436696 | G56: =Calculations!G319 -> 0 | H56: =Calculations!H319 -> 108.81532 | I56: =Calculations!I319 -> 31.051593 | J56: =Calculations!J319 -> 0 | ... BR56: =Calculations!BR319 -> 0 | BS56: 0 | BT56: =Calculations!BS319 -> 0 | BU56: =Calculations!BT319 -> 0 | BV56: =Calculations!BU319 -> 0 | BW56: =Calculations!BV319 -> 0 | BX56: =Calculations!BW319 -> 0 | BY56: =Calculations!BX319+'Calculations 2'!CJ56 -> 13.497061 | BZ56: =Calculations!BY319+'Calculations 2'!CK56 -> 70.934112 | CA56: =Calculations!BZ319+Calculations!CA319 -> 10.466137 | CB56: =Calculations!CB319+'Calculations 2'!CN56 -> 0 | CC56: =Calculations!CC319+'Calculations 2'!CO56 -> 0 | CD56: =Calculations!CD319 -> 129405.85 | CE56: =Calculations!CE319 -> 5189.9999 | CF56: =SUM(C56:CE56) -> 164500.62 | CH56: 0
B57: Machinery, nec | C57: =Calculations!C320 -> 0 | D57: =Calculations!D320 -> 0 | E57: =Calculations!E320 -> 124.53197 | F57: =Calculations!F320 -> 1.9763584 | G57: =Calculations!G320 -> 0.02071129 | H57: =Calculations!H320 -> 11.931423 | I57: =Calculations!I320 -> 31.869564 | J57: =Calculations!J320 -> 0 | ... BR57: =Calculations!BR320 -> 0 | BS57: 0 | BT57: =Calculations!BS320 -> 0 | BU57: =Calculations!BT320 -> 0 | BV57: =Calculations!BU320 -> 0 | BW57: =Calculations!BV320 -> 0 | BX57: =Calculations!BW320 -> 0 | BY57: =Calculations!BX320+'Calculations 2'!CJ57 -> 3.3748912 | BZ57: =Calculations!BY320+'Calculations 2'!CK57 -> 17.736818 | CA57: =Calculations!BZ320+Calculations!CA320 -> 2.6170197 | CB57: =Calculations!CB320+'Calculations 2'!CN57 -> 0 | CC57: =Calculations!CC320+'Calculations 2'!CO57 -> 0 | CD57: =Calculations!CD320 -> 40306.888 | CE57: =Calculations!CE320 -> 16971.404 | CF57: =SUM(C57:CE57) -> 68284.888 | CH57: 0
... B77: Private households with employed persons | C77: =Calculations!C340 -> 0 | D77: =Calculations!D340 -> 0 | E77: =Calculations!E340 -> 0 | F77: =Calculations!F340 -> 0 | G77: =Calculations!G340 -> 0 | H77: =Calculations!H340 -> 0 | I77: =Calculations!I340 -> 0 | J77: =Calculations!J340 -> 0 | ... BR77: =Calculations!BR340 -> 0 | BS77: 0 | BT77: =Calculations!BS340 -> 0 | BU77: =Calculations!BT340 -> 0 | BV77: =Calculations!BU340 -> 0 | BW77: =Calculations!BV340 -> 0 | BX77: =Calculations!BW340 -> 0 | BY77: =Calculations!BX340+'Calculations 2'!CJ77 -> 709.20232 | BZ77: =Calculations!BY340+'Calculations 2'!CK77 -> 1151.1445 | CA77: =Calculations!BZ340+Calculations!CA340 -> 84.995123 | CB77: =Calculations!CB340+'Calculations 2'!CN77 -> 0 | CC77: =Calculations!CC340+'Calculations 2'!CO77 -> 0 | CD77: =Calculations!CD340 -> 0 | CE77: =Calculations!CE340 -> 0 | CF77: =SUM(C77:CE77) -> 1945.3419 | CH77: 0
A78: Factors | B78: Emirati Labour | C78: {=TRANSPOSE('Estimating non em split'!AA296:AD328)} -> 14.240861 | D78: 90.364734 | E78: 69.178652 | F78: 21.659221 | G78: 0.19311588 | H78: 16.314918 | I78: 33.470438 | J78: 6.6922626 | K78: 40.239678 | L78: 18.177604 | M78: 44.044585 | N78: 104.69835 | O78: 34.173652 | P78: 19.647828 | Q78: 7.7914024 | R78: 74.587809 | S78: 48.108216 | T78: 1047.7648 | U78: 964.44287 | V78: 161.51725 | W78: 57.04909 | X78: 1.9528973 | Y78: 190.14759 | Z78: 120.23246 | AA78: 170.06177 | AB78: 1001.5209 | AC78: 129.87665 | AD78: 1671.9806 | AE78: 9787.3551 | AF78: 392.06384 | AG78: 380.61937 | AH78: 66.802582 | AI78: 147.79424 | AJ78: =Calculations!AJ341 -> 0 | AK78: =Calculations!AK341 -> 0 | AL78: =Calculations!AL341 -> 0 | AM78: =Calculations!AM341 -> 0 | AN78: =Calculations!AN341 -> 0 | AO78: =Calculations!AO341 -> 0 | AP78: =Calculations!AP341 -> 0 | AQ78: =Calculations!AQ341 -> 0 | ... BR78: =Calculations!BR341 -> 0 | BS78: 0 | BT78: =Calculations!BS341 -> 0 | BU78: =Calculations!BT341 -> 0 | BV78: =Calculations!BU341 -> 0 | BW78: =Calculations!BV341 -> 0 | BX78: =Calculations!BW341 -> 0 | BY78: =Calculations!BX341 -> 0 | BZ78: =Calculations!BY341 -> 0 | CA78: =Calculations!BZ341+Calculations!CA341 -> 0 | CB78: =Calculations!CB341 -> 0 | CC78: =Calculations!CC341 -> 0 | CD78: =Calculations!CD341 -> 0 | CE78: =Calculations!CE341 -> 0 | CF78: =SUM(C78:CE78) -> 16934.765 | CH78: 0
B79: Migrant HH | C79: 23.695215 | D79: 650.11793 | E79: 861.60638 | F79: 269.76131 | G79: 2.4052201 | H79: 203.19907 | I79: 416.86765 | J79: 83.350803 | K79: 501.17719 | L79: 226.39843 | M79: 548.56656 | N79: 1303.9972 | O79: 425.62606 | P79: 244.70981 | Q79: 97.040367 | R79: 928.97635 | S79: 2299.7808 | T79: 5638.2166 | U79: 32822.972 | V79: 9162.7838 | W79: 2625.203 | X79: 89.86562 | Y79: 8749.9382 | Z79: 5532.6843 | AA79: 2994.246 | AB79: 7840.3079 | AC79: 4789.0263 | AD79: 24970.453 | AE79: 9677.6428 | AF79: 4325.5946 | AG79: 3330.8359 | AH79: 1789.105 | AI79: 1275.7365 | AJ79: =Calculations!AJ342 -> 0 | AK79: =Calculations!AK342 -> 0 | AL79: =Calculations!AL342 -> 0 | AM79: =Calculations!AM342 -> 0 | AN79: =Calculations!AN342 -> 0 | AO79: =Calculations!AO342 -> 0 | AP79: =Calculations!AP342 -> 0 | AQ79: =Calculations!AQ342 -> 0 | ... BR79: =Calculations!BR342 -> 0 | BS79: 0 | BT79: =Calculations!BS342 -> 0 | BU79: =Calculations!BT342 -> 0 | BV79: =Calculations!BU342 -> 0 | BW79: =Calculations!BV342 -> 0 | BX79: =Calculations!BW342 -> 0 | BY79: =Calculations!BX342 -> 0 | BZ79: =Calculations!BY342 -> 0 | CA79: =Calculations!BZ342+Calculations!CA342 -> 0 | CB79: =Calculations!CB342 -> 0 | CC79: =Calculations!CC342 -> 0 | CD79: =Calculations!CD342 -> 0 | CE79: =Calculations!CE342 -> 0 | CF79: =SUM(C79:CE79) -> 134701.89 | CH79: 0
B80: Migrant Combine | C80: 132.08054 | D80: 167.09936 | E80: 994.88488 | F80: 311.48962 | G80: 2.7772738 | H80: 234.63114 | I80: 481.35129 | J80: 96.24401 | K80: 578.70234 | L80: 261.41915 | M80: 633.42218 | N80: 1505.7074 | O80: 491.46448 | P80: 282.56299 | Q80: 112.05117 | R80: 1072.6761 | S80: 759.27219 | T80: 8232.4673 | U80: 4393.992 | V80: 248.18614 | W80: 383.79383 | X80: 13.137982 | Y80: 1279.2048 | Z80: 808.85557 | AA80: 437.7464 | AB80: 78.442865 | AC80: 100.96981 | AD80: 526.46659 | AE80: 396.01315 | AF80: 42.307726 | AG80: 135.01981 | AH80: 61.040153 | AI80: 4.0321788 | AJ80: 0 | AK80: 0 | AL80: 0 | AM80: 0 | AN80: 0 | AO80: 0 | AP80: 0 | AQ80: 0 | AR80: 0 | AS80: 0 | AT80: 0 | AU80: 0 | AV80: 0 | AW80: 0 | AX80: 0 | AY80: 0 | AZ80: 0 | BA80: 0 | BB80: 0 | BC80: 0 | BD80: 0 | BE80: 0 | BF80: 0 | BG80: 0 | BH80: 0 | BI80: 0 | BJ80: 0 | BK80: 0 | BL80: 0 | BM80: 0 | BN80: 0 | BO80: 0 | BP80: 0 | BQ80: 0 | BR80: 0 | BS80: 0 | BT80: 0 | BU80: 0 | BV80: 0 | BW80: 0 | BX80: 0 | BY80: 0 | BZ80: 0 | CA80: =Calculations!BZ343+Calculations!CA343 -> 0 | CB80: 0 | CC80: 0 | CD80: 0 | CE80: 0 | CF80: =SUM(C80:CE80) -> 25259.512 | CH80: 0
B81: Commuting Labour | C81: 62.983383 | D81: 330.41798 | E81: 750.61809 | F81: 235.01186 | G81: 2.0953902 | H81: 177.02387 | I81: 363.16863 | J81: 72.613924 | K81: 436.61779 | L81: 197.23481 | M81: 477.90267 | N81: 1136.0221 | O81: 370.79881 | P81: 213.18738 | Q81: 84.540063 | R81: 809.30977 | S81: 1236.8388 | T81: 5608.2065 | U81: 15047.594 | V81: 3805.0512 | W81: 1216.6001 | X81: 41.646502 | Y81: 4054.9914 | Z81: 2564.0167 | AA81: 1387.626 | AB81: 3201.7159 | AC81: 1977.1273 | AD81: 10308.936 | AE81: 4072.989 | AF81: 1766.0339 | AG81: 1401.3177 | AH81: 748.05224 | AI81: 517.43712 | AJ81: =Calculations!AJ343 -> 0 | AK81: =Calculations!AK343 -> 0 | AL81: =Calculations!AL343 -> 0 | AM81: =Calculations!AM343 -> 0 | AN81: =Calculations!AN343 -> 0 | AO81: =Calculations!AO343 -> 0 | AP81: =Calculations!AP343 -> 0 | AQ81: =Calculations!AQ343 -> 0 | ... BR81: =Calculations!BR343 -> 0 | BS81: 0 | BT81: =Calculations!BS343 -> 0 | BU81: =Calculations!BT343 -> 0 | BV81: =Calculations!BU343 -> 0 | BW81: =Calculations!BV343 -> 0 | BX81: =Calculations!BW343 -> 0 | BY81: =Calculations!BX343 -> 0 | BZ81: =Calculations!BY343 -> 0 | CA81: =Calculations!BZ344+Calculations!CA344 -> 0 | CB81: =Calculations!CB343 -> 0 | CC81: =Calculations!CC343 -> 0 | CD81: =Calculations!CD343 -> 0 | CE81: =Calculations!CE343 -> 0 | CF81: =SUM(C81:CE81) -> 64675.726 | CH81: 0
B82: Capital | C82: =Calculations!C344 -> 414.32237 | D82: =Calculations!D344 -> 7222.3983 | E82: =Calculations!E344 -> 3400.165 | F82: =Calculations!F344 -> 812.752 | G82: =Calculations!G344 -> 3.813 | H82: =Calculations!H344 -> 307.873 | I82: =Calculations!I344 -> 879.574 | J82: =Calculations!J344 -> 1928.287 | ... BR82: =Calculations!BR344 -> 0 | BS82: 0 | BT82: =Calculations!BS344 -> 0 | BU82: =Calculations!BT344 -> 0 | BV82: =Calculations!BU344 -> 0 | BW82: =Calculations!BV344 -> 0 | BX82: =Calculations!BW344 -> 0 | BY82: =Calculations!BX344 -> 0 | BZ82: =Calculations!BY344 -> 0 | CA82: =Calculations!BZ345+Calculations!CA345 -> 0 | CB82: =Calculations!CB344 -> 0 | CC82: =Calculations!CC344 -> 0 | CD82: =Calculations!CD344 -> 0 | CE82: =Calculations!CE344 -> 0 | CF82: =SUM(C82:CE82) -> 246017.31 | CH82: 0
A83: Tax | B83: Indirect taxes | C83: =Calculations!C345 -> 0 | D83: =Calculations!D345 -> 0 | E83: =Calculations!E345 -> 0 | F83: =Calculations!F345 -> 0 | G83: =Calculations!G345 -> 0 | H83: =Calculations!H345 -> 0 | I83: =Calculations!I345 -> 0 | J83: =Calculations!J345 -> 0 | ... BR83: =Calculations!BR345 -> 0 | BS83: 0 | BT83: =Calculations!BS345 -> 0 | BU83: =Calculations!BT345 -> 0 | BV83: =Calculations!BU345 -> 0 | BW83: =Calculations!BV345 -> 0 | BX83: =Calculations!BW345 -> 0 | BY83: =Calculations!BX345 -> 0 | BZ83: =Calculations!BY345 -> 0 | CA83: =Calculations!BZ346+Calculations!CA346 -> 0 | CB83: =Calculations!CB345 -> 0 | CC83: =Calculations!CC345 -> 0 | CD83: =Calculations!CD345 -> 0 | CE83: =Calculations!CE345 -> 0 | CF83: =SUM(C83:CE83) -> 18030 | CH83: 0
B84: Subsidies | C84: =Calculations!C346 -> 0 | D84: =Calculations!D346 -> 0 | E84: =Calculations!E346 -> 0 | F84: =Calculations!F346 -> 0 | G84: =Calculations!G346 -> 0 | H84: =Calculations!H346 -> 0 | I84: =Calculations!I346 -> 0 | J84: =Calculations!J346 -> 0 | ... BR84: =Calculations!BR346 -> 0 | BS84: 0 | BT84: =Calculations!BS346 -> 0 | BU84: =Calculations!BT346 -> 0 | BV84: =Calculations!BU346 -> 0 | BW84: =Calculations!BV346 -> 0 | BX84: =Calculations!BW346 -> 0 | BY84: =Calculations!BX346 -> 0 | BZ84: =Calculations!BY346 -> 0 | CA84: =Calculations!BZ347+Calculations!CA347 -> 0 | CB84: =Calculations!CB346 -> 0 | CC84: =Calculations!CC346 -> 0 | CD84: =Calculations!CD346 -> 0 | CE84: =Calculations!CE346 -> 0 | CF84: =SUM(C84:CE84) -> 0 | CH84: 0
B85: Direct taxes | C85: =Calculations!C347 -> 0 | D85: =Calculations!D347 -> 0 | E85: =Calculations!E347 -> 0 | F85: =Calculations!F347 -> 0 | G85: =Calculations!G347 -> 0 | H85: =Calculations!H347 -> 0 | I85: =Calculations!I347 -> 0 | J85: =Calculations!J347 -> 0 | ... BR85: =Calculations!BR347 -> 0 | BS85: 0 | BT85: =Calculations!BS347 -> 0 | BU85: =Calculations!BT347 -> 39520 | BV85: =Calculations!BU347 -> 0 | BW85: =Calculations!BV347 -> 0 | BX85: =Calculations!BW347 -> 0 | BY85: =Calculations!BX347 -> 0 | BZ85: =Calculations!BY347 -> 0 | CA85: =Calculations!BZ348+Calculations!CA348 -> 0 | CB85: =Calculations!CB347 -> 0 | CC85: =Calculations!CC347 -> 0 | CD85: =Calculations!CD347 -> 0 | CE85: =Calculations!CE347 -> 0 | CF85: =SUM(C85:CE85) -> 39520 | CH85: 0
A86: Institutions | B86: Emirati Household | C86: =Calculations!C348 -> 0 | D86: =Calculations!D348 -> 0 | E86: =Calculations!E348 -> 0 | F86: =Calculations!F348 -> 0 | G86: =Calculations!G348 -> 0 | H86: =Calculations!H348 -> 0 | I86: =Calculations!I348 -> 0 | J86: =Calculations!J348 -> 0 | ... BR86: =Calculations!BR348 -> 0 | BT86: =Calculations!BS348 -> 0 | BU86: =Calculations!BT348 -> 185847.58 | BV86: =Calculations!BU348 -> 0 | BW86: =Calculations!BV348 -> 0 | BX86: =Calculations!BW348 -> 0 | BY86: =Calculations!BX348 -> 0 | BZ86: =Calculations!BY348 -> 0 | CA86: =Calculations!BZ349+Calculations!CA349 -> 0 | CB86: =Calculations!CB348 -> 0 | CC86: =G3 -> -2.6031075e-11 | CD86: =Calculations!CD348 -> 0 | CE86: =Calculations!CE348 -> 0 | CF86: =SUM(C86:CE86) -> 202782.34 | CH86: 0
B87: Non-Emirati Household | C87: =Calculations!C349 -> 0 | D87: =Calculations!D349 -> 0 | E87: =Calculations!E349 -> 0 | F87: =Calculations!F349 -> 0 | G87: =Calculations!G349 -> 0 | H87: =Calculations!H349 -> 0 | I87: =Calculations!I349 -> 0 | J87: =Calculations!J349 -> 0 | ... BQ87: =Calculations!BQ349 -> 0 | BR87: =CF79 -> 134701.89 | BT87: =Calculations!BS349 -> 0 | BU87: =Calculations!BT349 -> 20649.731 | BV87: =Calculations!BU349 -> 0 | BW87: =Calculations!BV349 -> 0 | BX87: =Calculations!BW349 -> 0 | BY87: =Calculations!BX349 -> 0 | BZ87: =Calculations!BY349 -> 0 | CA87: =Calculations!BZ350+Calculations!CA350 -> 0 | CB87: =Calculations!CB349 -> 0 | CC87: =Calculations!CC349 -> 0 | CD87: =Calculations!CD349 -> 0 | CE87: =Calculations!CE349 -> 0 | CF87: =SUM(C87:CE87) -> 155351.62 | CH87: 0
B88: Combines | C88: =Calculations!C350 -> 0 | D88: =Calculations!D350 -> 0 | E88: =Calculations!E350 -> 0 | F88: =Calculations!F350 -> 0 | G88: =Calculations!G350 -> 0 | H88: =Calculations!H350 -> 0 | I88: =Calculations!I350 -> 0 | J88: =Calculations!J350 -> 0 | ... BQ88: =Calculations!BQ350 -> 0 | BS88: =CF80 -> 25259.512 | BT88: =Calculations!BS350 -> 0 | BU88: =Calculations!BT350 -> 0 | BV88: =Calculations!BU350 -> 0 | BW88: =Calculations!BV350 -> 0 | BX88: =Calculations!BW350 -> 0 | BY88: =Calculations!BX350 -> 0 | BZ88: =Calculations!BY350 -> 0 | CA88: =Calculations!BZ351+Calculations!CA351 -> 0 | CB88: =Calculations!CB350 -> 0 | CC88: =Calculations!CC350 -> 0 | CD88: =Calculations!CD350 -> 0 | CE88: =Calculations!CE350 -> 0 | CF88: =SUM(C88:CE88) -> 25259.512 | CH88: 0
B89: Commuting Household | C89: =Calculations!C352 -> 0 | D89: =Calculations!D352 -> 0 | E89: =Calculations!E352 -> 0 | F89: =Calculations!F352 -> 0 | G89: =Calculations!G352 -> 0 | H89: =Calculations!H352 -> 0 | I89: =Calculations!I352 -> 0 | J89: =Calculations!J352 -> 0 | ... BR89: =Calculations!BR352 -> 0 | BT89: =Calculations!BS352 -> 64675.726 | BU89: =Calculations!BT352 -> 0 | BV89: =Calculations!BU352 -> 0 | BW89: =Calculations!BV352 -> 0 | BX89: =Calculations!BW352 -> 0 | BY89: =Calculations!BX352 -> 0 | BZ89: =Calculations!BY352 -> 0 | CA89: =Calculations!BZ353+Calculations!CA353 -> 0 | CB89: =Calculations!CB352 -> 0 | CC89: =Calculations!CC352 -> 0 | CD89: =Calculations!CD352 -> 0 | CE89: =Calculations!CE352 -> 0 | CF89: =SUM(C89:CE89) -> 64675.726 | CH89: 0
B90: Government | C90: =Calculations!C353 -> 0 | D90: =Calculations!D353 -> 0 | E90: =Calculations!E353 -> 0 | F90: =Calculations!F353 -> 0 | G90: =Calculations!G353 -> 0 | H90: =Calculations!H353 -> 0 | I90: =Calculations!I353 -> 0 | J90: =Calculations!J353 -> 0 | ... BR90: =Calculations!BR353 -> 0 | BS90: 0 | BT90: =Calculations!BS353 -> 0 | BU90: =Calculations!BT353 -> 0 | BV90: =Calculations!BU353 -> 18030 | BW90: =Calculations!BV353 -> 0 | BX90: =Calculations!BW353 -> 39520 | BY90: {=TRANSPOSE(F5:F7)} -> -4.0826326e-12 | BZ90: -1.073646e-11 | CA90: -2.5349578e-12 | CB90: =5/8*$CC86*CB71/SUM($BY71:$CA71) -> 0 | CC90: =Calculations!CC353 -> 0 | CD90: =Calculations!CD353 -> 0 | CE90: =Calculations!CE353 -> 0 | CF90: =SUM(C90:CE90) -> 57550 | CH90: 0
B91: Rest of the World | C91: =Calculations!C354 -> 0 | D91: =Calculations!D354 -> 0 | E91: =Calculations!E354 -> 0 | F91: =Calculations!F354 -> 0 | G91: =Calculations!G354 -> 0 | H91: =Calculations!H354 -> 0 | I91: =Calculations!I354 -> 0 | J91: =Calculations!J354 -> 0 | ... BR91: =Calculations!BR354 -> 0 | BS91: 0 | BT91: =Calculations!BS354 -> 0 | BU91: =Calculations!BT354 -> 0 | BV91: =Calculations!BU354 -> 0 | BW91: =Calculations!BV354 -> 0 | BX91: =Calculations!BW354 -> 0 | BY91: =CF86-SUM(BY92,BY12:BY90) -> 113534.54 | BZ91: =CF87-SUM(BZ92,BZ12:BZ90) -> 70377.917 | CA91: =CF88-SUM(CA92,CA12:CA90) -> 11773.816 | CB91: =Calculations!CB354 -> 64675.726 | CC91: =Calculations!CC354 -> 0 | CD91: =Calculations!CD354 -> 0 | CE91: =Calculations!CE354 -> 0 | CF91: =SUM(C91:CE91) -> 1054114.3 | CH91: 0
A92: Capital | B92: Savings - Investment | C92: =Calculations!C355 -> 0 | D92: =Calculations!D355 -> 0 | E92: =Calculations!E355 -> 0 | F92: =Calculations!F355 -> 0 | G92: =Calculations!G355 -> 0 | H92: =Calculations!H355 -> 0 | I92: =Calculations!I355 -> 0 | J92: =Calculations!J355 -> 0 | ... BR92: =Calculations!BR355 -> 0 | BS92: 0 | BT92: =Calculations!BS355 -> 0 | BU92: =Calculations!BT355 -> 0 | BV92: =Calculations!BU355 -> 0 | BW92: =Calculations!BV355 -> 0 | BX92: =Calculations!BW355 -> 0 | BY92: =Calculations!BX355 -> 69448.446 | BZ92: =Calculations!BY355 -> 7716.494 | CA92: =Calculations!BZ355+Calculations!CA355 -> 0 | CB92: =Calculations!CB355 -> 0 | CC92: =Calculations!CC355 -> 2800 | CD92: =Calculations!CD355 -> 36587.752 | CE92: =Calculations!CE355 -> 0 | CF92: =SUM(C92:CE92) -> 116552.69 | CH92: 0
B93: TOTAL | C93: =SUM(C12:C92) -> 1512.2992 | D93: =SUM(D12:D92) -> 11448.729 | E93: =SUM(E12:E92) -> 25557.719 | F93: =SUM(F12:F92) -> 3421.037 | G93: =SUM(G12:G92) -> 29.598 | H93: =SUM(H12:H92) -> 2673.883 | I93: =SUM(I12:I92) -> 7097.443 | J93: =SUM(J12:J92) -> 28389.412 | ... CE93: =SUM(CE12:CE92) -> 116552.69
A96: Labour quantities | C96: {=TRANSPOSE('Estimating non em split'!AF296:AI328)} -> 294.7307 | D96: 417.67695 | E96: 600.03135 | F96: 187.86448 | G96: 1.6750192 | H96: 141.50988 | I96: 290.31083 | J96: 58.046335 | K96: 349.02484 | L96: 157.66616 | M96: 382.02728 | N96: 908.11673 | O96: 296.41027 | P96: 170.41836 | Q96: 67.579892 | R96: 646.94848 | S96: 279.4069 | T96: 9011.4152 | U96: 7080.677 | V96: 1219.5779 | W96: 302.68467 | X96: 10.361463 | Y96: 1008.8637 | Z96: 637.91589 | AA96: 902.29465 | AB96: 4552.0074 | AC96: 510.24278 | AD96: 6568.6637 | AE96: 51379.516 | AF96: 1852.9477 | AG96: 1871.8314 | AH96: 785.0506 | AI96: 585.22456
C97: 1109.1749 | D97: 4612.3245 | E97: 10010.347 | F97: 3134.1507 | G97: 27.944415 | H97: 2360.8149 | I97: 4843.2671 | J97: 968.38931 | K97: 5822.7953 | L97: 2630.3508 | M97: 6373.3763 | N97: 15150.148 | O97: 4945.0244 | P97: 2843.0964 | Q97: 1127.438 | R97: 10793.067 | S97: 20480.942 | T97: 61763.987 | U97: 504020.18 | V97: 162664.28 | W97: 26194.216 | X97: 896.67712 | Y97: 87306.682 | Z97: 55204.998 | AA97: 29876.518 | AB97: 83575.095 | AC97: 42529.998 | AD97: 221755.58 | AE97: 113842.64 | AF97: 48441.03 | AG97: 36593.819 | AH97: 49622.505 | AI97: 12096.736
C98: 6689.9485 | D98: 4525.3538 | E98: 28943.606 | F98: 9061.9857 | G98: 80.797603 | H98: 6825.9868 | I98: 14003.672 | J98: 2799.9708 | K98: 16835.85 | L98: 7605.315 | M98: 18427.782 | N98: 43804.666 | O98: 14297.889 | P98: 8220.4401 | Q98: 3259.8393 | R98: 31206.739 | S98: 22498.587 | T98: 226827.71 | U98: 156971.51 | V98: 9238.0557 | W98: 12426.49 | X98: 425.38202 | Y98: 41418.136 | Z98: 26189.153 | AA98: 14173.368 | AB98: 3492.47 | AC98: 3944.1118 | AD98: 20564.989 | AE98: 14086.223 | AF98: 1497.5349 | AG98: 4639.0071 | AH98: 2975.2227 | AI98: 162.21353
C99: 3525.5281 | D99: 4130.6105 | E99: 17608.806 | F99: 5513.1608 | G99: 49.155913 | H99: 4152.8164 | I99: 8519.6003 | J99: 1703.4554 | K99: 10242.65 | L99: 4626.9465 | M99: 11211.155 | N99: 26650.027 | O99: 8698.5971 | P99: 5001.1786 | Q99: 1983.2318 | R99: 18985.659 | S99: 19428.534 | T99: 130455.45 | U99: 298795.73 | V99: 77707.005 | W99: 17458.165 | X99: 597.6257 | Y99: 58188.971 | Z99: 36793.541 | AA99: 19912.38 | AB99: 39358.16 | AC99: 21008.23 | AD99: 109538.97 | AE99: 57829.167 | AF99: 22574.308 | AG99: 18638.952 | AH99: 23776.36 | AI99: 5541.5551
A101: Implied wages | C101: =C78/C96*10^6 -> 48318.212 | D101: =D78/D96*10^6 -> 216350.78 | E101: =E78/E96*10^6 -> 115291.73 | F101: =F78/F96*10^6 -> 115291.73 | G101: =G78/G96*10^6 -> 115291.74 | H101: =H78/H96*10^6 -> 115291.73 | I101: =I78/I96*10^6 -> 115291.73 | J101: =J78/J96*10^6 -> 115291.73 | ... AI101: =AI78/AI96*10^6 -> 252542.79
C102: =C79/C97*10^6 -> 21362.919 | D102: =D79/D97*10^6 -> 140952.34 | E102: =E79/E97*10^6 -> 86071.579 | F102: =F79/F97*10^6 -> 86071.58 | G102: =G79/G97*10^6 -> 86071.588 | H102: =H79/H97*10^6 -> 86071.581 | I102: =I79/I97*10^6 -> 86071.579 | J102: =J79/J97*10^6 -> 86071.585 | ... AI102: =AI79/AI97*10^6 -> 105461.21
C103: =C80/C98*10^6 -> 19743.133 | D103: =D80/D98*10^6 -> 36925.148 | E103: =E80/E98*10^6 -> 34373.218 | F103: =F80/F98*10^6 -> 34373.219 | G103: =G80/G98*10^6 -> 34373.22 | H103: =H80/H98*10^6 -> 34373.219 | I103: =I80/I98*10^6 -> 34373.219 | J103: =J80/J98*10^6 -> 34373.22 | ... AI103: =AI80/AI98*10^6 -> 24857.229
C104: =C81/C99*10^6 -> 17864.95 | D104: =D81/D99*10^6 -> 79992.527 | E104: =E81/E99*10^6 -> 42627.426 | F104: =F81/F99*10^6 -> 42627.426 | G104: =G81/G99*10^6 -> 42627.43 | H104: =H81/H99*10^6 -> 42627.426 | I104: =I81/I99*10^6 -> 42627.426 | J104: =J81/J99*10^6 -> 42627.428 | ... AI104: =AI81/AI99*10^6 -> 93373.991

Sheet Calculations
C1: {='2022 SAM'!C3:AI3} -> Agriculture, hunting, forestry, and fishing | D1: Mining and quarrying | E1: Food, beverages, and tobacco | F1: Textiles and textile products | G1: Leather, leather products, and footwear | H1: Wood and products of wood and cork | I1: Pulp, paper, paper products, printing, and publishing | J1: Coke, refined petroleum, and nuclear fuel | K1: Chemicals and chemical products | L1: Rubber and plastics | M1: Other nonmetallic minerals | N1: Basic metals and fabricated metal | O1: Machinery, nec | P1: Electrical and optical equipment | Q1: Transport equipment | R1: Manufacturing, nec; recycling | S1: Electricity, gas, and water supply | T1: Construction | U1: Wholesale and Retail Trade; Repair of Motor Vehicles and Motorcycles | V1: Hotels and restaurants | W1: Inland transport | X1: Water transport | Y1: Air transport | Z1: Other supporting and auxiliary transport activities; activities of travel agencies | AA1: Post and telecommunications | AB1: Financial intermediation | AC1: Real estate activities | AD1: Renting of M&Eq and other business activities | AE1: Public administration and defense; compulsory social security | AF1: Education | AG1: Health and social work | AH1: Other community, social, and personal services | AI1: Private households with employed persons | AJ1: Agriculture, hunting, forestry, and fishing | AK1: Mining and quarrying | AL1: Food, beverages, and tobacco | AM1: Textiles and textile products | AN1: Leather, leather products, and footwear | AO1: Wood and products of wood and cork | AP1: Pulp, paper, paper products, printing, and publishing | AQ1: Coke, refined petroleum, and nuclear fuel | AR1: Chemicals and chemical products | AS1: Rubber and plastics | AT1: Other nonmetallic minerals | AU1: Basic metals and fabricated metal | AV1: Machinery, nec | AW1: Electrical and optical equipment | AX1: Transport equipment | AY1: Manufacturing, nec; recycling | AZ1: Electricity, gas, and water supply | BA1: Construction | BB1: Wholesale and Retail Trade; Repair of Motor Vehicles and Motorcycles | BC1: Hotels and restaurants | BD1: Inland transport | BE1: Water transport | BF1: Air transport | BG1: Other supporting and auxiliary transport activities; activities of travel agencies | BH1: Post and telecommunications | BI1: Financial intermediation | BJ1: Real estate activities | BK1: Renting of M&Eq and other business activities | BL1: Public administration and defense; compulsory social security | BM1: Education | BN1: Health and social work | BO1: Other community, social, and personal services | BP1: Private households with employed persons | BQ1: Emirati Labour | BR1: Migrant Labour | BS1: Commuting Labour | BT1: Capital | BU1: Indirect taxes | BV1: Subsidies | BW1: Direct taxes | BX1: Emirati Household | BY1: Non-Emirati Household | BZ1: Collective Households | CA1: Labour Camps | CB1: Commuting household | CC1: Government | CD1: Rest of the World | CE1: Savings - Investment | CF1: TOTAL
B2: Input data
C4: Total value of labour supplied by activity
C6: {='2022 SAM'!C70:AI70} -> 233 | D6: 1238 | E6: 2676.288 | F6: 837.922 | G6: 7.471 | H6: 631.169 | I6: 1294.858 | J6: 258.901 | K6: 1556.737 | L6: 703.23 | M6: 1703.936 | N6: 4050.425 | O6: 1322.063 | P6: 760.108 | Q6: 301.423 | R6: 2885.55 | S6: 4344 | T6: 20526.655 | U6: 53229 | V6: 13377.538 | W6: 4282.646 | X6: 146.603 | Y6: 14274.282 | Z6: 9025.789 | AA6: 4989.6802 | AB6: 12121.988 | AC6: 6997 | AD6: 37477.836 | AE6: 23934 | AF6: 6526 | AG6: 5247.7927 | AH6: 2665 | AI6: 1945
C8: Total value of labour and capital supplied by households
C10: Labour | D10: Capital
C11: {='2022 SAM'!BQ75:BR75} -> 241571.89 | D11: 206497.31
B12: Check | C12: =SUM(_xlfn.ANCHORARRAY(C6))-C11 -> 0
C14: Estimate of Emirati supply of labour by activity - there is decent data on this from an official publication
B16: Persons | C16: {='Labour force absolute size'!$H$17*TRANSPOSE('Emirati workforce distribution'!G82:G114)} -> 185.33617 | D16: 1176.0422 | E16: 900.31823 | F16: 281.88164 | G16: 2.5132861 | H16: 212.32878 | I16: 435.59746 | J16: 87.095742 | K16: 523.69502 | L16: 236.5705 | M16: 573.21358 | N16: 1362.5856 | O16: 444.74938 | P16: 255.70458 | Q16: 101.40038 | R16: 970.71513 | S16: 626.09928 | T16: 13636.024 | U16: 12551.639 | V16: 2102.0491 | W16: 742.45933 | X16: 25.415775 | Y16: 2474.6556 | Z16: 1564.7526 | AA16: 2213.2508 | AB16: 13034.187 | AC16: 1690.2659 | AD16: 21759.814 | AE16: 509.50598 | AF16: 5102.4732 | AG16: 4953.5304 | AH16: 869.39512 | AI16: 1923.4525
B17: Value, million AED | C17: =C16*'HES - 2014'!$F$2/10^6 -> 14.240861 | D17: =D16*'HES - 2014'!$F$2/10^6 -> 90.364734 | E17: =E16*'HES - 2014'!$F$2/10^6 -> 69.178652 | F17: =F16*'HES - 2014'!$F$2/10^6 -> 21.659221 | G17: =G16*'HES - 2014'!$F$2/10^6 -> 0.19311588 | H17: =H16*'HES - 2014'!$F$2/10^6 -> 16.314918 | I17: =I16*'HES - 2014'!$F$2/10^6 -> 33.470438 | J17: =J16*'HES - 2014'!$F$2/10^6 -> 6.6922626 | ... AD17: =AD16*'HES - 2014'!$F$2/10^6 -> 1671.9806 | AE17: =AE16*'HES - 2014'!$F$2/10^6*250 -> 9787.3551 | AF17: =AF16*'HES - 2014'!$F$2/10^6 -> 392.06384 | AG17: =AG16*'HES - 2014'!$F$2/10^6 -> 380.61937 | AH17: =AH16*'HES - 2014'!$F$2/10^6 -> 66.802582 | AI17: =AI16*'HES - 2014'!$F$2/10^6 -> 147.79424
B19: Check - as % of total | C19: =C17/C6 -> 0.061119573 | D19: =D17/D6 -> 0.072992515 | E19: =E17/E6 -> 0.025848732 | F19: =F17/F6 -> 0.025848732 | G19: =G17/G6 -> 0.025848732 | H19: =H17/H6 -> 0.025848732 | I19: =I17/I6 -> 0.025848732 | J19: =J17/J6 -> 0.025848732 | ... AI19: =AI17/AI6 -> 0.075986756
C21: Occupation by activity breakdown - this will help to map labour income to household types
D23: Percentage of value
B25: Professionals and managers | C25: {=TRANSPOSE('GTAP data'!P2:T34)} -> 0.0055274848 | D25: 0.38814891 | E25: 0.1172783 | F25: 0.11727831 | G25: 0.11727833 | H25: 0.11727831 | I25: 0.11727831 | J25: 0.11727832 | K25: 0.11727831 | L25: 0.1172783 | M25: 0.11727831 | N25: 0.11727831 | O25: 0.11727831 | P25: 0.11727831 | Q25: 0.1172783 | R25: 0.11727831 | S25: 0.19712716 | T25: 0.15721797 | U25: 0.10700638 | V25: 0.14568525 | W25: 0.23291133 | X25: 0.23291133 | Y25: 0.23291132 | Z25: 0.23291134 | AA25: 0.23291133 | AB25: 0.24900807 | AC25: 0.41809135 | AD25: 0.41809136 | AE25: 0.23581982 | AF25: 0.30796195 | AG25: 0.27949193 | AH25: 0.015254677 | AI25: 0.38072038
B26: Technicians and associate professionals | C26: 0.0025549028 | D26: 0.17122257 | E26: 0.12678159 | F26: 0.12678158 | G26: 0.1267816 | H26: 0.12678159 | I26: 0.12678158 | J26: 0.12678159 | K26: 0.12678158 | L26: 0.12678157 | M26: 0.12678158 | N26: 0.12678159 | O26: 0.12678158 | P26: 0.1267816 | Q26: 0.12678157 | R26: 0.12678158 | S26: 0.22001853 | T26: 0.068395922 | U26: 0.15212039 | V26: 0.043141848 | W26: 0.22673487 | X26: 0.22673489 | Y26: 0.22673492 | Z26: 0.22673487 | AA26: 0.22673489 | AB26: 0.23702443 | AC26: 0.29402063 | AD26: 0.2940206 | AE26: 0.20118003 | AF26: 0.24905581 | AG26: 0.25655973 | AH26: 0.022930647 | AI26: 0.41137093
B27: Clerical workers | C27: 0.0032232693 | D27: 0.094645027 | E27: 0.070668613 | F27: 0.070668621 | G27: 0.070668618 | H27: 0.070668607 | I27: 0.070668611 | J27: 0.070668609 | K27: 0.070668614 | L27: 0.070668613 | M27: 0.07066862 | N27: 0.070668611 | O27: 0.070668623 | P27: 0.070668618 | Q27: 0.070668618 | R27: 0.070668611 | S27: 0.20133883 | T27: 0.06007877 | U27: 0.13935393 | V27: 0.088517633 | W27: 0.2042543 | X27: 0.20425428 | Y27: 0.20425429 | Z27: 0.20425429 | AA27: 0.20425431 | AB27: 0.49147451 | AC27: 0.17026179 | AD27: 0.17026178 | AE27: 0.22339388 | AF27: 0.11178135 | AG27: 0.11597641 | AH27: 0.015116665 | AI27: 0.065444389
B28: Service and shop workers | C28: 0.0058491225 | D28: 0.10896437 | E28: 0.064079172 | F28: 0.064079172 | G28: 0.064079178 | H28: 0.064079166 | I28: 0.064079166 | J28: 0.064079163 | K28: 0.064079168 | L28: 0.06407916 | M28: 0.064079167 | N28: 0.064079175 | O28: 0.064079171 | P28: 0.064079173 | Q28: 0.064079169 | R28: 0.064079174 | S28: 0.093804349 | T28: 0.026323405 | U28: 0.46466311 | V28: 0.69208571 | W28: 0.18824913 | X28: 0.18824914 | Y28: 0.1882491 | Z28: 0.18824913 | AA28: 0.18824911 | AB28: 0.011010324 | AC28: 0.093691467 | AD28: 0.093691486 | AE28: 0.29403736 | AF28: 0.31997313 | AG28: 0.30281409 | AH28: 0.90845466 | AI28: 0.1388121
B29: Agricultural and low skilled workers | C29: 0.98284522 | D29: 0.23701913 | E29: 0.62119232 | F29: 0.62119232 | G29: 0.62119228 | H29: 0.62119233 | I29: 0.62119234 | J29: 0.62119232 | K29: 0.62119233 | L29: 0.62119236 | M29: 0.62119233 | N29: 0.62119231 | O29: 0.62119232 | P29: 0.6211923 | Q29: 0.62119234 | R29: 0.62119233 | S29: 0.28771113 | T29: 0.68798393 | U29: 0.1368562 | V29: 0.030569568 | W29: 0.14785037 | X29: 0.14785036 | Y29: 0.14785036 | Z29: 0.14785037 | AA29: 0.14785037 | AB29: 0.011482671 | AC29: 0.023934766 | AD29: 0.02393477 | AE29: 0.045568911 | AF29: 0.011227755 | AG29: 0.045157841 | AH29: 0.038243353 | AI29: 0.0036521994
D31: Value of non Emirati labour
B33: Professionals and managers | C33: =C25*(C$6-C$17) -> 1.2091878 | D33: =D25*(D$6-D$17) -> 445.45337 | E33: =E25*(E$6-E$17) -> 305.75736 | F33: =F25*(F$6-F$17) -> 95.729916 | G33: =G25*(G$6-G$17) -> 0.85353806 | H33: =H25*(H$6-H$17) -> 72.109048 | I33: =I25*(I$6-I$17) -> 147.9334 | J33: =J25*(J$6-J$17) -> 29.578618 | ... AI33: =AI25*(AI$6-AI$17) -> 684.23286
B34: Technicians and associate professionals | C34: =C26*(C$6-C$17) -> 0.55890834 | D34: =D26*(D$6-D$17) -> 196.50106 | E34: =E26*(E$6-E$17) -> 330.53347 | F34: =F26*(F$6-F$17) -> 103.48709 | G34: =G26*(G$6-G$17) -> 0.92270179 | H34: =H26*(H$6-H$17) -> 77.952176 | I34: =I26*(I$6-I$17) -> 159.92071 | J34: =J26*(J$6-J$17) -> 31.975424 | ... AI34: =AI26*(AI$6-AI$17) -> 739.31821
B35: Clerical workers | C35: =C27*(C$6-C$17) -> 0.70511961 | D35: =D27*(D$6-D$17) -> 108.61797 | E35: =E27*(E$6-E$17) -> 184.2408 | F35: =F27*(F$6-F$17) -> 57.684165 | G35: =G27*(G$6-G$17) -> 0.51431801 | H35: =H27*(H$6-H$17) -> 43.450881 | I35: =I27*(I$6-I$17) -> 89.140507 | J35: =J27*(J$6-J$17) -> 17.823241 | ... AI35: =AI27*(AI$6-AI$17) -> 117.61703
B36: Service and shop workers | C36: =C28*(C$6-C$17) -> 1.279549 | D36: =D28*(D$6-D$17) -> 125.05135 | E36: =E28*(E$6-E$17) -> 167.06141 | F36: =F28*(F$6-F$17) -> 52.305443 | G36: =G28*(G$6-G$17) -> 0.46636083 | H36: =H28*(H$6-H$17) -> 39.399337 | I36: =I28*(I$6-I$17) -> 80.828664 | J36: =J28*(J$6-J$17) -> 16.161325 | ... AI36: =AI28*(AI$6-AI$17) -> 249.47391
B37: Agricultural and low skilled workers | C37: =C29*(C$6-C$17) -> 215.00637 | D37: =D29*(D$6-D$17) -> 272.01151 | E37: =E29*(E$6-E$17) -> 1619.5163 | F37: =F29*(F$6-F$17) -> 507.05617 | G37: =G29*(G$6-G$17) -> 4.5209654 | H37: =H29*(H$6-H$17) -> 381.94264 | I37: =I29*(I$6-I$17) -> 783.56429 | J37: =J29*(J$6-J$17) -> 156.67013 | ... AI37: =AI29*(AI$6-AI$17) -> 6.5637538
C39: Estimate of wage differential by occupation
D41: ISCO Cat. | E41: Local currency
D43: ='ILO occupation by income'!E5 -> Occupation (ISCO-08): 1. Managers | E43: ='ILO occupation by income'!H18 -> 22038.627
D44: ='ILO occupation by income'!E6 -> Occupation (ISCO-08): 2. Professionals | E44: ='ILO occupation by income'!H19 -> 13688.694
D45: ='ILO occupation by income'!E7 -> Occupation (ISCO-08): 3. Technicians and associate professionals | E45: ='ILO occupation by income'!H20 -> 10221.388
D46: ='ILO occupation by income'!E8 -> Occupation (ISCO-08): 4. Clerical support workers | E46: ='ILO occupation by income'!H21 -> 7144.619
D47: ='ILO occupation by income'!E9 -> Occupation (ISCO-08): 5. Service and sales workers | E47: ='ILO occupation by income'!H22 -> 3680.021
D48: ='ILO occupation by income'!E10 -> Occupation (ISCO-08): 6. Skilled agricultural, forestry and fishery workers | E48: ='ILO occupation by income'!H23 -> 1260.034
D49: ='ILO occupation by income'!E11 -> Occupation (ISCO-08): 7. Craft and related trades workers | E49: ='ILO occupation by income'!H24 -> 2392.537
D50: ='ILO occupation by income'!E12 -> Occupation (ISCO-08): 8. Plant and machine operators, and assemblers | E50: ='ILO occupation by income'!H25 -> 3198.739
D51: ='ILO occupation by income'!E13 -> Occupation (ISCO-08): 9. Elementary occupations | E51: ='ILO occupation by income'!H26 -> 1797.091
D53: GTAP | E53: Local currency | F53: Indexed to max | G53: Inverse (for calcs below) | K53: Note - the aggregation of occupations is by simple averaging and could be refined
D55: Professionals and managers | E55: =AVERAGE(E43:E44) -> 17863.66 | F55: =E55/$E$55 -> 1 | G55: =1/F55 -> 1
D56: Technicians and associate professionals | E56: =E45 -> 10221.388 | F56: =E56/$E$55 -> 0.57218889 | G56: =1/F56 -> 1.7476746
D57: Clerical workers | E57: =E46 -> 7144.619 | F57: =E57/$E$55 -> 0.39995269 | G57: =1/F57 -> 2.5002957
D58: Service and shop workers | E58: =E47 -> 3680.021 | F58: =E58/$E$55 -> 0.20600599 | G58: =1/F58 -> 4.8542279
D59: Agricultural and low skilled workers | E59: =AVERAGE(E49:E51) -> 2462.789 | F59: =E59/$E$55 -> 0.13786586 | G59: =1/F59 -> 7.2534271
C61: Approximate allocation of workers to occupation and activity
D63: I want to do an approximate conversion to headcount - because I have approximately 500,000 people living in labour camps and I want to assign them to low skilled folk in construction and manufacturing | K63: https://www.laboraccommodation.ae/labor-camp-regulations-in-dubai-version-2025/
D65: In % terms, of non Emirati value
B67: Professionals and managers | C67: =(C$6-C$17)*C25/(SUM(_xlfn.ANCHORARRAY($C$6))-SUM($C$17:$AI$17)) -> 5.3828494e-06 | D67: =(D$6-D$17)*D25/(SUM(_xlfn.ANCHORARRAY($C$6))-SUM($C$17:$AI$17)) -> 0.0019829909 | E67: =(E$6-E$17)*E25/(SUM(_xlfn.ANCHORARRAY($C$6))-SUM($C$17:$AI$17)) -> 0.0013611168 | F67: =(F$6-F$17)*F25/(SUM(_xlfn.ANCHORARRAY($C$6))-SUM($C$17:$AI$17)) -> 0.00042615358 | G67: =(G$6-G$17)*G25/(SUM(_xlfn.ANCHORARRAY($C$6))-SUM($C$17:$AI$17)) -> 3.7996304e-06 | H67: =(H$6-H$17)*H25/(SUM(_xlfn.ANCHORARRAY($C$6))-SUM($C$17:$AI$17)) -> 0.00032100236 | I67: =(I$6-I$17)*I25/(SUM(_xlfn.ANCHORARRAY($C$6))-SUM($C$17:$AI$17)) -> 0.00065854385 | J67: =(J$6-J$17)*J25/(SUM(_xlfn.ANCHORARRAY($C$6))-SUM($C$17:$AI$17)) -> 0.00013167288 | ... AI67: =(AI$6-AI$17)*AI25/(SUM(_xlfn.ANCHORARRAY($C$6))-SUM($C$17:$AI$17)) -> 0.0030459473
B68: Technicians and associate professionals | C68: =(C$6-C$17)*C26/(SUM(_xlfn.ANCHORARRAY($C$6))-SUM($C$17:$AI$17)) -> 2.4880497e-06 | D68: =(D$6-D$17)*D26/(SUM(_xlfn.ANCHORARRAY($C$6))-SUM($C$17:$AI$17)) -> 0.00087474884 | E68: =(E$6-E$17)*E26/(SUM(_xlfn.ANCHORARRAY($C$6))-SUM($C$17:$AI$17)) -> 0.0014714107 | F68: =(F$6-F$17)*F26/(SUM(_xlfn.ANCHORARRAY($C$6))-SUM($C$17:$AI$17)) -> 0.0004606856 | G68: =(G$6-G$17)*G26/(SUM(_xlfn.ANCHORARRAY($C$6))-SUM($C$17:$AI$17)) -> 4.1075213e-06 | H68: =(H$6-H$17)*H26/(SUM(_xlfn.ANCHORARRAY($C$6))-SUM($C$17:$AI$17)) -> 0.00034701377 | I68: =(I$6-I$17)*I26/(SUM(_xlfn.ANCHORARRAY($C$6))-SUM($C$17:$AI$17)) -> 0.00071190684 | J68: =(J$6-J$17)*J26/(SUM(_xlfn.ANCHORARRAY($C$6))-SUM($C$17:$AI$17)) -> 0.00014234256 | ... AI68: =(AI$6-AI$17)*AI26/(SUM(_xlfn.ANCHORARRAY($C$6))-SUM($C$17:$AI$17)) -> 0.0032911666
B69: Clerical workers | C69: =(C$6-C$17)*C27/(SUM(_xlfn.ANCHORARRAY($C$6))-SUM($C$17:$AI$17)) -> 3.1389273e-06 | D69: =(D$6-D$17)*D27/(SUM(_xlfn.ANCHORARRAY($C$6))-SUM($C$17:$AI$17)) -> 0.00048352635 | E69: =(E$6-E$17)*E27/(SUM(_xlfn.ANCHORARRAY($C$6))-SUM($C$17:$AI$17)) -> 0.00082017075 | F69: =(F$6-F$17)*F27/(SUM(_xlfn.ANCHORARRAY($C$6))-SUM($C$17:$AI$17)) -> 0.00025678821 | G69: =(G$6-G$17)*G27/(SUM(_xlfn.ANCHORARRAY($C$6))-SUM($C$17:$AI$17)) -> 2.2895504e-06 | H69: =(H$6-H$17)*H27/(SUM(_xlfn.ANCHORARRAY($C$6))-SUM($C$17:$AI$17)) -> 0.00019342698 | I69: =(I$6-I$17)*I27/(SUM(_xlfn.ANCHORARRAY($C$6))-SUM($C$17:$AI$17)) -> 0.00039682001 | J69: =(J$6-J$17)*J27/(SUM(_xlfn.ANCHORARRAY($C$6))-SUM($C$17:$AI$17)) -> 7.9342364e-05 | ... AI69: =(AI$6-AI$17)*AI27/(SUM(_xlfn.ANCHORARRAY($C$6))-SUM($C$17:$AI$17)) -> 0.00052358679
B70: Service and shop workers | C70: =(C$6-C$17)*C28/(SUM(_xlfn.ANCHORARRAY($C$6))-SUM($C$17:$AI$17)) -> 5.6960709e-06 | D70: =(D$6-D$17)*D28/(SUM(_xlfn.ANCHORARRAY($C$6))-SUM($C$17:$AI$17)) -> 0.00055668157 | E70: =(E$6-E$17)*E28/(SUM(_xlfn.ANCHORARRAY($C$6))-SUM($C$17:$AI$17)) -> 0.00074369456 | F70: =(F$6-F$17)*F28/(SUM(_xlfn.ANCHORARRAY($C$6))-SUM($C$17:$AI$17)) -> 0.00023284416 | G70: =(G$6-G$17)*G28/(SUM(_xlfn.ANCHORARRAY($C$6))-SUM($C$17:$AI$17)) -> 2.076063e-06 | H70: =(H$6-H$17)*H28/(SUM(_xlfn.ANCHORARRAY($C$6))-SUM($C$17:$AI$17)) -> 0.00017539103 | I70: =(I$6-I$17)*I28/(SUM(_xlfn.ANCHORARRAY($C$6))-SUM($C$17:$AI$17)) -> 0.00035981881 | J70: =(J$6-J$17)*J28/(SUM(_xlfn.ANCHORARRAY($C$6))-SUM($C$17:$AI$17)) -> 7.194414e-05 | ... AI70: =(AI$6-AI$17)*AI28/(SUM(_xlfn.ANCHORARRAY($C$6))-SUM($C$17:$AI$17)) -> 0.001110564
B71: Agricultural and low skilled workers | C71: =(C$6-C$17)*C29/(SUM(_xlfn.ANCHORARRAY($C$6))-SUM($C$17:$AI$17)) -> 0.00095712752 | D71: =(D$6-D$17)*D29/(SUM(_xlfn.ANCHORARRAY($C$6))-SUM($C$17:$AI$17)) -> 0.0012108929 | E71: =(E$6-E$17)*E29/(SUM(_xlfn.ANCHORARRAY($C$6))-SUM($C$17:$AI$17)) -> 0.0072094775 | F71: =(F$6-F$17)*F29/(SUM(_xlfn.ANCHORARRAY($C$6))-SUM($C$17:$AI$17)) -> 0.0022572234 | G71: =(G$6-G$17)*G29/(SUM(_xlfn.ANCHORARRAY($C$6))-SUM($C$17:$AI$17)) -> 2.0125638e-05 | H71: =(H$6-H$17)*H29/(SUM(_xlfn.ANCHORARRAY($C$6))-SUM($C$17:$AI$17)) -> 0.001700265 | I71: =(I$6-I$17)*I29/(SUM(_xlfn.ANCHORARRAY($C$6))-SUM($C$17:$AI$17)) -> 0.0034881335 | J71: =(J$6-J$17)*J29/(SUM(_xlfn.ANCHORARRAY($C$6))-SUM($C$17:$AI$17)) -> 0.0006974365 | ... AI71: =(AI$6-AI$17)*AI29/(SUM(_xlfn.ANCHORARRAY($C$6))-SUM($C$17:$AI$17)) -> 2.9219363e-05
B73: Check | C73: =1-SUM(C67:AI71) -> 0
D75: Adjusted for wage differential
B77: Professionals and managers | C77: =C67*$G55/SUMPRODUCT(C$67:C$71,$G$55:$G$59)*SUM(C$67:C$71) -> 7.5017682e-07 | D77: =D67*$G55/SUMPRODUCT(D$67:D$71,$G$55:$G$59)*SUM(D$67:D$71) -> 0.00062512133 | E77: =E67*$G55/SUMPRODUCT(E$67:E$71,$G$55:$G$59)*SUM(E$67:E$71) -> 0.00025525541 | F77: =F67*$G55/SUMPRODUCT(F$67:F$71,$G$55:$G$59)*SUM(F$67:F$71) -> 7.9918205e-05 | G77: =G67*$G55/SUMPRODUCT(G$67:G$71,$G$55:$G$59)*SUM(G$67:G$71) -> 7.125592e-07 | H77: =H67*$G55/SUMPRODUCT(H$67:H$71,$G$55:$G$59)*SUM(H$67:H$71) -> 6.0198796e-05 | I77: =I67*$G55/SUMPRODUCT(I$67:I$71,$G$55:$G$59)*SUM(I$67:I$71) -> 0.00012349924 | J77: =J67*$G55/SUMPRODUCT(J$67:J$71,$G$55:$G$59)*SUM(J$67:J$71) -> 2.4693117e-05 | ... AI77: =AI67*$G55/SUMPRODUCT(AI$67:AI$71,$G$55:$G$59)*SUM(AI$67:AI$71) -> 0.0015511979
B78: Technicians and associate professionals | C78: =C68*$G56/SUMPRODUCT(C$67:C$71,$G$55:$G$59)*SUM(C$67:C$71) -> 6.059978e-07 | D78: =D68*$G56/SUMPRODUCT(D$67:D$71,$G$55:$G$59)*SUM(D$67:D$71) -> 0.00048193399 | E78: =E68*$G56/SUMPRODUCT(E$67:E$71,$G$55:$G$59)*SUM(E$67:E$71) -> 0.00048225203 | F78: =F68*$G56/SUMPRODUCT(F$67:F$71,$G$55:$G$59)*SUM(F$67:F$71) -> 0.00015098882 | G78: =G68*$G56/SUMPRODUCT(G$67:G$71,$G$55:$G$59)*SUM(G$67:G$71) -> 1.3462323e-06 | H78: =H68*$G56/SUMPRODUCT(H$67:H$71,$G$55:$G$59)*SUM(H$67:H$71) -> 0.0001137331 | I78: =I68*$G56/SUMPRODUCT(I$67:I$71,$G$55:$G$59)*SUM(I$67:I$71) -> 0.0002333261 | J78: =J68*$G56/SUMPRODUCT(J$67:J$71,$G$55:$G$59)*SUM(J$67:J$71) -> 4.6652502e-05 | ... AI78: =AI68*$G56/SUMPRODUCT(AI$67:AI$71,$G$55:$G$59)*SUM(AI$67:AI$71) -> 0.0029292421
B79: Clerical workers | C79: =C69*$G57/SUMPRODUCT(C$67:C$71,$G$55:$G$59)*SUM(C$67:C$71) -> 1.0937651e-06 | D79: =D69*$G57/SUMPRODUCT(D$67:D$71,$G$55:$G$59)*SUM(D$67:D$71) -> 0.0003811142 | E79: =E69*$G57/SUMPRODUCT(E$67:E$71,$G$55:$G$59)*SUM(E$67:E$71) -> 0.00038456985 | F79: =F69*$G57/SUMPRODUCT(F$67:F$71,$G$55:$G$59)*SUM(F$67:F$71) -> 0.00012040542 | G79: =G69*$G57/SUMPRODUCT(G$67:G$71,$G$55:$G$59)*SUM(G$67:G$71) -> 1.0735473e-06 | H79: =H69*$G57/SUMPRODUCT(H$67:H$71,$G$55:$G$59)*SUM(H$67:H$71) -> 9.0695974e-05 | I79: =I69*$G57/SUMPRODUCT(I$67:I$71,$G$55:$G$59)*SUM(I$67:I$71) -> 0.00018606493 | J79: =J69*$G57/SUMPRODUCT(J$67:J$71,$G$55:$G$59)*SUM(J$67:J$71) -> 3.720284e-05 | ... AI79: =AI69*$G57/SUMPRODUCT(AI$67:AI$71,$G$55:$G$59)*SUM(AI$67:AI$71) -> 0.00066669144
B80: Service and shop workers | C80: =C70*$G58/SUMPRODUCT(C$67:C$71,$G$55:$G$59)*SUM(C$67:C$71) -> 3.8534254e-06 | D80: =D70*$G58/SUMPRODUCT(D$67:D$71,$G$55:$G$59)*SUM(D$67:D$71) -> 0.00085186466 | E80: =E70*$G58/SUMPRODUCT(E$67:E$71,$G$55:$G$59)*SUM(E$67:E$71) -> 0.00067700884 | F80: =F70*$G58/SUMPRODUCT(F$67:F$71,$G$55:$G$59)*SUM(F$67:F$71) -> 0.00021196545 | G80: =G70*$G58/SUMPRODUCT(G$67:G$71,$G$55:$G$59)*SUM(G$67:G$71) -> 1.8899064e-06 | H80: =H70*$G58/SUMPRODUCT(H$67:H$71,$G$55:$G$59)*SUM(H$67:H$71) -> 0.00015966404 | I80: =I70*$G58/SUMPRODUCT(I$67:I$71,$G$55:$G$59)*SUM(I$67:I$71) -> 0.00032755452 | J80: =J70*$G58/SUMPRODUCT(J$67:J$71,$G$55:$G$59)*SUM(J$67:J$71) -> 6.5493042e-05 | ... AI80: =AI70*$G58/SUMPRODUCT(AI$67:AI$71,$G$55:$G$59)*SUM(AI$67:AI$71) -> 0.0027454186
B81: Agricultural and low skilled workers | C81: =C71*$G59/SUMPRODUCT(C$67:C$71,$G$55:$G$59)*SUM(C$67:C$71) -> 0.00096753005 | D81: =D71*$G59/SUMPRODUCT(D$67:D$71,$G$55:$G$59)*SUM(D$67:D$71) -> 0.0027688064 | E81: =E71*$G59/SUMPRODUCT(E$67:E$71,$G$55:$G$59)*SUM(E$67:E$71) -> 0.0098067842 | F81: =F71*$G59/SUMPRODUCT(F$67:F$71,$G$55:$G$59)*SUM(F$67:F$71) -> 0.003070417 | G81: =G71*$G59/SUMPRODUCT(G$67:G$71,$G$55:$G$59)*SUM(G$67:G$71) -> 2.7376158e-05 | H81: =H71*$G59/SUMPRODUCT(H$67:H$71,$G$55:$G$59)*SUM(H$67:H$71) -> 0.0023128072 | I81: =I71*$G59/SUMPRODUCT(I$67:I$71,$G$55:$G$59)*SUM(I$67:I$71) -> 0.0047447782 | J81: =J71*$G59/SUMPRODUCT(J$67:J$71,$G$55:$G$59)*SUM(J$67:J$71) -> 0.00094869694 | ... AI81: =AI71*$G59/SUMPRODUCT(AI$67:AI$71,$G$55:$G$59)*SUM(AI$67:AI$71) -> 0.00010793413
B83: Check | C83: =1-SUM(C77:AI81) -> 0
D85: In persons, total
AK86: Total
B87: Professionals and managers | C87: {=C77:AI81*'Labour force absolute size'!H23} -> 2.6270767 | D87: 2189.1394 | E87: 893.88997 | F87: 279.86902 | G87: 2.4953419 | H87: 210.81277 | I87: 432.48732 | J87: 86.473896 | K87: 519.95588 | L87: 234.88137 | M87: 569.12086 | N87: 1352.8569 | O87: 441.5739 | P87: 253.87887 | Q87: 100.67638 | R87: 963.78427 | S87: 3639.5242 | T87: 8609.8064 | U87: 21963.605 | V87: 7459.6854 | W87: 4907.999 | X87: 168.01 | Y87: 16358.616 | Z87: 10343.737 | AA87: 5597.9505 | AB87: 21277.53 | AC87: 22536.258 | AD87: 117506.26 | AE87: 17909.819 | AF87: 11081.802 | AG87: 7532.596 | AH87: 129.25325 | AI87: 5432.207 | AK87: =SUM(C87:AI87) -> 290989.19
B88: Technicians and associate professionals | C88: 2.1221699 | D88: 1687.7055 | E88: 1688.8192 | F88: 528.75428 | G88: 4.7144291 | H88: 398.28685 | I88: 817.09477 | J88: 163.37442 | K88: 982.34835 | L88: 443.75948 | M88: 1075.2354 | N88: 2555.9415 | O88: 834.26195 | P88: 479.65134 | Q88: 190.20706 | R88: 1820.8698 | S88: 7099.3404 | T88: 6546.0904 | U88: 54568.493 | V88: 3860.6841 | W88: 8350.1203 | X88: 285.8403 | Y88: 27831.394 | Z88: 17598.098 | AA88: 9523.9557 | AB88: 35396.595 | AC88: 27698.039 | AD88: 144420.27 | AE88: 26702.772 | AF88: 15662.842 | AG88: 12084.383 | AH88: 339.55907 | AI88: 10258.04 | AK88: =SUM(C88:AI88) -> 421899.66
B89: Clerical workers | C89: 3.8303033 | D89: 1334.6403 | E89: 1346.7418 | F89: 421.65295 | G89: 3.7595017 | H89: 317.61216 | I89: 651.58882 | J89: 130.28224 | K89: 783.36966 | L89: 353.87418 | M89: 857.44213 | N89: 2038.2248 | O89: 665.27884 | P89: 382.49595 | Q89: 151.67986 | R89: 1452.045 | S89: 9294.3084 | T89: 8226.2826 | U89: 71516.222 | V89: 11332.51 | W89: 10761.59 | X89: 368.38936 | Y89: 35868.938 | Z89: 22680.332 | AA89: 12274.422 | AB89: 105002.63 | AC89: 22946.645 | AD89: 119646.05 | AE89: 42420.281 | AF89: 10057.13 | AG89: 7815.1347 | AH89: 320.24755 | AI89: 2334.7156 | AK89: =SUM(C89:AI89) -> 503760.35
B90: Service and shop workers | C90: 13.494477 | D90: 2983.1817 | E90: 2370.8466 | F90: 742.291 | G90: 6.6183449 | H90: 559.13441 | I90: 1147.0773 | J90: 229.35292 | K90: 1379.0684 | L90: 622.97109 | M90: 1509.4678 | N90: 3588.1552 | O90: 1171.1776 | P90: 673.35783 | Q90: 267.02195 | R90: 2556.2258 | S90: 8407.0046 | T90: 6997.6696 | U90: 462969.43 | V90: 172022.39 | W90: 19256.04 | X90: 659.17037 | Y90: 64181.375 | Z90: 40582.611 | AA90: 21962.993 | AB90: 4566.9689 | AC90: 24514.94 | AD90: 127823.33 | AE90: 108401.07 | AF90: 55891.656 | AG90: 39616.093 | AH90: 37364.731 | AI90: 9614.3002 | AK90: =SUM(C90:AI90) -> 1224651.2
B91: Agricultural and low skilled workers | C91: 3388.2354 | D91: 9696.203 | E91: 34342.802 | F91: 10752.426 | G91: 95.869752 | H91: 8099.3197 | I91: 16615.944 | J91: 3322.2829 | K91: 19976.442 | L91: 9024.0248 | M91: 21865.336 | N91: 51976.074 | O91: 16965.045 | P91: 9753.8973 | Q91: 3867.9359 | R91: 37028.105 | S91: 38529.916 | T91: 273283.09 | U91: 203751.91 | V91: 11353.702 | W91: 22598.494 | X91: 773.5888 | Y91: 75321.959 | Z91: 47626.921 | AA91: 25775.323 | AB91: 7116.951 | AC91: 9358.0006 | AD91: 48793.54 | AE91: 25102.836 | AF91: 2930.5524 | AG91: 8827.7867 | AH91: 2350.3777 | AI91: 377.97922 | AK91: =SUM(C91:AI91) -> 1060642.9
D93: By household type
D95: Labour camps - all low skilled folk in agriculture, mining, manufacting, construction
B96: Professionals and managers | C96: 0 | D96: 0 | E96: 0 | F96: 0 | G96: 0 | H96: 0 | I96: 0 | J96: 0 | K96: 0 | L96: 0 | M96: 0 | N96: 0 | O96: 0 | P96: 0 | Q96: 0 | R96: 0 | S96: 0 | T96: 0 | U96: 0 | V96: 0 | W96: 0 | X96: 0 | Y96: 0 | Z96: 0 | AA96: 0 | AB96: 0 | AC96: 0 | AD96: 0 | AE96: 0 | AF96: 0 | AG96: 0 | AH96: 0 | AI96: 0
B97: Technicians and associate professionals | C97: 0 | D97: 0 | E97: 0 | F97: 0 | G97: 0 | H97: 0 | I97: 0 | J97: 0 | K97: 0 | L97: 0 | M97: 0 | N97: 0 | O97: 0 | P97: 0 | Q97: 0 | R97: 0 | S97: 0 | T97: 0 | U97: 0 | V97: 0 | W97: 0 | X97: 0 | Y97: 0 | Z97: 0 | AA97: 0 | AB97: 0 | AC97: 0 | AD97: 0 | AE97: 0 | AF97: 0 | AG97: 0 | AH97: 0 | AI97: 0
B98: Clerical workers | C98: 0 | D98: 0 | E98: 0 | F98: 0 | G98: 0 | H98: 0 | I98: 0 | J98: 0 | K98: 0 | L98: 0 | M98: 0 | N98: 0 | O98: 0 | P98: 0 | Q98: 0 | R98: 0 | S98: 0 | T98: 0 | U98: 0 | V98: 0 | W98: 0 | X98: 0 | Y98: 0 | Z98: 0 | AA98: 0 | AB98: 0 | AC98: 0 | AD98: 0 | AE98: 0 | AF98: 0 | AG98: 0 | AH98: 0 | AI98: 0
B99: Service and shop workers | C99: 0 | D99: 0 | E99: 0 | F99: 0 | G99: 0 | H99: 0 | I99: 0 | J99: 0 | K99: 0 | L99: 0 | M99: 0 | N99: 0 | O99: 0 | P99: 0 | Q99: 0 | R99: 0 | S99: 0 | T99: 0 | U99: 0 | V99: 0 | W99: 0 | X99: 0 | Y99: 0 | Z99: 0 | AA99: 0 | AB99: 0 | AC99: 0 | AD99: 0 | AE99: 0 | AF99: 0 | AG99: 0 | AH99: 0 | AI99: 0
B100: Agricultural and low skilled workers | C100: 1 | D100: 1 | E100: 1 | F100: 1 | G100: 1 | H100: 1 | I100: 1 | J100: 1 | K100: 1 | L100: 1 | M100: 1 | N100: 1 | O100: 1 | P100: 1 | Q100: 1 | R100: 1 | S100: 1 | T100: 1 | U100: 0 | V100: 0 | W100: 0 | X100: 0 | Y100: 0 | Z100: 0 | AA100: 0 | AB100: 0 | AC100: 0 | AD100: 0 | AE100: 0 | AF100: 0 | AG100: 0 | AH100: 0 | AI100: 0
B102: Implied value of labour by sector | C102: =SUMPRODUCT(C96:C100,C$33:C$37) -> 215.00637 | D102: =SUMPRODUCT(D96:D100,D$33:D$37) -> 272.01151 | E102: =SUMPRODUCT(E96:E100,E$33:E$37) -> 1619.5163 | F102: =SUMPRODUCT(F96:F100,F$33:F$37) -> 507.05617 | G102: =SUMPRODUCT(G96:G100,G$33:G$37) -> 4.5209654 | H102: =SUMPRODUCT(H96:H100,H$33:H$37) -> 381.94264 | I102: =SUMPRODUCT(I96:I100,I$33:I$37) -> 783.56429 | J102: =SUMPRODUCT(J96:J100,J$33:J$37) -> 156.67013 | ... AI102: =SUMPRODUCT(AI96:AI100,AI$33:AI$37) -> 0
B103: Implied total persons | C103: =SUMPRODUCT(C96:AI100,_xlfn.ANCHORARRAY($C$87)) -> 568582.95
B104: Implied value of labour | C104: =SUMPRODUCT(C96:AI100,$C$33:$AI$37) -> 26615.726
B105: Implied wage (AED, annual) | C105: =C104*10^6/C103 -> 46810.629
B106: % of labour income | C106: =C104/SUM($C$104,$C$117,$C$130) -> 0.1184832
D108: Collective households - this is the remainder
B109: Professionals and managers | C109: =1-C96-C122 -> 0 | D109: =1-D96-D122 -> 0 | E109: =1-E96-E122 -> 0 | F109: =1-F96-F122 -> 0 | G109: =1-G96-G122 -> 0 | H109: =1-H96-H122 -> 0 | I109: =1-I96-I122 -> 0 | J109: =1-J96-J122 -> 0 | ... AI109: =1-AI96-AI122 -> 0
B110: Technicians and associate professionals | C110: =1-C97-C123 -> 0 | D110: =1-D97-D123 -> 0 | E110: =1-E97-E123 -> 0 | F110: =1-F97-F123 -> 0 | G110: =1-G97-G123 -> 0 | H110: =1-H97-H123 -> 0 | I110: =1-I97-I123 -> 0 | J110: =1-J97-J123 -> 0 | ... AI110: =1-AI97-AI123 -> 0
B111: Clerical workers | C111: =1-C98-C124 -> 0 | D111: =1-D98-D124 -> 0 | E111: =1-E98-E124 -> 0 | F111: =1-F98-F124 -> 0 | G111: =1-G98-G124 -> 0 | H111: =1-H98-H124 -> 0 | I111: =1-I98-I124 -> 0 | J111: =1-J98-J124 -> 0 | ... AI111: =1-AI98-AI124 -> 0
B112: Service and shop workers | C112: =1-C99-C125 -> 1 | D112: =1-D99-D125 -> 1 | E112: =1-E99-E125 -> 1 | F112: =1-F99-F125 -> 1 | G112: =1-G99-G125 -> 1 | H112: =1-H99-H125 -> 1 | I112: =1-I99-I125 -> 1 | J112: =1-J99-J125 -> 1 | ... AI112: =1-AI99-AI125 -> 1
B113: Agricultural and low skilled workers | C113: =1-C100-C126 -> 0 | D113: =1-D100-D126 -> 0 | E113: =1-E100-E126 -> 0 | F113: =1-F100-F126 -> 0 | G113: =1-G100-G126 -> 0 | H113: =1-H100-H126 -> 0 | I113: =1-I100-I126 -> 0 | J113: =1-J100-J126 -> 0 | ... AI113: =1-AI100-AI126 -> 1
B115: Implied value of labour by sector | C115: =SUMPRODUCT(C109:C113,C$33:C$37) -> 1.279549 | D115: =SUMPRODUCT(D109:D113,D$33:D$37) -> 125.05135 | E115: =SUMPRODUCT(E109:E113,E$33:E$37) -> 167.06141 | F115: =SUMPRODUCT(F109:F113,F$33:F$37) -> 52.305443 | G115: =SUMPRODUCT(G109:G113,G$33:G$37) -> 0.46636083 | H115: =SUMPRODUCT(H109:H113,H$33:H$37) -> 39.399337 | I115: =SUMPRODUCT(I109:I113,I$33:I$37) -> 80.828664 | J115: =SUMPRODUCT(J109:J113,J$33:J$37) -> 16.161325 | ... AI115: =SUMPRODUCT(AI109:AI113,AI$33:AI$37) -> 256.03766
B116: Implied total persons | C116: =SUMPRODUCT(C109:AI113,_xlfn.ANCHORARRAY($C$87)) -> 1716711.1
B117: Implied value of labour | C117: =SUMPRODUCT(C109:AI113,$C$33:$AI$37) -> 70546.604
B118: Implied wage (AED, annual) | C118: =C117*10^6/C116 -> 41094.045
B119: % of labour income | C119: =C117/SUM($C$104,$C$117,$C$130) -> 0.31404695
D121: Regular households - assuming all professionals to clerical live in regular households
B122: Professionals and managers | C122: 1 | D122: 1 | E122: 1 | F122: 1 | G122: 1 | H122: 1 | I122: 1 | J122: 1 | K122: 1 | L122: 1 | M122: 1 | N122: 1 | O122: 1 | P122: 1 | Q122: 1 | R122: 1 | S122: 1 | T122: 1 | U122: 1 | V122: 1 | W122: 1 | X122: 1 | Y122: 1 | Z122: 1 | AA122: 1 | AB122: 1 | AC122: 1 | AD122: 1 | AE122: 1 | AF122: 1 | AG122: 1 | AH122: 1 | AI122: 1
B123: Technicians and associate professionals | C123: 1 | D123: 1 | E123: 1 | F123: 1 | G123: 1 | H123: 1 | I123: 1 | J123: 1 | K123: 1 | L123: 1 | M123: 1 | N123: 1 | O123: 1 | P123: 1 | Q123: 1 | R123: 1 | S123: 1 | T123: 1 | U123: 1 | V123: 1 | W123: 1 | X123: 1 | Y123: 1 | Z123: 1 | AA123: 1 | AB123: 1 | AC123: 1 | AD123: 1 | AE123: 1 | AF123: 1 | AG123: 1 | AH123: 1 | AI123: 1
B124: Clerical workers | C124: 1 | D124: 1 | E124: 1 | F124: 1 | G124: 1 | H124: 1 | I124: 1 | J124: 1 | K124: 1 | L124: 1 | M124: 1 | N124: 1 | O124: 1 | P124: 1 | Q124: 1 | R124: 1 | S124: 1 | T124: 1 | U124: 1 | V124: 1 | W124: 1 | X124: 1 | Y124: 1 | Z124: 1 | AA124: 1 | AB124: 1 | AC124: 1 | AD124: 1 | AE124: 1 | AF124: 1 | AG124: 1 | AH124: 1 | AI124: 1
B125: Service and shop workers | C125: 0 | D125: 0 | E125: 0 | F125: 0 | G125: 0 | H125: 0 | I125: 0 | J125: 0 | K125: 0 | L125: 0 | M125: 0 | N125: 0 | O125: 0 | P125: 0 | Q125: 0 | R125: 0 | S125: 0 | T125: 0 | U125: 0 | V125: 0 | W125: 0 | X125: 0 | Y125: 0 | Z125: 0 | AA125: 0 | AB125: 0 | AC125: 0 | AD125: 0 | AE125: 0 | AF125: 0 | AG125: 0 | AH125: 0 | AI125: 0
B126: Agricultural and low skilled workers | C126: 0 | D126: 0 | E126: 0 | F126: 0 | G126: 0 | H126: 0 | I126: 0 | J126: 0 | K126: 0 | L126: 0 | M126: 0 | N126: 0 | O126: 0 | P126: 0 | Q126: 0 | R126: 0 | S126: 0 | T126: 0 | U126: 0 | V126: 0 | W126: 0 | X126: 0 | Y126: 0 | Z126: 0 | AA126: 0 | AB126: 0 | AC126: 0 | AD126: 0 | AE126: 0 | AF126: 0 | AG126: 0 | AH126: 0 | AI126: 0
B128: Implied value of labour by sector | C128: =SUMPRODUCT(C122:C126,C$33:C$37) -> 2.4732158 | D128: =SUMPRODUCT(D122:D126,D$33:D$37) -> 750.57241 | E128: =SUMPRODUCT(E122:E126,E$33:E$37) -> 820.53163 | F128: =SUMPRODUCT(F122:F126,F$33:F$37) -> 256.90117 | G128: =SUMPRODUCT(G122:G126,G$33:G$37) -> 2.2905579 | H128: =SUMPRODUCT(H122:H126,H$33:H$37) -> 193.51211 | I128: =SUMPRODUCT(I122:I126,I$33:I$37) -> 396.99461 | J128: =SUMPRODUCT(J122:J126,J$33:J$37) -> 79.377283 | ... AI128: =SUMPRODUCT(AI122:AI126,AI$33:AI$37) -> 1541.1681
B129: Implied total persons | C129: =SUMPRODUCT(C122:AI126,_xlfn.ANCHORARRAY($C$87)) -> 1216649.2
B130: Implied value of labour | C130: =SUMPRODUCT(C122:AI126,$C$33:$AI$37) -> 127474.8
B131: Implied wage (AED, annual) | C131: =C130*10^6/C129 -> 104775.31
B132: % of labour income | C132: =C130/SUM($C$104,$C$117,$C$130) -> 0.56746985
C134: Assumption - approximately 1100000 folks commuting
...

Sheet Input data ->

Sheet 2022 SAM
A1: Dubai SAM 2022
C2: Activities | AJ2: Commodities | BQ2: Factors | BS2: Tax | BV2: Institutions | BY2: Capital
B3: Million AED | C3: Agriculture, hunting, forestry, and fishing | D3: Mining and quarrying | E3: Food, beverages, and tobacco | F3: Textiles and textile products | G3: Leather, leather products, and footwear | H3: Wood and products of wood and cork | I3: Pulp, paper, paper products, printing, and publishing | J3: Coke, refined petroleum, and nuclear fuel | K3: Chemicals and chemical products | L3: Rubber and plastics | M3: Other nonmetallic minerals | N3: Basic metals and fabricated metal | O3: Machinery, nec | P3: Electrical and optical equipment | Q3: Transport equipment | R3: Manufacturing, nec; recycling | S3: Electricity, gas, and water supply | T3: Construction | U3: Wholesale and Retail Trade; Repair of Motor Vehicles and Motorcycles | V3: Hotels and restaurants | W3: Inland transport | X3: Water transport | Y3: Air transport | Z3: Other supporting and auxiliary transport activities; activities of travel agencies | AA3: Post and telecommunications | AB3: Financial intermediation | AC3: Real estate activities | AD3: Renting of M&Eq and other business activities | AE3: Public administration and defense; compulsory social security | AF3: Education | AG3: Health and social work | AH3: Other community, social, and personal services | AI3: Private households with employed persons | AJ3: Agriculture, hunting, forestry, and fishing | AK3: Mining and quarrying | AL3: Food, beverages, and tobacco | AM3: Textiles and textile products | AN3: Leather, leather products, and footwear | AO3: Wood and products of wood and cork | AP3: Pulp, paper, paper products, printing, and publishing | AQ3: Coke, refined petroleum, and nuclear fuel | AR3: Chemicals and chemical products | AS3: Rubber and plastics | AT3: Other nonmetallic minerals | AU3: Basic metals and fabricated metal | AV3: Machinery, nec | AW3: Electrical and optical equipment | AX3: Transport equipment | AY3: Manufacturing, nec; recycling | AZ3: Electricity, gas, and water supply | BA3: Construction | BB3: Wholesale and Retail Trade; Repair of Motor Vehicles and Motorcycles | BC3: Hotels and restaurants | BD3: Inland transport | BE3: Water transport | BF3: Air transport | BG3: Other supporting and auxiliary transport activities; activities of travel agencies | BH3: Post and telecommunications | BI3: Financial intermediation | BJ3: Real estate activities | BK3: Renting of M&Eq and other business activities | BL3: Public administration and defense; compulsory social security | BM3: Education | BN3: Health and social work | BO3: Other community, social, and personal services | BP3: Private households with employed persons | BQ3: Labour | BR3: Capital | BS3: Indirect taxes | BT3: Subsidies | BU3: Direct taxes | BV3: Households | BW3: Government | BX3: Rest of the World | BY3: Savings - Investment | BZ3: TOTAL
A4: Activities | B4: Agriculture, hunting, forestry, and fishing | C4: 0 | D4: 0 | E4: 0 | F4: 0 | G4: 0 | H4: 0 | I4: 0 | J4: 0 | K4: 0 | L4: 0 | M4: 0 | N4: 0 | O4: 0 | P4: 0 | Q4: 0 | R4: 0 | S4: 0 | T4: 0 | U4: 0 | V4: 0 | W4: 0 | X4: 0 | Y4: 0 | Z4: 0 | AA4: 0 | AB4: 0 | AC4: 0 | AD4: 0 | AE4: 0 | AF4: 0 | AG4: 0 | AH4: 0 | AI4: 0 | AJ4: 1512.2992 | AK4: 0 | AL4: 0 | AM4: 0 | AN4: 0 | AO4: 0 | AP4: 0 | AQ4: 0 | AR4: 0 | AS4: 0 | AT4: 0 | AU4: 0 | AV4: 0 | AW4: 0 | AX4: 0 | AY4: 0 | AZ4: 0 | BA4: 0 | BB4: 0 | BC4: 0 | BD4: 0 | BE4: 0 | BF4: 0 | BG4: 0 | BH4: 0 | BI4: 0 | BJ4: 0 | BK4: 0 | BL4: 0 | BM4: 0 | BN4: 0 | BO4: 0 | BP4: 0 | BQ4: 0 | BR4: 0 | BS4: 0 | BU4: 0 | BV4: 0 | BW4: 0 | BX4: 0 | BY4: 0 | BZ4: 1512.2992 | CB4: 1512.2992 | CD4: 0
B5: Mining and quarrying | C5: 0 | D5: 0 | E5: 0 | F5: 0 | G5: 0 | H5: 0 | I5: 0 | J5: 0 | K5: 0 | L5: 0 | M5: 0 | N5: 0 | O5: 0 | P5: 0 | Q5: 0 | R5: 0 | S5: 0 | T5: 0 | U5: 0 | V5: 0 | W5: 0 | X5: 0 | Y5: 0 | Z5: 0 | AA5: 0 | AB5: 0 | AC5: 0 | AD5: 0 | AE5: 0 | AF5: 0 | AG5: 0 | AH5: 0 | AI5: 0 | AJ5: 0 | AK5: 11448.729 | AL5: 0 | AM5: 0 | AN5: 0 | AO5: 0 | AP5: 0 | AQ5: 0 | AR5: 0 | AS5: 0 | AT5: 0 | AU5: 0 | AV5: 0 | AW5: 0 | AX5: 0 | AY5: 0 | AZ5: 0 | BA5: 0 | BB5: 0 | BC5: 0 | BD5: 0 | BE5: 0 | BF5: 0 | BG5: 0 | BH5: 0 | BI5: 0 | BJ5: 0 | BK5: 0 | BL5: 0 | BM5: 0 | BN5: 0 | BO5: 0 | BP5: 0 | BQ5: 0 | BR5: 0 | BS5: 0 | BU5: 0 | BV5: 0 | BW5: 0 | BX5: 0 | BY5: 0 | BZ5: 11448.729 | CB5: 11448.729 | CD5: 0
B6: Food, beverages, and tobacco | C6: 0 | D6: 0 | E6: 0 | F6: 0 | G6: 0 | H6: 0 | I6: 0 | J6: 0 | K6: 0 | L6: 0 | M6: 0 | N6: 0 | O6: 0 | P6: 0 | Q6: 0 | R6: 0 | S6: 0 | T6: 0 | U6: 0 | V6: 0 | W6: 0 | X6: 0 | Y6: 0 | Z6: 0 | AA6: 0 | AB6: 0 | AC6: 0 | AD6: 0 | AE6: 0 | AF6: 0 | AG6: 0 | AH6: 0 | AI6: 0 | AJ6: 0 | AK6: 0 | AL6: 25557.719 | AM6: 0 | AN6: 0 | AO6: 0 | AP6: 0 | AQ6: 0 | AR6: 0 | AS6: 0 | AT6: 0 | AU6: 0 | AV6: 0 | AW6: 0 | AX6: 0 | AY6: 0 | AZ6: 0 | BA6: 0 | BB6: 0 | BC6: 0 | BD6: 0 | BE6: 0 | BF6: 0 | BG6: 0 | BH6: 0 | BI6: 0 | BJ6: 0 | BK6: 0 | BL6: 0 | BM6: 0 | BN6: 0 | BO6: 0 | BP6: 0 | BQ6: 0 | BR6: 0 | BS6: 0 | BU6: 0 | BV6: 0 | BW6: 0 | BX6: 0 | BY6: 0 | BZ6: 25557.719 | CB6: 25557.719 | CD6: 0
B7: Textiles and textile products | C7: 0 | D7: 0 | E7: 0 | F7: 0 | G7: 0 | H7: 0 | I7: 0 | J7: 0 | K7: 0 | L7: 0 | M7: 0 | N7: 0 | O7: 0 | P7: 0 | Q7: 0 | R7: 0 | S7: 0 | T7: 0 | U7: 0 | V7: 0 | W7: 0 | X7: 0 | Y7: 0 | Z7: 0 | AA7: 0 | AB7: 0 | AC7: 0 | AD7: 0 | AE7: 0 | AF7: 0 | AG7: 0 | AH7: 0 | AI7: 0 | AJ7: 0 | AK7: 0 | AL7: 0 | AM7: 3421.037 | AN7: 0 | AO7: 0 | AP7: 0 | AQ7: 0 | AR7: 0 | AS7: 0 | AT7: 0 | AU7: 0 | AV7: 0 | AW7: 0 | AX7: 0 | AY7: 0 | AZ7: 0 | BA7: 0 | BB7: 0 | BC7: 0 | BD7: 0 | BE7: 0 | BF7: 0 | BG7: 0 | BH7: 0 | BI7: 0 | BJ7: 0 | BK7: 0 | BL7: 0 | BM7: 0 | BN7: 0 | BO7: 0 | BP7: 0 | BQ7: 0 | BR7: 0 | BS7: 0 | BU7: 0 | BV7: 0 | BW7: 0 | BX7: 0 | BY7: 0 | BZ7: 3421.037 | CB7: 3421.037 | CD7: 0
B8: Leather, leather products, and footwear | C8: 0 | D8: 0 | E8: 0 | F8: 0 | G8: 0 | H8: 0 | I8: 0 | J8: 0 | K8: 0 | L8: 0 | M8: 0 | N8: 0 | O8: 0 | P8: 0 | Q8: 0 | R8: 0 | S8: 0 | T8: 0 | U8: 0 | V8: 0 | W8: 0 | X8: 0 | Y8: 0 | Z8: 0 | AA8: 0 | AB8: 0 | AC8: 0 | AD8: 0 | AE8: 0 | AF8: 0 | AG8: 0 | AH8: 0 | AI8: 0 | AJ8: 0 | AK8: 0 | AL8: 0 | AM8: 0 | AN8: 29.598 | AO8: 0 | AP8: 0 | AQ8: 0 | AR8: 0 | AS8: 0 | AT8: 0 | AU8: 0 | AV8: 0 | AW8: 0 | AX8: 0 | AY8: 0 | AZ8: 0 | BA8: 0 | BB8: 0 | BC8: 0 | BD8: 0 | BE8: 0 | BF8: 0 | BG8: 0 | BH8: 0 | BI8: 0 | BJ8: 0 | BK8: 0 | BL8: 0 | BM8: 0 | BN8: 0 | BO8: 0 | BP8: 0 | BQ8: 0 | BR8: 0 | BS8: 0 | BU8: 0 | BV8: 0 | BW8: 0 | BX8: 0 | BY8: 0 | BZ8: 29.598 | CB8: 29.598 | CD8: 0
B9: Wood and products of wood and cork | C9: 0 | D9: 0 | E9: 0 | F9: 0 | G9: 0 | H9: 0 | I9: 0 | J9: 0 | K9: 0 | L9: 0 | M9: 0 | N9: 0 | O9: 0 | P9: 0 | Q9: 0 | R9: 0 | S9: 0 | T9: 0 | U9: 0 | V9: 0 | W9: 0 | X9: 0 | Y9: 0 | Z9: 0 | AA9: 0 | AB9: 0 | AC9: 0 | AD9: 0 | AE9: 0 | AF9: 0 | AG9: 0 | AH9: 0 | AI9: 0 | AJ9: 0 | AK9: 0 | AL9: 0 | AM9: 0 | AN9: 0 | AO9: 2673.883 | AP9: 0 | AQ9: 0 | AR9: 0 | AS9: 0 | AT9: 0 | AU9: 0 | AV9: 0 | AW9: 0 | AX9: 0 | AY9: 0 | AZ9: 0 | BA9: 0 | BB9: 0 | BC9: 0 | BD9: 0 | BE9: 0 | BF9: 0 | BG9: 0 | BH9: 0 | BI9: 0 | BJ9: 0 | BK9: 0 | BL9: 0 | BM9: 0 | BN9: 0 | BO9: 0 | BP9: 0 | BQ9: 0 | BR9: 0 | BS9: 0 | BU9: 0 | BV9: 0 | BW9: 0 | BX9: 0 | BY9: 0 | BZ9: 2673.883 | CB9: 2673.883 | CD9: 0
B10: Pulp, paper, paper products, printing, and publishing | C10: 0 | D10: 0 | E10: 0 | F10: 0 | G10: 0 | H10: 0 | I10: 0 | J10: 0 | K10: 0 | L10: 0 | M10: 0 | N10: 0 | O10: 0 | P10: 0 | Q10: 0 | R10: 0 | S10: 0 | T10: 0 | U10: 0 | V10: 0 | W10: 0 | X10: 0 | Y10: 0 | Z10: 0 | AA10: 0 | AB10: 0 | AC10: 0 | AD10: 0 | AE10: 0 | AF10: 0 | AG10: 0 | AH10: 0 | AI10: 0 | AJ10: 0 | AK10: 0 | AL10: 0 | AM10: 0 | AN10: 0 | AO10: 0 | AP10: 7097.443 | AQ10: 0 | AR10: 0 | AS10: 0 | AT10: 0 | AU10: 0 | AV10: 0 | AW10: 0 | AX10: 0 | AY10: 0 | AZ10: 0 | BA10: 0 | BB10: 0 | BC10: 0 | BD10: 0 | BE10: 0 | BF10: 0 | BG10: 0 | BH10: 0 | BI10: 0 | BJ10: 0 | BK10: 0 | BL10: 0 | BM10: 0 | BN10: 0 | BO10: 0 | BP10: 0 | BQ10: 0 | BR10: 0 | BS10: 0 | BU10: 0 | BV10: 0 | BW10: 0 | BX10: 0 | BY10: 0 | BZ10: 7097.443 | CB10: 7097.443 | CD10: 0
B11: Coke, refined petroleum, and nuclear fuel | C11: 0 | D11: 0 | E11: 0 | F11: 0 | G11: 0 | H11: 0 | I11: 0 | J11: 0 | K11: 0 | L11: 0 | M11: 0 | N11: 0 | O11: 0 | P11: 0 | Q11: 0 | R11: 0 | S11: 0 | T11: 0 | U11: 0 | V11: 0 | W11: 0 | X11: 0 | Y11: 0 | Z11: 0 | AA11: 0 | AB11: 0 | AC11: 0 | AD11: 0 | AE11: 0 | AF11: 0 | AG11: 0 | AH11: 0 | AI11: 0 | AJ11: 0 | AK11: 0 | AL11: 0 | AM11: 0 | AN11: 0 | AO11: 0 | AP11: 0 | AQ11: 28389.412 | AR11: 0 | AS11: 0 | AT11: 0 | AU11: 0 | AV11: 0 | AW11: 0 | AX11: 0 | AY11: 0 | AZ11: 0 | BA11: 0 | BB11: 0 | BC11: 0 | BD11: 0 | BE11: 0 | BF11: 0 | BG11: 0 | BH11: 0 | BI11: 0 | BJ11: 0 | BK11: 0 | BL11: 0 | BM11: 0 | BN11: 0 | BO11: 0 | BP11: 0 | BQ11: 0 | BR11: 0 | BS11: 0 | BU11: 0 | BV11: 0 | BW11: 0 | BX11: 0 | BY11: 0 | BZ11: 28389.412 | CB11: 28389.412 | CD11: 0
B12: Chemicals and chemical products | C12: 0 | D12: 0 | E12: 0 | F12: 0 | G12: 0 | H12: 0 | I12: 0 | J12: 0 | K12: 0 | L12: 0 | M12: 0 | N12: 0 | O12: 0 | P12: 0 | Q12: 0 | R12: 0 | S12: 0 | T12: 0 | U12: 0 | V12: 0 | W12: 0 | X12: 0 | Y12: 0 | Z12: 0 | AA12: 0 | AB12: 0 | AC12: 0 | AD12: 0 | AE12: 0 | AF12: 0 | AG12: 0 | AH12: 0 | AI12: 0 | AJ12: 0 | AK12: 0 | AL12: 0 | AM12: 0 | AN12: 0 | AO12: 0 | AP12: 0 | AQ12: 0 | AR12: 13147.266 | AS12: 0 | AT12: 0 | AU12: 0 | AV12: 0 | AW12: 0 | AX12: 0 | AY12: 0 | AZ12: 0 | BA12: 0 | BB12: 0 | BC12: 0 | BD12: 0 | BE12: 0 | BF12: 0 | BG12: 0 | BH12: 0 | BI12: 0 | BJ12: 0 | BK12: 0 | BL12: 0 | BM12: 0 | BN12: 0 | BO12: 0 | BP12: 0 | BQ12: 0 | BR12: 0 | BS12: 0 | BU12: 0 | BV12: 0 | BW12: 0 | BX12: 0 | BY12: 0 | BZ12: 13147.266 | CB12: 13147.266 | CD12: 0
B13: Rubber and plastics | C13: 0 | D13: 0 | E13: 0 | F13: 0 | G13: 0 | H13: 0 | I13: 0 | J13: 0 | K13: 0 | L13: 0 | M13: 0 | N13: 0 | O13: 0 | P13: 0 | Q13: 0 | R13: 0 | S13: 0 | T13: 0 | U13: 0 | V13: 0 | W13: 0 | X13: 0 | Y13: 0 | Z13: 0 | AA13: 0 | AB13: 0 | AC13: 0 | AD13: 0 | AE13: 0 | AF13: 0 | AG13: 0 | AH13: 0 | AI13: 0 | AJ13: 0 | AK13: 0 | AL13: 0 | AM13: 0 | AN13: 0 | AO13: 0 | AP13: 0 | AQ13: 0 | AR13: 0 | AS13: 6406.529 | AT13: 0 | AU13: 0 | AV13: 0 | AW13: 0 | AX13: 0 | AY13: 0 | AZ13: 0 | BA13: 0 | BB13: 0 | BC13: 0 | BD13: 0 | BE13: 0 | BF13: 0 | BG13: 0 | BH13: 0 | BI13: 0 | BJ13: 0 | BK13: 0 | BL13: 0 | BM13: 0 | BN13: 0 | BO13: 0 | BP13: 0 | BQ13: 0 | BR13: 0 | BS13: 0 | BU13: 0 | BV13: 0 | BW13: 0 | BX13: 0 | BY13: 0 | BZ13: 6406.529 | CB13: 6406.529 | CD13: 0
B14: Other nonmetallic minerals | C14: 0 | D14: 0 | E14: 0 | F14: 0 | G14: 0 | H14: 0 | I14: 0 | J14: 0 | K14: 0 | L14: 0 | M14: 0 | N14: 0 | O14: 0 | P14: 0 | Q14: 0 | R14: 0 | S14: 0 | T14: 0 | U14: 0 | V14: 0 | W14: 0 | X14: 0 | Y14: 0 | Z14: 0 | AA14: 0 | AB14: 0 | AC14: 0 | AD14: 0 | AE14: 0 | AF14: 0 | AG14: 0 | AH14: 0 | AI14: 0 | AJ14: 0 | AK14: 0 | AL14: 0 | AM14: 0 | AN14: 0 | AO14: 0 | AP14: 0 | AQ14: 0 | AR14: 0 | AS14: 0 | AT14: 8147.143 | AU14: 0 | AV14: 0 | AW14: 0 | AX14: 0 | AY14: 0 | AZ14: 0 | BA14: 0 | BB14: 0 | BC14: 0 | BD14: 0 | BE14: 0 | BF14: 0 | BG14: 0 | BH14: 0 | BI14: 0 | BJ14: 0 | BK14: 0 | BL14: 0 | BM14: 0 | BN14: 0 | BO14: 0 | BP14: 0 | BQ14: 0 | BR14: 0 | BS14: 0 | BU14: 0 | BV14: 0 | BW14: 0 | BX14: 0 | BY14: 0 | BZ14: 8147.143 | CB14: 8147.143 | CD14: 0
B15: Basic metals and fabricated metal | C15: 0 | D15: 0 | E15: 0 | F15: 0 | G15: 0 | H15: 0 | I15: 0 | J15: 0 | K15: 0 | L15: 0 | M15: 0 | N15: 0 | O15: 0 | P15: 0 | Q15: 0 | R15: 0 | S15: 0 | T15: 0 | U15: 0 | V15: 0 | W15: 0 | X15: 0 | Y15: 0 | Z15: 0 | AA15: 0 | AB15: 0 | AC15: 0 | AD15: 0 | AE15: 0 | AF15: 0 | AG15: 0 | AH15: 0 | AI15: 0 | AJ15: 0 | AK15: 0 | AL15: 0 | AM15: 0 | AN15: 0 | AO15: 0 | AP15: 0 | AQ15: 0 | AR15: 0 | AS15: 0 | AT15: 0 | AU15: 38703.505 | AV15: 0 | AW15: 0 | AX15: 0 | AY15: 0 | AZ15: 0 | BA15: 0 | BB15: 0 | BC15: 0 | BD15: 0 | BE15: 0 | BF15: 0 | BG15: 0 | BH15: 0 | BI15: 0 | BJ15: 0 | BK15: 0 | BL15: 0 | BM15: 0 | BN15: 0 | BO15: 0 | BP15: 0 | BQ15: 0 | BR15: 0 | BS15: 0 | BU15: 0 | BV15: 0 | BW15: 0 | BX15: 0 | BY15: 0 | BZ15: 38703.505 | CB15: 38703.505 | CD15: 0
B16: Machinery, nec | C16: 0 | D16: 0 | E16: 0 | F16: 0 | G16: 0 | H16: 0 | I16: 0 | J16: 0 | K16: 0 | L16: 0 | M16: 0 | N16: 0 | O16: 0 | P16: 0 | Q16: 0 | R16: 0 | S16: 0 | T16: 0 | U16: 0 | V16: 0 | W16: 0 | X16: 0 | Y16: 0 | Z16: 0 | AA16: 0 | AB16: 0 | AC16: 0 | AD16: 0 | AE16: 0 | AF16: 0 | AG16: 0 | AH16: 0 | AI16: 0 | AJ16: 0 | AK16: 0 | AL16: 0 | AM16: 0 | AN16: 0 | AO16: 0 | AP16: 0 | AQ16: 0 | AR16: 0 | AS16: 0 | AT16: 0 | AU16: 0 | AV16: 7111.347 | AW16: 0 | AX16: 0 | AY16: 0 | AZ16: 0 | BA16: 0 | BB16: 0 | BC16: 0 | BD16: 0 | BE16: 0 | BF16: 0 | BG16: 0 | BH16: 0 | BI16: 0 | BJ16: 0 | BK16: 0 | BL16: 0 | BM16: 0 | BN16: 0 | BO16: 0 | BP16: 0 | BQ16: 0 | BR16: 0 | BS16: 0 | BU16: 0 | BV16: 0 | BW16: 0 | BX16: 0 | BY16: 0 | BZ16: 7111.347 | CB16: 7111.347 | CD16: 0
... B36: Private households with employed persons | C36: 0 | D36: 0 | E36: 0 | F36: 0 | G36: 0 | H36: 0 | I36: 0 | J36: 0 | K36: 0 | L36: 0 | M36: 0 | N36: 0 | O36: 0 | P36: 0 | Q36: 0 | R36: 0 | S36: 0 | T36: 0 | U36: 0 | V36: 0 | W36: 0 | X36: 0 | Y36: 0 | Z36: 0 | AA36: 0 | AB36: 0 | AC36: 0 | AD36: 0 | AE36: 0 | AF36: 0 | AG36: 0 | AH36: 0 | AI36: 0 | AJ36: 0 | AK36: 0 | AL36: 0 | AM36: 0 | AN36: 0 | AO36: 0 | AP36: 0 | AQ36: 0 | AR36: 0 | AS36: 0 | AT36: 0 | AU36: 0 | AV36: 0 | AW36: 0 | AX36: 0 | AY36: 0 | AZ36: 0 | BA36: 0 | BB36: 0 | BC36: 0 | BD36: 0 | BE36: 0 | BF36: 0 | BG36: 0 | BH36: 0 | BI36: 0 | BJ36: 0 | BK36: 0 | BL36: 0 | BM36: 0 | BN36: 0 | BO36: 0 | BP36: 1945.3419 | BQ36: 0 | BR36: 0 | BS36: 0 | BU36: 0 | BV36: 0 | BW36: 0 | BX36: 0 | BY36: 0 | BZ36: 1945.3419 | CB36: 1945.3419 | CD36: 0
A37: Commodities | B37: Agriculture, hunting, forestry, and fishing | C37: 143.07824 | D37: 0 | E37: 2948.276 | F37: 0.80286355 | G37: 0 | H37: 47.293888 | I37: 0 | J37: 0 | K37: 0 | L37: 5.2979159 | M37: 0 | N37: 0 | O37: 0 | P37: 0 | Q37: 0 | R37: 0 | S37: 0 | T37: 0 | U37: 0 | V37: 1610.6116 | W37: 0 | X37: 0 | Y37: 546.04977 | Z37: 0 | AA37: 0 | AB37: 0 | AC37: 0 | AD37: 0 | AE37: 0 | AF37: 0 | AG37: 36.561041 | AH37: 0 | AI37: 0 | AJ37: 0 | AK37: 0 | AL37: 0 | AM37: 0 | AN37: 0 | AO37: 0 | AP37: 0 | AQ37: 0 | AR37: 0 | AS37: 0 | AT37: 0 | AU37: 0 | AV37: 0 | AW37: 0 | AX37: 0 | AY37: 0 | AZ37: 0 | BA37: 0 | BB37: 0 | BC37: 0 | BD37: 0 | BE37: 0 | BF37: 0 | BG37: 0 | BH37: 0 | BI37: 0 | BJ37: 0 | BK37: 0 | BL37: 0 | BM37: 0 | BN37: 0 | BO37: 0 | BP37: 0 | BQ37: 0 | BR37: 0 | BS37: 0 | BU37: 0 | BV37: 2724.79 | BW37: 0 | BX37: 13478.352 | BY37: 327.99153 | BZ37: 21869.105 | CB37: 21869.105 | CD37: 20356.806 | CE37: 20356.806 | CG37: 0
B38: Mining and quarrying | C38: 0 | D38: 653.16941 | E38: 101.44139 | F38: 0 | G38: 0 | H38: 6.1203669 | I38: 0 | J38: 22262.802 | K38: 22.487697 | L38: 0 | M38: 297.72952 | N38: 23.711953 | O38: 0.024323442 | P38: 0 | Q38: 0 | R38: 349.98527 | S38: 0 | T38: 284.62507 | U38: 60.706332 | V38: 0 | W38: 0.68713536 | X38: 0 | Y38: 0 | Z38: 407.34275 | AA38: 0 | AB38: 0 | AC38: 0 | AD38: 0 | AE38: 0 | AF38: 0 | AG38: 0 | AH38: 0 | AI38: 0 | AJ38: 0 | AK38: 0 | AL38: 0 | AM38: 0 | AN38: 0 | AO38: 0 | AP38: 0 | AQ38: 0 | AR38: 0 | AS38: 0 | AT38: 0 | AU38: 0 | AV38: 0 | AW38: 0 | AX38: 0 | AY38: 0 | AZ38: 0 | BA38: 0 | BB38: 0 | BC38: 0 | BD38: 0 | BE38: 0 | BF38: 0 | BG38: 0 | BH38: 0 | BI38: 0 | BJ38: 0 | BK38: 0 | BL38: 0 | BM38: 0 | BN38: 0 | BO38: 0 | BP38: 0 | BQ38: 0 | BR38: 0 | BS38: 0 | BU38: 0 | BV38: 514.07806 | BW38: 0 | BX38: 125317.36 | BY38: 521.23281 | BZ38: 150823.5 | CB38: 150823.5 | CD38: 139374.78 | CE38: 139374.78 | CG38: 0
B39: Food, beverages, and tobacco | C39: 443.27859 | D39: 0 | E39: 8805.5268 | F39: 0 | G39: 0 | H39: 0.023586799 | I39: 0.24330827 | J39: 0 | K39: 45.323193 | L39: 0 | M39: 0 | N39: 4.1326844 | O39: 0 | P39: 0.37408768 | Q39: 0.086673368 | R39: 0.23063435 | S39: 0.048891827 | T39: 0.907421 | U39: 44.821312 | V39: 9221.4896 | W39: 0.057621653 | X39: 0 | Y39: 2734.1727 | Z39: 47.926888 | AA39: 0 | AB39: 0 | AC39: 52.97269 | AD39: 61.641521 | AE39: 91.856638 | AF39: 5.6700135 | AG39: 258.32035 | AH39: 386.26082 | AI39: 0 | AJ39: 0 | AK39: 0 | AL39: 0 | AM39: 0 | AN39: 0 | AO39: 0 | AP39: 0 | AQ39: 0 | AR39: 0 | AS39: 0 | AT39: 0 | AU39: 0 | AV39: 0 | AW39: 0 | AX39: 0 | AY39: 0 | AZ39: 0 | BA39: 0 | BB39: 0 | BC39: 0 | BD39: 0 | BE39: 0 | BF39: 0 | BG39: 0 | BH39: 0 | BI39: 0 | BJ39: 0 | BK39: 0 | BL39: 0 | BM39: 0 | BN39: 0 | BO39: 0 | BP39: 0 | BQ39: 0 | BR39: 0 | BS39: 0 | BU39: 0 | BV39: 9135.7623 | BW39: 0 | BX39: 40267.725 | BY39: 187.14831 | BZ39: 71796.001 | CB39: 71796.001 | CD39: 46238.282 | CE39: 46238.282 | CG39: 0
B40: Textiles and textile products | C40: 9.8214309 | D40: 0 | E40: 40.776498 | F40: 847.77563 | G40: 2.7194627 | H40: 24.203471 | I40: 14.517659 | J40: 0.0014346228 | K40: 3.9443526 | L40: 0.27723272 | M40: 3.1923405 | N40: 15.217026 | O40: 4.4747492 | P40: 2.6666001 | Q40: 69.70273 | R40: 74.578343 | S40: 0.58925543 | T40: 122.73765 | U40: 137.0978 | V40: 490.74924 | W40: 15.468951 | X40: 0.017603693 | Y40: 246.6236 | Z40: 176.32222 | AA40: 83.761825 | AB40: 0 | AC40: 1.869174 | AD40: 136.2798 | AE40: 390.75646 | AF40: 14.621531 | AG40: 19.954026 | AH40: 55.460526 | AI40: 0 | AJ40: 0 | AK40: 0 | AL40: 0 | AM40: 0 | AN40: 0 | AO40: 0 | AP40: 0 | AQ40: 0 | AR40: 0 | AS40: 0 | AT40: 0 | AU40: 0 | AV40: 0 | AW40: 0 | AX40: 0 | AY40: 0 | AZ40: 0 | BA40: 0 | BB40: 0 | BC40: 0 | BD40: 0 | BE40: 0 | BF40: 0 | BG40: 0 | BH40: 0 | BI40: 0 | BJ40: 0 | BK40: 0 | BL40: 0 | BM40: 0 | BN40: 0 | BO40: 0 | BP40: 0 | BQ40: 0 | BR40: 0 | BS40: 0 | BU40: 0 | BV40: 2769.5525 | BW40: 0 | BX40: 18250.608 | BY40: 2712.2572 | BZ40: 26738.597 | CB40: 26738.597 | CD40: 23317.56 | CE40: 23317.56 | CG40: 0
B41: Leather, leather products, and footwear | C41: 0 | D41: 0 | E41: 0 | F41: 0.047137753 | G41: 4.6397824 | H41: 0 | I41: 43.06195 | J41: 0 | K41: 0 | L41: 0 | M41: 0 | N41: 0 | O41: 0 | P41: 0.73110918 | Q41: 0 | R41: 0.45001763 | S41: 0 | T41: 90.826996 | U41: 0 | V41: 31.612477 | W41: 0 | X41: 0 | Y41: 84.17935 | Z41: 0 | AA41: 31.790731 | AB41: 0 | AC41: 0 | AD41: 0.31434999 | AE41: 189.05613 | AF41: 0 | AG41: 0 | AH41: 1.5814538 | AI41: 0 | AJ41: 0 | AK41: 0 | AL41: 0 | AM41: 0 | AN41: 0 | AO41: 0 | AP41: 0 | AQ41: 0 | AR41: 0 | AS41: 0 | AT41: 0 | AU41: 0 | AV41: 0 | AW41: 0 | AX41: 0 | AY41: 0 | AZ41: 0 | BA41: 0 | BB41: 0 | BC41: 0 | BD41: 0 | BE41: 0 | BF41: 0 | BG41: 0 | BH41: 0 | BI41: 0 | BJ41: 0 | BK41: 0 | BL41: 0 | BM41: 0 | BN41: 0 | BO41: 0 | BP41: 0 | BQ41: 0 | BR41: 0 | BS41: 0 | BU41: 0 | BV41: 1956.4286 | BW41: 0 | BX41: 11177.055 | BY41: 1235.1536 | BZ41: 14846.928 | CB41: 14846.928 | CD41: 14817.33 | CE41: 14817.33 | CG41: 0
B42: Wood and products of wood and cork | C42: 0 | D42: 0 | E42: 0 | F42: 0 | G42: 0 | H42: 442.57759 | I42: 17.960527 | J42: 0 | K42: 0 | L42: 0 | M42: 2.5637885 | N42: 120.23754 | O42: 0 | P42: 13.401103 | Q42: 0.50438249 | R42: 845.54258 | S42: 0 | T42: 1600.1933 | U42: 11.336138 | V42: 0 | W42: 0 | X42: 0 | Y42: 0 | Z42: 1396.7649 | AA42: 0 | AB42: 0 | AC42: 0 | AD42: 48.062394 | AE42: 0 | AF42: 0 | AG42: 0 | AH42: 2.014916 | AI42: 0 | AJ42: 0 | AK42: 0 | AL42: 0 | AM42: 0 | AN42: 0 | AO42: 0 | AP42: 0 | AQ42: 0 | AR42: 0 | AS42: 0 | AT42: 0 | AU42: 0 | AV42: 0 | AW42: 0 | AX42: 0 | AY42: 0 | AZ42: 0 | BA42: 0 | BB42: 0 | BC42: 0 | BD42: 0 | BE42: 0 | BF42: 0 | BG42: 0 | BH42: 0 | BI42: 0 | BJ42: 0 | BK42: 0 | BL42: 0 | BM42: 0 | BN42: 0 | BO42: 0 | BP42: 0 | BQ42: 0 | BR42: 0 | BS42: 0 | BU42: 0 | BV42: 0 | BW42: 0 | BX42: 2027.6278 | BY42: 37.222327 | BZ42: 6566.0093 | CB42: 6566.0093 | CD42: 3892.1263 | CE42: 3892.1263 | CG42: 0
B43: Pulp, paper, paper products, printing, and publishing | C43: 0 | D43: 0 | E43: 232.2301 | F43: 5.5587769 | G43: 0.30999411 | H43: 28.845784 | I43: 2353.3699 | J43: 0.16826761 | K43: 33.623037 | L43: 18.961868 | M43: 23.997227 | N43: 192.10009 | O43: 6.5156528 | P43: 8.2368065 | Q43: 0.40523784 | R43: 14.535779 | S43: 6.1360102 | T43: 231.95064 | U43: 1091.8054 | V43: 365.7776 | W43: 66.801478 | X43: 5.9089028 | Y43: 119.59023 | Z43: 49.638261 | AA43: 197.4785 | AB43: 184.88434 | AC43: 30.587658 | AD43: 2995.4108 | AE43: 666.79727 | AF43: 782.20715 | AG43: 91.815264 | AH43: 40.3963 | AI43: 0 | AJ43: 0 | AK43: 0 | AL43: 0 | AM43: 0 | AN43: 0 | AO43: 0 | AP43: 0 | AQ43: 0 | AR43: 0 | AS43: 0 | AT43: 0 | AU43: 0 | AV43: 0 | AW43: 0 | AX43: 0 | AY43: 0 | AZ43: 0 | BA43: 0 | BB43: 0 | BC43: 0 | BD43: 0 | BE43: 0 | BF43: 0 | BG43: 0 | BH43: 0 | BI43: 0 | BJ43: 0 | BK43: 0 | BL43: 0 | BM43: 0 | BN43: 0 | BO43: 0 | BP43: 0 | BQ43: 0 | BR43: 0 | BS43: 0 | BU43: 0 | BV43: 256.30421 | BW43: 0 | BX43: 3806.5156 | BY43: 621.12181 | BZ43: 14529.986 | CB43: 14529.986 | CD43: 7432.5429 | CE43: 7432.5429 | CG43: 0
B44: Coke, refined petroleum, and nuclear fuel | C44: 36.592313 | D44: 494.32315 | E44: 413.30215 | F44: 7.4312133 | G44: 0.12144779 | H44: 9.4906176 | I44: 15.137528 | J44: 1608.8147 | K44: 138.00557 | L44: 10.506636 | M44: 445.5735 | N44: 288.39334 | O44: 58.49667 | P44: 23.440948 | Q44: 9.1102494 | R44: 213.2158 | S44: 10967.363 | T44: 2161.7113 | U44: 1072.5683 | V44: 178.57844 | W44: 2721.1057 | X44: 52.545397 | Y44: 27097.859 | Z44: 1120.7657 | AA44: 387.9922 | AB44: 11.690594 | AC44: 44.523953 | AD44: 1167.3757 | AE44: 828.83294 | AF44: 60.792723 | AG44: 60.668637 | AH44: 274.72731 | AI44: 0 | AJ44: 0 | AK44: 0 | AL44: 0 | AM44: 0 | AN44: 0 | AO44: 0 | AP44: 0 | AQ44: 0 | AR44: 0 | AS44: 0 | AT44: 0 | AU44: 0 | AV44: 0 | AW44: 0 | AX44: 0 | AY44: 0 | AZ44: 0 | BA44: 0 | BB44: 0 | BC44: 0 | BD44: 0 | BE44: 0 | BF44: 0 | BG44: 0 | BH44: 0 | BI44: 0 | BJ44: 0 | BK44: 0 | BL44: 0 | BM44: 0 | BN44: 0 | BO44: 0 | BP44: 0 | BQ44: 0 | BR44: 0 | BS44: 0 | BU44: 0 | BV44: 1806.0896 | BW44: 0 | BX44: 23605.032 | BY44: 126.2385 | BZ44: 77518.417 | CB44: 77518.417 | CD44: 49129.005 | CE44: 49129.005 | CG44: 0
B45: Chemicals and chemical products | C45: 6.3345435 | D45: 0 | E45: 96.322723 | F45: 1.930536 | G45: 0.78651652 | H45: 387.75162 | I45: 347.68442 | J45: 679.9407 | K45: 5025.1749 | L45: 2086.959 | M45: 280.77506 | N45: 1201.9457 | O45: 4.6280511 | P45: 340.92086 | Q45: 81.560035 | R45: 50.836777 | S45: 14.910196 | T45: 1203.5116 | U45: 116.20495 | V45: 239.50491 | W45: 4.296757 | X45: 0.055558081 | Y45: 415.14746 | Z45: 5.8966489 | AA45: 3.6393652 | AB45: 0 | AC45: 3.678205 | AD45: 737.07099 | AE45: 24.74785 | AF45: 3.5360601 | AG45: 916.62251 | AH45: 226.62071 | AI45: 0 | AJ45: 0 | AK45: 0 | AL45: 0 | AM45: 0 | AN45: 0 | AO45: 0 | AP45: 0 | AQ45: 0 | AR45: 0 | AS45: 0 | AT45: 0 | AU45: 0 | AV45: 0 | AW45: 0 | AX45: 0 | AY45: 0 | AZ45: 0 | BA45: 0 | BB45: 0 | BC45: 0 | BD45: 0 | BE45: 0 | BF45: 0 | BG45: 0 | BH45: 0 | BI45: 0 | BJ45: 0 | BK45: 0 | BL45: 0 | BM45: 0 | BN45: 0 | BO45: 0 | BP45: 0 | BQ45: 0 | BR45: 0 | BS45: 0 | BU45: 0 | BV45: 2538.7912 | BW45: 0 | BX45: 44799.938 | BY45: 1384.6515 | BZ45: 63232.375 | CB45: 63232.375 | CD45: 50085.109 | CE45: 50085.109 | CG45: 0
B46: Rubber and plastics | C46: 0 | D46: 0 | E46: 1298.929 | F46: 31.663667 | G46: 0.60545612 | H46: 73.899941 | I46: 160.16559 | J46: 244.93128 | K46: 571.52178 | L46: 708.09949 | M46: 143.68553 | N46: 275.00095 | O46: 16.083088 | P46: 196.63703 | Q46: 35.308233 | R46: 54.534899 | S46: 1.4967563 | T46: 234.32824 | U46: 585.74362 | V46: 191.03214 | W46: 176.39961 | X46: 0.087147766 | Y46: 0 | Z46: 109.88555 | AA46: 114.62628 | AB46: 0 | AC46: 0 | AD46: 346.20003 | AE46: 0 | AF46: 0 | AG46: 3.6852383 | AH46: 18.458981 | AI46: 0 | AJ46: 0 | AK46: 0 | AL46: 0 | AM46: 0 | AN46: 0 | AO46: 0 | AP46: 0 | AQ46: 0 | AR46: 0 | AS46: 0 | AT46: 0 | AU46: 0 | AV46: 0 | AW46: 0 | AX46: 0 | AY46: 0 | AZ46: 0 | BA46: 0 | BB46: 0 | BC46: 0 | BD46: 0 | BE46: 0 | BF46: 0 | BG46: 0 | BH46: 0 | BI46: 0 | BJ46: 0 | BK46: 0 | BL46: 0 | BM46: 0 | BN46: 0 | BO46: 0 | BP46: 0 | BQ46: 0 | BR46: 0 | BS46: 0 | BU46: 0 | BV46: 7.4606115 | BW46: 0 | BX46: 11455.931 | BY46: 1290.6428 | BZ46: 18347.044 | CB46: 18347.044 | CD46: 11940.515 | CE46: 11940.515 | CG46: 0
B47: Other nonmetallic minerals | C47: 0 | D47: 0 | E47: 3.6321957 | F47: 9.3401169 | G47: 0.46547115 | H47: 31.308112 | I47: 0 | J47: 0 | K47: 225.97732 | L47: 5.0598815 | M47: 1364.7265 | N47: 253.96793 | O47: 0 | P47: 0 | Q47: 4.0385608 | R47: 349.02423 | S47: 0 | T47: 6470.3455 | U47: 0 | V47: 16.971143 | W47: 0 | X47: 0 | Y47: 0 | Z47: 0 | AA47: 0 | AB47: 0 | AC47: 0 | AD47: 0 | AE47: 0 | AF47: 0.12730818 | AG47: 47.171651 | AH47: 0 | AI47: 0 | AJ47: 0 | AK47: 0 | AL47: 0 | AM47: 0 | AN47: 0 | AO47: 0 | AP47: 0 | AQ47: 0 | AR47: 0 | AS47: 0 | AT47: 0 | AU47: 0 | AV47: 0 | AW47: 0 | AX47: 0 | AY47: 0 | AZ47: 0 | BA47: 0 | BB47: 0 | BC47: 0 | BD47: 0 | BE47: 0 | BF47: 0 | BG47: 0 | BH47: 0 | BI47: 0 | BJ47: 0 | BK47: 0 | BL47: 0 | BM47: 0 | BN47: 0 | BO47: 0 | BP47: 0 | BQ47: 0 | BR47: 0 | BS47: 0 | BU47: 0 | BV47: 89.342972 | BW47: 0 | BX47: 4728.6533 | BY47: 734.57118 | BZ47: 14334.723 | CB47: 14334.723 | CD47: 6187.5803 | CE47: 6187.5803 | CG47: 0
B48: Basic metals and fabricated metal | C48: 0 | D48: 0 | E48: 15.077205 | F48: 82.436696 | G48: 0 | H48: 108.81532 | I48: 31.051593 | J48: 0 | K48: 1.7759274 | L48: 382.46884 | M48: 132.11199 | N48: 14746.858 | O48: 1842.676 | P48: 2666.1366 | Q48: 232.72698 | R48: 2332.263 | S48: 0.00036431721 | T48: 6395.639 | U48: 142.76295 | V48: 499.74632 | W48: 0 | X48: 0 | Y48: 0 | Z48: 0.090288998 | AA48: 0 | AB48: 0 | AC48: 0 | AD48: 35.405645 | AE48: 161.2195 | AF48: 0 | AG48: 0 | AH48: 0.60532124 | AI48: 0 | AJ48: 0 | AK48: 0 | AL48: 0 | AM48: 0 | AN48: 0 | AO48: 0 | AP48: 0 | AQ48: 0 | AR48: 0 | AS48: 0 | AT48: 0 | AU48: 0 | AV48: 0 | AW48: 0 | AX48: 0 | AY48: 0 | AZ48: 0 | BA48: 0 | BB48: 0 | BC48: 0 | BD48: 0 | BE48: 0 | BF48: 0 | BG48: 0 | BH48: 0 | BI48: 0 | BJ48: 0 | BK48: 0 | BL48: 0 | BM48: 0 | BN48: 0 | BO48: 0 | BP48: 0 | BQ48: 0 | BR48: 0 | BS48: 0 | BU48: 0 | BV48: 94.897311 | BW48: 0 | BX48: 129405.85 | BY48: 5189.9999 | BZ48: 164500.62 | CB48: 164500.62 | CD48: 125797.11 | CE48: 125797.11 | CG48: 0
B49: Machinery, nec | C49: 0 | D49: 0 | E49: 124.53197 | F49: 1.9763584 | G49: 0.02071129 | H49: 11.931423 | I49: 31.869564 | J49: 0 | K49: 35.325611 | L49: 14.666918 | M49: 285.36399 | N49: 665.34982 | O49: 937.64182 | P49: 138.33713 | Q49: 42.586335 | R49: 239.91282 | S49: 8.8472113 | T49: 6843.112 | U49: 201.37956 | V49: 0 | W49: 0 | X49: 0 | Y49: 0 | Z49: 842.32799 | AA49: 0 | AB49: 0 | AC49: 276.01649 | AD49: 122.09173 | AE49: 60.30957 | AF49: 8.4299487 | AG49: 40.09257 | AH49: 50.746488 | AI49: 0 | AJ49: 0 | AK49: 0 | AL49: 0 | AM49: 0 | AN49: 0 | AO49: 0 | AP49: 0 | AQ49: 0 | AR49: 0 | AS49: 0 | AT49: 0 | AU49: 0 | AV49: 0 | AW49: 0 | AX49: 0 | AY49: 0 | AZ49: 0 | BA49: 0 | BB49: 0 | BC49: 0 | BD49: 0 | BE49: 0 | BF49: 0 | BG49: 0 | BH49: 0 | BI49: 0 | BJ49: 0 | BK49: 0 | BL49: 0 | BM49: 0 | BN49: 0 | BO49: 0 | BP49: 0 | BQ49: 0 | BR49: 0 | BS49: 0 | BU49: 0 | BV49: 23.728728 | BW49: 0 | BX49: 40306.888 | BY49: 16971.404 | BZ49: 68284.888 | CB49: 68284.888 | CD49: 61173.541 | CE49: 61173.541 | CG49: 0
... B69: Private households with employed persons | C69: 0 | D69: 0 | E69: 0 | F69: 0 | G69: 0 | H69: 0 | I69: 0 | J69: 0 | K69: 0 | L69: 0 | M69: 0 | N69: 0 | O69: 0 | P69: 0 | Q69: 0 | R69: 0 | S69: 0 | T69: 0 | U69: 0 | V69: 0 | W69: 0 | X69: 0 | Y69: 0 | Z69: 0 | AA69: 0 | AB69: 0 | AC69: 0 | AD69: 0 | AE69: 0 | AF69: 0 | AG69: 0 | AH69: 0 | AI69: 0 | AJ69: 0 | AK69: 0 | AL69: 0 | AM69: 0 | AN69: 0 | AO69: 0 | AP69: 0 | AQ69: 0 | AR69: 0 | AS69: 0 | AT69: 0 | AU69: 0 | AV69: 0 | AW69: 0 | AX69: 0 | AY69: 0 | AZ69: 0 | BA69: 0 | BB69: 0 | BC69: 0 | BD69: 0 | BE69: 0 | BF69: 0 | BG69: 0 | BH69: 0 | BI69: 0 | BJ69: 0 | BK69: 0 | BL69: 0 | BM69: 0 | BN69: 0 | BO69: 0 | BP69: 0 | BQ69: 0 | BR69: 0 | BS69: 0 | BU69: 0 | BV69: 1945.3419 | BW69: 0 | BX69: 0 | BY69: 0 | BZ69: 1945.3419 | CB69: 1945.3419 | CD69: 0 | CE69: 0 | CG69: 0
A70: Factors | B70: Labour | C70: 233 | D70: 1238 | E70: 2676.288 | F70: 837.922 | G70: 7.471 | H70: 631.169 | I70: 1294.858 | J70: 258.901 | K70: 1556.737 | L70: 703.23 | M70: 1703.936 | N70: 4050.425 | O70: 1322.063 | P70: 760.108 | Q70: 301.423 | R70: 2885.55 | S70: 4344 | T70: 20526.655 | U70: 53229 | V70: 13377.538 | W70: 4282.646 | X70: 146.603 | Y70: 14274.282 | Z70: 9025.789 | AA70: 4989.6802 | AB70: 12121.988 | AC70: 6997 | AD70: 37477.836 | AE70: 23934 | AF70: 6526 | AG70: 5247.7927 | AH70: 2665 | AI70: 1945 | AJ70: 0 | AK70: 0 | AL70: 0 | AM70: 0 | AN70: 0 | AO70: 0 | AP70: 0 | AQ70: 0 | AR70: 0 | AS70: 0 | AT70: 0 | AU70: 0 | AV70: 0 | AW70: 0 | AX70: 0 | AY70: 0 | AZ70: 0 | BA70: 0 | BB70: 0 | BC70: 0 | BD70: 0 | BE70: 0 | BF70: 0 | BG70: 0 | BH70: 0 | BI70: 0 | BJ70: 0 | BK70: 0 | BL70: 0 | BM70: 0 | BN70: 0 | BO70: 0 | BP70: 0 | BQ70: 0 | BR70: 0 | BS70: 0 | BU70: 0 | BV70: 0 | BW70: 0 | BX70: 0 | BY70: 0 | BZ70: 241571.89
B71: Capital | C71: 414.32237 | D71: 7222.3983 | E71: 3400.165 | F71: 812.752 | G71: 3.813 | H71: 307.873 | I71: 879.574 | J71: 1928.287 | K71: 2437.259 | L71: 1202.565 | M71: 847.075 | N71: 7323.436 | O71: 982.25 | P71: 685.347 | Q71: 614.316 | R71: 2003.807 | S71: 14343.292 | T71: 6345.6596 | U71: 54326.709 | V71: 14840.133 | W71: 4127.523 | X71: 363.011 | Y71: 16945.328 | Z71: 9873.722 | AA71: 9673.979 | AB71: 42425.425 | AC71: 26572.159 | AD71: 4521.0209 | AE71: 7398.0203 | AF71: 1751.912 | AG71: 1148.2119 | AH71: 295.61848 | AI71: 0.34192339 | AJ71: 0 | AK71: 0 | AL71: 0 | AM71: 0 | AN71: 0 | AO71: 0 | AP71: 0 | AQ71: 0 | AR71: 0 | AS71: 0 | AT71: 0 | AU71: 0 | AV71: 0 | AW71: 0 | AX71: 0 | AY71: 0 | AZ71: 0 | BA71: 0 | BB71: 0 | BC71: 0 | BD71: 0 | BE71: 0 | BF71: 0 | BG71: 0 | BH71: 0 | BI71: 0 | BJ71: 0 | BK71: 0 | BL71: 0 | BM71: 0 | BN71: 0 | BO71: 0 | BP71: 0 | BQ71: 0 | BR71: 0 | BS71: 0 | BU71: 0 | BV71: 0 | BW71: 0 | BX71: 0 | BY71: 0 | BZ71: 246017.31
A72: Tax | B72: Indirect taxes | C72: 0 | D72: 0 | E72: 0 | F72: 0 | G72: 0 | H72: 0 | I72: 0 | J72: 0 | K72: 0 | L72: 0 | M72: 0 | N72: 0 | O72: 0 | P72: 0 | Q72: 0 | R72: 0 | S72: 0 | T72: 0 | U72: 0 | V72: 0 | W72: 0 | X72: 0 | Y72: 0 | Z72: 0 | AA72: 0 | AB72: 0 | AC72: 0 | AD72: 0 | AE72: 0 | AF72: 0 | AG72: 0 | AH72: 0 | AI72: 0 | AJ72: 144.4832 | AK72: 273.09907 | AL72: 470.15579 | AM72: 316.85345 | AN72: 123.97176 | AO72: 25.615143 | AP72: 76.334952 | AQ72: 110.92151 | AR72: 341.30384 | AS72: 117.91219 | AT72: 78.717072 | AU72: 767.68665 | AV72: 552.83399 | AW72: 901.72973 | AX72: 798.31085 | AY72: 364.30454 | AZ72: 251.03151 | BA72: 1798.4194 | BB72: 2096.4555 | BC72: 1115.9617 | BD72: 304.84349 | BE72: 11.783962 | BF72: 1717.8932 | BG72: 230.70109 | BH72: 873.7389 | BI72: 646.64652 | BJ72: 1383.7912 | BK72: 565.9172 | BL72: 742.85725 | BM72: 276.62232 | BN72: 348.84261 | BO72: 200.26044 | BP72: 0 | BQ72: 0 | BR72: 0 | BS72: 0 | BU72: 0 | BV72: 0 | BW72: 0 | BX72: 0 | BY72: 0 | BZ72: 18030
B73: Subsidies | BZ73: 0
B74: Direct taxes | C74: 0 | D74: 0 | E74: 0 | F74: 0 | G74: 0 | H74: 0 | I74: 0 | J74: 0 | K74: 0 | L74: 0 | M74: 0 | N74: 0 | O74: 0 | P74: 0 | Q74: 0 | R74: 0 | S74: 0 | T74: 0 | U74: 0 | V74: 0 | W74: 0 | X74: 0 | Y74: 0 | Z74: 0 | AA74: 0 | AB74: 0 | AC74: 0 | AD74: 0 | AE74: 0 | AF74: 0 | AG74: 0 | AH74: 0 | AI74: 0 | AJ74: 0 | AK74: 0 | AL74: 0 | AM74: 0 | AN74: 0 | AO74: 0 | AP74: 0 | AQ74: 0 | AR74: 0 | AS74: 0 | AT74: 0 | AU74: 0 | AV74: 0 | AW74: 0 | AX74: 0 | AY74: 0 | AZ74: 0 | BA74: 0 | BB74: 0 | BC74: 0 | BD74: 0 | BE74: 0 | BF74: 0 | BG74: 0 | BH74: 0 | BI74: 0 | BJ74: 0 | BK74: 0 | BL74: 0 | BM74: 0 | BN74: 0 | BO74: 0 | BP74: 0 | BQ74: 0 | BR74: 39520 | BS74: 0 | BU74: 0 | BV74: 0 | BW74: 0 | BX74: 0 | BY74: 0 | BZ74: 39520
A75: Institutions | B75: Households | C75: 0 | D75: 0 | E75: 0 | F75: 0 | G75: 0 | H75: 0 | I75: 0 | J75: 0 | K75: 0 | L75: 0 | M75: 0 | N75: 0 | O75: 0 | P75: 0 | Q75: 0 | R75: 0 | S75: 0 | T75: 0 | U75: 0 | V75: 0 | W75: 0 | X75: 0 | Y75: 0 | Z75: 0 | AA75: 0 | AB75: 0 | AC75: 0 | AD75: 0 | AE75: 0 | AF75: 0 | AG75: 0 | AH75: 0 | AI75: 0 | AJ75: 0 | AK75: 0 | AL75: 0 | AM75: 0 | AN75: 0 | AO75: 0 | AP75: 0 | AQ75: 0 | AR75: 0 | AS75: 0 | AT75: 0 | AU75: 0 | AV75: 0 | AW75: 0 | AX75: 0 | AY75: 0 | AZ75: 0 | BA75: 0 | BB75: 0 | BC75: 0 | BD75: 0 | BE75: 0 | BF75: 0 | BG75: 0 | BH75: 0 | BI75: 0 | BJ75: 0 | BK75: 0 | BL75: 0 | BM75: 0 | BN75: 0 | BO75: 0 | BP75: 0 | BQ75: 241571.89 | BR75: 206497.31 | BS75: 0 | BU75: 0 | BV75: 0 | BW75: 0 | BX75: 0 | BY75: 0 | BZ75: 448069.2
B76: Government | C76: 0 | D76: 0 | E76: 0 | F76: 0 | G76: 0 | H76: 0 | I76: 0 | J76: 0 | K76: 0 | L76: 0 | M76: 0 | N76: 0 | O76: 0 | P76: 0 | Q76: 0 | R76: 0 | S76: 0 | T76: 0 | U76: 0 | V76: 0 | W76: 0 | X76: 0 | Y76: 0 | Z76: 0 | AA76: 0 | AB76: 0 | AC76: 0 | AD76: 0 | AE76: 0 | AF76: 0 | AG76: 0 | AH76: 0 | AI76: 0 | AJ76: 0 | AK76: 0 | AL76: 0 | AM76: 0 | AN76: 0 | AO76: 0 | AP76: 0 | AQ76: 0 | AR76: 0 | AS76: 0 | AT76: 0 | AU76: 0 | AV76: 0 | AW76: 0 | AX76: 0 | AY76: 0 | AZ76: 0 | BA76: 0 | BB76: 0 | BC76: 0 | BD76: 0 | BE76: 0 | BF76: 0 | BG76: 0 | BH76: 0 | BI76: 0 | BJ76: 0 | BK76: 0 | BL76: 0 | BM76: 0 | BN76: 0 | BO76: 0 | BP76: 0 | BQ76: 0 | BR76: 0 | BS76: 18030 | BU76: 39520 | BV76: 0 | BW76: 0 | BX76: 0 | BY76: 0 | BZ76: 57550
B77: Rest of the World | C77: 0 | D77: 0 | E77: 0 | F77: 0 | G77: 0 | H77: 0 | I77: 0 | J77: 0 | K77: 0 | L77: 0 | M77: 0 | N77: 0 | O77: 0 | P77: 0 | Q77: 0 | R77: 0 | S77: 0 | T77: 0 | U77: 0 | V77: 0 | W77: 0 | X77: 0 | Y77: 0 | Z77: 0 | AA77: 0 | AB77: 0 | AC77: 0 | AD77: 0 | AE77: 0 | AF77: 0 | AG77: 0 | AH77: 0 | AI77: 0 | AJ77: 20212.322 | AK77: 139101.68 | AL77: 45768.127 | AM77: 23000.706 | AN77: 14693.358 | AO77: 3866.5112 | AP77: 7356.2079 | AQ77: 49018.083 | AR77: 49743.806 | AS77: 11822.603 | AT77: 6108.8632 | AU77: 125029.43 | AV77: 60620.707 | AW77: 137577.64 | AX77: 48554.679 | AY77: 46547.767 | AZ77: 0 | BA77: 0 | BB77: 0 | BC77: 219.06404 | BD77: 0 | BE77: 0 | BF77: 0 | BG77: 0 | BH77: 0 | BI77: 0 | BJ77: 0 | BK77: 0 | BL77: 0 | BM77: 4022.6955 | BN77: 38.399524 | BO77: 449.61518 | BP77: 0 | BQ77: 0 | BR77: 0 | BS77: 0 | BU77: 0 | BV77: 260362 | BW77: 0 | BX77: 0 | BY77: 0 | BZ77: 1054114.3
A78: Capital | B78: Savings - Investment | C78: 0 | D78: 0 | E78: 0 | F78: 0 | G78: 0 | H78: 0 | I78: 0 | J78: 0 | K78: 0 | L78: 0 | M78: 0 | N78: 0 | O78: 0 | P78: 0 | Q78: 0 | R78: 0 | S78: 0 | T78: 0 | U78: 0 | V78: 0 | W78: 0 | X78: 0 | Y78: 0 | Z78: 0 | AA78: 0 | AB78: 0 | AC78: 0 | AD78: 0 | AE78: 0 | AF78: 0 | AG78: 0 | AH78: 0 | AI78: 0 | AJ78: 0 | AK78: 0 | AL78: 0 | AM78: 0 | AN78: 0 | AO78: 0 | AP78: 0 | AQ78: 0 | AR78: 0 | AS78: 0 | AT78: 0 | AU78: 0 | AV78: 0 | AW78: 0 | AX78: 0 | AY78: 0 | AZ78: 0 | BA78: 0 | BB78: 0 | BC78: 0 | BD78: 0 | BE78: 0 | BF78: 0 | BG78: 0 | BH78: 0 | BI78: 0 | BJ78: 0 | BK78: 0 | BL78: 0 | BM78: 0 | BN78: 0 | BO78: 0 | BP78: 0 | BQ78: 0 | BR78: 0 | BS78: 0 | BU78: 0 | BV78: 77164.94 | BW78: 2800 | BX78: 36587.752 | BY78: 0 | BZ78: 116552.69
B79: TOTAL | C79: 1512.2992 | D79: 11448.729 | E79: 25557.719 | F79: 3421.037 | G79: 29.598 | H79: 2673.883 | I79: 7097.443 | J79: 28389.412 | K79: 13147.266 | L79: 6406.529 | M79: 8147.143 | N79: 38703.505 | O79: 7111.347 | P79: 6245.682 | Q79: 2014.772 | R79: 13743.5 | S79: 32516.284 | T79: 89406.357 | U79: 190466.7 | V79: 61824.291 | W79: 15857.389 | X79: 2289.528 | Y79: 102307.01 | Z79: 51951.453 | AA79: 33978.015 | AB79: 68358.296 | AC79: 51738.012 | AD79: 92686.292 | AE79: 48821.367 | AF79: 12497.737 | AG79: 11654.9 | AH79: 7820.8397 | AI79: 1945.3419 | AJ79: 21869.105 | AK79: 150823.5 | AL79: 71796.001 | AM79: 26738.597 | AN79: 14846.928 | AO79: 6566.0093 | AP79: 14529.986 | AQ79: 77518.417 | AR79: 63232.375 | AS79: 18347.044 | AT79: 14334.723 | AU79: 164500.62 | AV79: 68284.888 | AW79: 144725.05 | AX79: 51367.761 | AY79: 60655.572 | AZ79: 32767.316 | BA79: 91204.776 | BB79: 192563.16 | BC79: 63159.317 | BD79: 16162.232 | BE79: 2301.312 | BF79: 104024.9 | BG79: 52182.154 | BH79: 34851.754 | BI79: 69004.943 | BJ79: 53121.803 | BK79: 93252.209 | BL79: 49564.224 | BM79: 16797.055 | BN79: 12042.143 | BO79: 8470.7153 | BP79: 1945.3419 | BQ79: 241571.89 | BR79: 246017.31 | BS79: 18030 | BT79: 0 | BU79: 39520 | BV79: 448069.2 | BW79: 57550 | BX79: 1054114.3 | BY79: 116552.69
AJ81: 20356.806 | AK81: 139374.78 | AL81: 46238.282 | AM81: 23317.56 | AN81: 14817.33 | AO81: 3892.1263 | AP81: 7432.5429 | AQ81: 49129.005 | AR81: 50085.109 | AS81: 11940.515 | AT81: 6187.5803 | AU81: 125797.11 | AV81: 61173.541 | AW81: 138479.37 | AX81: 49352.989 | AY81: 46912.072 | AZ81: 251.03151 | BA81: 1798.4194 | BB81: 2096.4555 | BC81: 1335.0258 | BD81: 304.84349 | BE81: 11.783962 | BF81: 1717.8932 | BG81: 230.70109 | BH81: 873.7389 | BI81: 646.64652 | BJ81: 1383.7912 | BK81: 565.9172 | BL81: 742.85725 | BM81: 4299.3178 | BN81: 387.24213 | BO81: 649.87562 | BP81: 0 | BV81: Total factor income = domestic consumption + import consumption + savings
B82: From official sources
B83: Estimated from 2015 IO using statistically balancing methods
C85: 2022 | E85: 2015 (IO Table)
B86: GDP | C86: 505619.2 | D86: 1 | E86: 402550.35 | F86: 1
B88: CP | C88: 110542.26 | D88: 0.21862749 | E88: 94349.509 | F88: 0.2343794
B89: CG | C89: 54750 | D89: 0.10828307 | E89: 30515.442 | F89: 0.075805282 | H89: =C89/D89*9% -> 45505.728 | I89: =C89-H89 -> 9244.2722
B90: I 1 | C90: 116552.69 | D90: 0.23051477 | E90: 92130.443 | F90: 0.22886688
B91: EX 2 | C91: 1017526.5 | D91: 2.0124365 | E91: 796729.29 | F91: 1.9792041
B92: IM 2 | C92: 793752.26 | D92: 1.5698618 | E92: 611174.34 | F92: 1.5182556
B94: 1: Assumes constant investment propensity & 32% foreign / 68% domestic financing
B95: 2: Assumes constant sector propensity to export and import

Sheet Household characteristics
B2: Households and Residential Combines by Selected Characteristics - Emirate of Dubai
B4: Source:
B6: https://www.dsc.gov.ae/Report/DSC_SYB_2022_01_06.pdf
B7: https://www.dsc.gov.ae/Report/DSC_SYB_2024_01_06.pdf
E10: 2020 | F10: 2021 | G10: 2022 | H10: 2023 | I10: 2024
B11: Households
B12: # households | E12: 598870 | F12: 624195 | G12: 669750 | H12: 711590 | I12: 771200
B13: # individuals | E13: 2595090 | F13: 2690971 | G13: 2755900 | H13: 2855000 | I13: 3022000
B14: Average size | E14: 4.3 | F14: 4.3 | G14: 4.1 | H14: 4 | I14: 3.9
B15: Residential Combines
B16: # combines | E16: 2346 | F16: 2247 | G16: 2249 | H16: 2253 | I16: 2260
B17: # individuals | E17: 816110 | F17: 787329 | G17: 794000 | H17: 800000 | I17: 841600
B18: Average size | E18: 347.9 | F18: 350.4 | G18: 353 | H18: 355.1 | I18: 372.4
B21: Calculated hh size | E21: =E13/E12 -> 4.3333111 | F21: =F13/F12 -> 4.3111063 | G21: =G13/G12 -> 4.114819 | H21: =H13/H12 -> 4.0121418 | I21: =I13/I12 -> 3.9185685
B22: Calculated combine size | E22: =E17/E16 -> 347.87298 | F22: =F17/F16 -> 350.39119 | G22: =G17/G16 -> 353.0458 | H22: =H17/H16 -> 355.08211 | I22: =I17/I16 -> 372.38938

Sheet Labour force absolute size
E1: 2019 | F1: 2020 | G1: 2021 | H1: 2022 | I1: 2023 | J1: 2024 | K1: 2025
B2: Population by nationality
C4: Emirati | H4: 284650
C5: Non-emirati | H5: 3265250
B7: Labour force status by nationality, %
C9: Emirati - in labour force, % | E9: 34.29796
C10: Non-emirati - in labour force, % | E10: 74.082983
C12: Emirati - employment rate, % | E12: 95.8
C13: Non-emirati - employment rate, % | E13: 99.7
B15: Labour stock by nationality
C17: Emirati | H17: =H4*E9%*E12% -> 93528.719 | M17: =H17/SUM($H$17:$H$18) -> 0.037332845
C18: Non-emirati | H18: =H5*E10%*E13% -> 2411737.6 | M18: =H18/SUM($H$17:$H$18) -> 0.96266716
B21: Commuting labour | H21: =H27-H17-H18 -> 1090205.7 | J21: =H21/H27 -> 0.30321629
H23: =H21+H18 -> 3501943.3
H25: =H23+H4 -> 3786593.3
B27: Total Employment | H27: 3595472

Sheet Emirati workforce distribution
B2: Data
B5: 2023 | C5: 2024 | D5: Economic Activities
B6: 0.17354778 | C6: 0.17312315 | D6: N-Administrative and support service activities | E6: =LEFT(D6,1) -> N
B7: 0.13465834 | C7: 0.15341629 | D7: F-Construction | E7: =LEFT(D7,1) -> F
B8: 0.17987861 | C8: 0.14664513 | D8: K-Financial and insurance activities | E8: =LEFT(D8,1) -> K
B9: 0.13340525 | C9: 0.14121608 | D9: G-Wholesale and retail trade; repair of motor vehicles and motorcycles | E9: =LEFT(D9,1) -> G
B10: 0.060943851 | C10: 0.071874313 | D10: C-Manufacturing | E10: =LEFT(D10,1) -> C
B11: 0.068200887 | C11: 0.071692333 | D11: M-Professional, scientific and technical activities | E11: =LEFT(D11,1) -> M
B12: 0.053752193 | C12: 0.057406944 | D12: P-Education | E12: =LEFT(D12,1) -> P
B13: 0.050951805 | C13: 0.055731216 | D13: Q-Human health and social work activities | E13: =LEFT(D13,1) -> Q
B14: 0.05661796 | C14: 0.054085818 | D14: H-Transportation and storage | E14: =LEFT(D14,1) -> H
B15: 0.072385124 | C15: 0.050059522 | D15: OTHER | E15: -
B16: 0.02440805 | C16: 0.024900859 | D16: J-Information and communication | E16: =LEFT(D16,1) -> J
B17: 0.020746843 | C17: 0.02364975 | D17: I-Accommodation and food service activities | E17: =LEFT(D17,1) -> I
B18: 0.028210912 | C18: 0.021640393 | D18: S-Other service activities | E18: =LEFT(D18,1) -> S
B19: 0.018818171 | C19: 0.019016856 | D19: L-Real estate activities | E19: =LEFT(D19,1) -> L
B20: 0.022991512 | C20: 0.013231425 | D20: B-Mining and quarrying | E20: =LEFT(D20,1) -> B
B21: 0.0096106698 | C21: 0.0097813971 | D21: R-Arts, entertainment and recreation | E21: =LEFT(D21,1) -> R
B22: 0.0062109771 | C22: 0.0057323537 | D22: O-Public administration and defence; compulsory social security | E22: =LEFT(D22,1) -> O
B23: 0.0047508526 | C23: 0.0037533268 | D23: D-Electricity, gas, steam and air conditioning supply | E23: =LEFT(D23,1) -> D
B24: 0.0037810685 | C24: 0.0032907956 | D24: E-Water supply; sewerage, waste management and remediation activities | E24: =LEFT(D24,1) -> E
B25: 0.003454175 | C25: 0.0020851816 | D25: A-Agriculture, forestry and fishing | E25: =LEFT(D25,1) -> A
B26: 1 | C26: 1 | D26: Totals
B29: Sorted
B31: 2023 | C31: 2024 | D31: Economic Activities
A32: A | B32: =OFFSET(B$5,MATCH($A32,$E$6:$E$25,0),0) -> 0.003454175 | C32: =OFFSET(C$5,MATCH($A32,$E$6:$E$25,0),0) -> 0.0020851816 | D32: =OFFSET(D$5,MATCH($A32,$E$6:$E$25,0),0) -> A-Agriculture, forestry and fishing
A33: B | B33: =OFFSET(B$5,MATCH($A33,$E$6:$E$25,0),0) -> 0.022991512 | C33: =OFFSET(C$5,MATCH($A33,$E$6:$E$25,0),0) -> 0.013231425 | D33: =OFFSET(D$5,MATCH($A33,$E$6:$E$25,0),0) -> B-Mining and quarrying
A34: C | B34: =OFFSET(B$5,MATCH($A34,$E$6:$E$25,0),0) -> 0.060943851 | C34: =OFFSET(C$5,MATCH($A34,$E$6:$E$25,0),0) -> 0.071874313 | D34: =OFFSET(D$5,MATCH($A34,$E$6:$E$25,0),0) -> C-Manufacturing
A35: D | B35: =OFFSET(B$5,MATCH($A35,$E$6:$E$25,0),0) -> 0.0047508526 | C35: =OFFSET(C$5,MATCH($A35,$E$6:$E$25,0),0) -> 0.0037533268 | D35: =OFFSET(D$5,MATCH($A35,$E$6:$E$25,0),0) -> D-Electricity, gas, steam and air conditioning supply
A36: E | B36: =OFFSET(B$5,MATCH($A36,$E$6:$E$25,0),0) -> 0.0037810685 | C36: =OFFSET(C$5,MATCH($A36,$E$6:$E$25,0),0) -> 0.0032907956 | D36: =OFFSET(D$5,MATCH($A36,$E$6:$E$25,0),0) -> E-Water supply; sewerage, waste management and remediation activities
A37: F | B37: =OFFSET(B$5,MATCH($A37,$E$6:$E$25,0),0) -> 0.13465834 | C37: =OFFSET(C$5,MATCH($A37,$E$6:$E$25,0),0) -> 0.15341629 | D37: =OFFSET(D$5,MATCH($A37,$E$6:$E$25,0),0) -> F-Construction
A38: G | B38: =OFFSET(B$5,MATCH($A38,$E$6:$E$25,0),0) -> 0.13340525 | C38: =OFFSET(C$5,MATCH($A38,$E$6:$E$25,0),0) -> 0.14121608 | D38: =OFFSET(D$5,MATCH($A38,$E$6:$E$25,0),0) -> G-Wholesale and retail trade; repair of motor vehicles and motorcycles
A39: H | B39: =OFFSET(B$5,MATCH($A39,$E$6:$E$25,0),0) -> 0.05661796 | C39: =OFFSET(C$5,MATCH($A39,$E$6:$E$25,0),0) -> 0.054085818 | D39: =OFFSET(D$5,MATCH($A39,$E$6:$E$25,0),0) -> H-Transportation and storage
A40: I | B40: =OFFSET(B$5,MATCH($A40,$E$6:$E$25,0),0) -> 0.020746843 | C40: =OFFSET(C$5,MATCH($A40,$E$6:$E$25,0),0) -> 0.02364975 | D40: =OFFSET(D$5,MATCH($A40,$E$6:$E$25,0),0) -> I-Accommodation and food service activities
A41: J | B41: =OFFSET(B$5,MATCH($A41,$E$6:$E$25,0),0) -> 0.02440805 | C41: =OFFSET(C$5,MATCH($A41,$E$6:$E$25,0),0) -> 0.024900859 | D41: =OFFSET(D$5,MATCH($A41,$E$6:$E$25,0),0) -> J-Information and communication
A42: K | B42: =OFFSET(B$5,MATCH($A42,$E$6:$E$25,0),0) -> 0.17987861 | C42: =OFFSET(C$5,MATCH($A42,$E$6:$E$25,0),0) -> 0.14664513 | D42: =OFFSET(D$5,MATCH($A42,$E$6:$E$25,0),0) -> K-Financial and insurance activities
A43: L | B43: =OFFSET(B$5,MATCH($A43,$E$6:$E$25,0),0) -> 0.018818171 | C43: =OFFSET(C$5,MATCH($A43,$E$6:$E$25,0),0) -> 0.019016856 | D43: =OFFSET(D$5,MATCH($A43,$E$6:$E$25,0),0) -> L-Real estate activities
... A50: S | B50: =OFFSET(B$5,MATCH($A50,$E$6:$E$25,0),0) -> 0.028210912 | C50: =OFFSET(C$5,MATCH($A50,$E$6:$E$25,0),0) -> 0.021640393 | D50: =OFFSET(D$5,MATCH($A50,$E$6:$E$25,0),0) -> S-Other service activities
B52: Sorted, other reallocated
B54: 2023 | C54: 2024 | D54: Economic Activities
A55: A | B55: =B32/SUM(B$32:B$50) -> 0.003274286 | C55: =C32/SUM(C$32:C$50) -> 0.0019815964 | D55: =D32 -> A-Agriculture, forestry and fishing
A56: B | B56: =B33/SUM(B$32:B$50) -> 0.021794143 | C56: =C33/SUM(C$32:C$50) -> 0.01257413 | D56: =D33 -> B-Mining and quarrying
A57: C | B57: =B34/SUM(B$32:B$50) -> 0.057769974 | C57: =C34/SUM(C$32:C$50) -> 0.068303826 | D57: =D34 -> C-Manufacturing
A58: D | B58: =B35/SUM(B$32:B$50) -> 0.0045034344 | C58: =C35/SUM(C$32:C$50) -> 0.0035668735 | D58: =D35 -> D-Electricity, gas, steam and air conditioning supply
A59: E | B59: =B36/SUM(B$32:B$50) -> 0.0035841553 | C59: =C36/SUM(C$32:C$50) -> 0.0031273194 | D59: =D36 -> E-Water supply; sewerage, waste management and remediation activities
A60: F | B60: =B37/SUM(B$32:B$50) -> 0.12764551 | C60: =C37/SUM(C$32:C$50) -> 0.14579505 | D60: =D37 -> F-Construction
A61: G | B61: =B38/SUM(B$32:B$50) -> 0.12645768 | C61: =C38/SUM(C$32:C$50) -> 0.13420091 | D61: =D38 -> G-Wholesale and retail trade; repair of motor vehicles and motorcycles
A62: H | B62: =B39/SUM(B$32:B$50) -> 0.053669369 | C62: =C39/SUM(C$32:C$50) -> 0.051399007 | D62: =D39 -> H-Transportation and storage
A63: I | B63: =B40/SUM(B$32:B$50) -> 0.019666374 | C63: =C40/SUM(C$32:C$50) -> 0.022474906 | D63: =D40 -> I-Accommodation and food service activities
A64: J | B64: =B41/SUM(B$32:B$50) -> 0.023136911 | C64: =C41/SUM(C$32:C$50) -> 0.023663864 | D64: =D41 -> J-Information and communication
A65: K | B65: =B42/SUM(B$32:B$50) -> 0.17051077 | C65: =C42/SUM(C$32:C$50) -> 0.13936027 | D65: =D42 -> K-Financial and insurance activities
A66: L | B66: =B43/SUM(B$32:B$50) -> 0.017838145 | C66: =C43/SUM(C$32:C$50) -> 0.018072159 | D66: =D43 -> L-Real estate activities
... A73: S | B73: =B50/SUM(B$32:B$50) -> 0.026741724 | C73: =C50/SUM(C$32:C$50) -> 0.020565367 | D73: =D50 -> S-Other service activities
A75: Check | B75: =1-SUM(B55:B73) -> 0 | C75: =1-SUM(C55:C73) -> 0
B77: Mapping to SAM categories
D81: Code | E81: Value of labour | F81: Distribution of value in category | G81: Emirati employment distribution
B82: Agriculture, hunting, forestry, and fishing | C82: Agriculture, forestry and fishing | D82: A | E82: {=TRANSPOSE('2022 SAM'!C70:AI70)} -> 233 | F82: =E82/SUMIFS($E$82:$E$114,$D$82:$D$114,D82) -> 1 | G82: =VLOOKUP(D82,$A$55:$C$73,3,FALSE)*F82 -> 0.0019815964
B83: Mining and quarrying | C83: Mining and quarrying | D83: B | E83: 1238 | F83: =E83/SUMIFS($E$82:$E$114,$D$82:$D$114,D83) -> 1 | G83: =VLOOKUP(D83,$A$55:$C$73,3,FALSE)*F83 -> 0.01257413
B84: Food, beverages, and tobacco | C84: Manufacturing | D84: C | E84: 2676.288 | F84: =E84/SUMIFS($E$82:$E$114,$D$82:$D$114,D84) -> 0.14093084 | G84: =VLOOKUP(D84,$A$55:$C$73,3,FALSE)*F84 -> 0.0096261153
B85: Textiles and textile products | C85: Manufacturing | D85: C | E85: 837.922 | F85: =E85/SUMIFS($E$82:$E$114,$D$82:$D$114,D85) -> 0.044124193 | G85: =VLOOKUP(D85,$A$55:$C$73,3,FALSE)*F85 -> 0.0030138512
B86: Leather, leather products, and footwear | C86: Manufacturing | D86: C | E86: 7.471 | F86: =E86/SUMIFS($E$82:$E$114,$D$82:$D$114,D86) -> 0.00039341591 | G86: =VLOOKUP(D86,$A$55:$C$73,3,FALSE)*F86 -> 2.6871812e-05
B87: Wood and products of wood and cork | C87: Manufacturing | D87: C | E87: 631.169 | F87: =E87/SUMIFS($E$82:$E$114,$D$82:$D$114,D87) -> 0.033236772 | G87: =VLOOKUP(D87,$A$55:$C$73,3,FALSE)*F87 -> 0.0022701987
B88: Pulp, paper, paper products, printing, and publishing | C88: Manufacturing | D88: C | E88: 1294.858 | F88: =E88/SUMIFS($E$82:$E$114,$D$82:$D$114,D88) -> 0.068186018 | G88: =VLOOKUP(D88,$A$55:$C$73,3,FALSE)*F88 -> 0.0046573659
B89: Coke, refined petroleum, and nuclear fuel | C89: Manufacturing | D89: C | E89: 258.901 | F89: =E89/SUMIFS($E$82:$E$114,$D$82:$D$114,D89) -> 0.013633486 | G89: =VLOOKUP(D89,$A$55:$C$73,3,FALSE)*F89 -> 0.00093121924
B90: Chemicals and chemical products | C90: Manufacturing | D90: C | E90: 1556.737 | F90: =E90/SUMIFS($E$82:$E$114,$D$82:$D$114,D90) -> 0.081976322 | G90: =VLOOKUP(D90,$A$55:$C$73,3,FALSE)*F90 -> 0.0055992964
B91: Rubber and plastics | C91: Manufacturing | D91: C | E91: 703.23 | F91: =E91/SUMIFS($E$82:$E$114,$D$82:$D$114,D91) -> 0.037031438 | G91: =VLOOKUP(D91,$A$55:$C$73,3,FALSE)*F91 -> 0.0025293889
B92: Other nonmetallic minerals | C92: Manufacturing | D92: C | E92: 1703.936 | F92: =E92/SUMIFS($E$82:$E$114,$D$82:$D$114,D92) -> 0.089727685 | G92: =VLOOKUP(D92,$A$55:$C$73,3,FALSE)*F92 -> 0.0061287441
B93: Basic metals and fabricated metal | C93: Manufacturing | D93: C | E93: 4050.425 | F93: =E93/SUMIFS($E$82:$E$114,$D$82:$D$114,D93) -> 0.21329161 | G93: =VLOOKUP(D93,$A$55:$C$73,3,FALSE)*F93 -> 0.014568633
B94: Machinery, nec | C94: Manufacturing | D94: C | E94: 1322.063 | F94: =E94/SUMIFS($E$82:$E$114,$D$82:$D$114,D94) -> 0.069618608 | G94: =VLOOKUP(D94,$A$55:$C$73,3,FALSE)*F94 -> 0.0047552172
